Workbook

Sheet Price List
A2: Manufactur | B2: Part # | C2: QTL Cost With MHSW | D2: MHSW | E2: QTL Cost Without MHSW | F2: List Price | G2: Baldwin | H2: Donaldson | I2: Fleetguard
A3: Air Filter | B3: 03-36867-010 | C3: 345 | D3: 355 in np | K3: Counter | L3: Counter | M3: Void | N3: Void
A4: Air Filter | B4: 03-42776-010 | C4: 115 | K4: 1----10 | L4: 7 | M4: 1---20 | N4: 5
A5: Air Filter | B5: 03-43216-010 | C5: 165.31 | K5: 10---15 | L5: 8 | M5: 20---35 | N5: 10
A6: Air Filter | B6: 21715813 | C6: 114.08 | K6: 15---20 | L6: 9 | M6: 35---50 | N6: 15
A7: Air Filter | B7: 23883251 | C7: 301.78
A8: Air Filter | B8: 2515573C1 | C8: 181.62 | K8: 20---25 | L8: 10 | M8: 50---70 | N8: 20
A9: Air Filter | B9: 2599273C92 | C9: 591.98 | K9: 25---30 | L9: 11 | M9: 70---90 | N9: 25
A10: Air Filter | B10: 4329012482 | C10: 95.69 | D10: 84.97 in np
A11: Air Filter | B11: 950011-G3 | C11: 22.52 | K11: 30---35 | L11: 12 | M11: 90---110 | N11: 30
A12: Air Filter | B12: AC1001 | C12: 70.95 | D12: 52.99 in np | K12: 35---40 | L12: 13
A13: Air Filter | B13: AD27747 | C13: =D13+E13 -> 45.7696 | E13: =F13*0.32 -> 45.7696 | F13: 143.03
A14: Air Filter | B14: AD27750 | C14: =D14+E14 -> 46.256 | E14: =F14*0.32 -> 46.256 | F14: 144.55
A15: Air Filter | B15: AF1651 | C15: 6.49
A16: Air Filter | B16: AF25139M | C16: =D16+E16 -> 55.4176 | E16: =F16*0.32 -> 55.4176 | F16: 173.18
A17: Air Filter | B17: AF25550 | C17: =D17+E17 -> 13.2896 | E17: =F17*0.32 -> 13.2896 | F17: 41.53 | K17: 40---45 | L17: 14
A18: Air Filter | B18: AF25707 | C18: =D18+E18 -> 54.2304 | E18: =F18*0.32 -> 54.2304 | F18: 169.47 | K18: 45---50 | L18: 15
A19: Air Filter | B19: AF25732 | C19: =D19+E19 -> 49.8368 | E19: =F19*0.32 -> 49.8368 | F19: 155.74 | K19: 50---60 | L19: 16
A20: Air Filter | B20: AF26163M | C20: =D20+E20 -> 59.776 | E20: =F20*0.32 -> 59.776 | F20: 186.8
A21: Air Filter | B21: AF26268 | C21: =D21+E21 -> 44.6304 | E21: =F21*0.32 -> 44.6304 | F21: 139.47 | K21: 60---70 | L21: 17
A22: Air Filter | B22: AF26403 | C22: =D22+E22 -> 24.2272 | E22: =F22*0.32 -> 24.2272 | F22: 75.71 | K22: 70---80 | L22: 18
A23: Air Filter | B23: AF27690 | C23: =D23+E23 -> 47.7952 | E23: =F23*0.32 -> 47.7952 | F23: 149.36 | K23: 80---90 | L23: 19
A24: Air Filter | B24: AF27693 | C24: =D24+E24 -> 31.3312 | E24: =F24*0.32 -> 31.3312 | F24: 97.91 | K24: 90---100 | L24: 20
A25: Air Filter | B25: AF27905 | C25: =D25+E25 -> 47.136 | E25: =F25*0.32 -> 47.136 | F25: 147.3 | K25: 100--110 | L25: 21
A26: Air Filter | B26: AF27906 | C26: =D26+E26 -> 9.664 | E26: =F26*0.32 -> 9.664 | F26: 30.2 | K26: 110--120 | L26: 22
A27: Air Filter | B27: AF4878 | C27: =D27+E27 -> 28.544 | E27: =F27*0.32 -> 28.544 | F27: 89.2 | K27: 120--130 | L27: 23
A28: Air Filter | B28: AF890 | C28: =D28+E28 -> 69.296 | E28: =F28*0.32 -> 69.296 | F28: 216.55
A29: Air Filter | B29: AH8501 | C29: =D29+E29 -> 143.3376 | E29: =F29*0.32 -> 143.3376 | F29: 447.93
A30: Air Filter | B30: CA30132 | C30: 100.45 | H30: P648156 / P634517
A31: Air Filter | B31: CA4700 | C31: 35.14 | H31: P607955
A32: Air Filter | B32: CA5368 | C32: 54.38 | H32: P607965
A33: Air Filter | B33: CA5500 | C33: 85.87 | H33: P616056
A34: Air Filter | B34: CA5790 | C34: 73.96 | H34: P618478
A35: Air Filter | B35: D37-1061 | C35: 327.43 | K35: D37-1032 | L35: New
A36: Air Filter | B36: ME073821 | C36: 74.4
A37: Air Filter | B37: P129396 | C37: 78.9
A38: Air Filter | B38: P141317 | C38: 67.12 | G38: PA2703
A39: Air Filter | B39: P150695 | C39: 70.13 | G39: PA2680
A40: Air Filter | B40: P151097 | C40: 73.76 | G40: PA3951
A41: Air Filter | B41: P153551 | C41: 52.82 | G41: PA2705
A42: Air Filter | B42: P154927 | C42: 93.7
A43: Air Filter | B43: P181009 | C43: 60.14 | G43: PA2357
A44: Air Filter | B44: P181016 | C44: 64.63 | G44: PA2493
A45: Air Filter | B45: P181028 | C45: 40.4 | G45: PA2521
A46: Air Filter | B46: P181041 | C46: 50.26
A47: Air Filter | B47: P181186 | C47: 89.66
A48: Air Filter | B48: P181189 | C48: 78.64 | G48: PA2642
A49: Air Filter | B49: P521598 | C49: 74.39
A50: Air Filter | B50: P522293 | C50: 71.11 | G50: PA2732
A51: Air Filter | B51: P527682 | C51: 53.55 | G51: RS3518
A52: Air Filter | B52: P532966 | C52: 35.72 | G52: RS3517
A53: Air Filter | B53: P533235 | C53: 51.88 | G53: RS3530
A54: Air Filter | B54: P533814 | C54: 69.9
A55: Air Filter | B55: P533930 | C55: 42.47 | G55: RS3548
A56: Air Filter | B56: P533938 | C56: 78.65 | G56: RS3738
A57: Air Filter | B57: P534096 | C57: 60.2 | G57: RS3516
A58: Air Filter | B58: P534816 | C58: 59.62 | G58: RS3539
A59: Air Filter | B59: P534925 | C59: 73.63 | G59: RS3534
A60: Air Filter | B60: P539765 | C60: 63.15 | G60: RS3743
A61: Air Filter | B61: P540388 | C61: 52.06 | G61: RS3740
A62: Air Filter | B62: P544243 | C62: 64.01
A63: Air Filter | B63: P549644 | C63: 51.08 | G63: RS3750
A64: Air Filter | B64: P600676 | C64: 59.89 | G64: RS3936
A65: Air Filter | B65: P606503 | C65: 51.2 | G65: RS4636
A66: Air Filter | B66: P606720 | C66: 57.98 | G66: RS4642
A67: Air Filter | B67: P607955 | C67: 54.51
A68: Air Filter | B68: P607965 | C68: 81.64
A69: Air Filter | B69: P610260 | C69: 58.75
A70: Air Filter | B70: P611696 | C70: 252.6
A71: Air Filter | B71: P613336 | C71: 59.2 | G71: RS4862
A72: Air Filter | B72: P614556 | C72: 64.84
A73: Air Filter | B73: P614986 | C73: 209.28
A74: Air Filter | B74: P616056 | C74: 132.5
A75: Air Filter | B75: P618478 | C75: 58.61
A76: Air Filter | B76: P619498 | C76: 138.98
A77: Air Filter | B77: P621725 | C77: 193.59
A78: Air Filter | B78: P625128 | C78: 84.98 | G78: RS5287XP / X011622
A79: Air Filter | B79: P625287 | C79: 69.67 | G79: RS5288XP
A80: Air Filter | B80: P634517 | C80: 103.12
A81: Air Filter | B81: P637453 | C81: 99.72
A82: Air Filter | B82: P637454 | C82: 102.97
A83: Air Filter | B83: P640017 | C83: 243.38
A84: Air Filter | B84: P644827 | C84: 103.42
A85: Air Filter | B85: P645114 | C85: 54.48 | G85: RS4634
A86: Air Filter | B86: P648156 | C86: 107.56
A87: Air Filter | B87: P780622 | C87: 70.74
A88: Air Filter | B88: PA2333 | C88: 33.44 | H88: P181099 / P182099
A89: Air Filter | B89: PA2357 | C89: 60.05
A90: Air Filter | B90: PA2493 | C90: 59.95
A91: Air Filter | B91: PA2521 | C91: 38.83 | H91: P181028
A92: Air Filter | B92: PA2525 | C92: 32.14 | H92: P181015
A93: Air Filter | B93: PA2608 | C93: 54.15
A94: Air Filter | B94: PA2642 | C94: 74.55 | H94: P181189
A95: Air Filter | B95: PA2680 | C95: 68.44 | H95: PP150695
A96: Air Filter | B96: PA2703 | C96: 61.5 | H96: P141317
A97: Air Filter | B97: PA2705 | C97: 49.81 | H97: P153551
A98: Air Filter | B98: PA2732 | C98: 68.44 | H98: P522993
A99: Air Filter | B99: PA2789 | C99: 38.84 | H99: P522926
A100: Air Filter | B100: PA3951 | C100: 70.62 | H100: P151097
A101: Air Filter | B101: PA5306 | C101: 11.41 | H101: P614222
...

Sheet Cost Source
A1: Cost Source | G1: Without Service | S1: With Service
A2: Manufactur | B2: Part # | C2: Type | D2: Spinner | E2: Fuel Filter | F2: Fuel Separator | G2: Oil Filter | H2: Coolant Filter | I2: Air Filter | J2: Cabin Filter | K2: CV Filter | L2: Other | M2: DEF Filter | N2: Over Counter | O2: Labour | P2: Void Price | Q2: Spinner | R2: Fuel Filter | S2: Fuel Separator | T2: Oil Filter | U2: Coolant Filter | V2: Air Filter | W2: Cabin Filter | X2: CV Filter | Y2: Other | Z2: DEF Filter
A3: Air Filter | B3: 03-36867-010 | C3: Air Filter | I3: =V3 -> 55 | N3: 0 | O3: 10 | V3: 55
A4: Air Filter | B4: 03-42776-010 | C4: Air Filter | I4: =V4 -> 55 | N4: 0 | O4: 10 | V4: 55
A5: Air Filter | B5: 03-43216-010 | C5: Air Filter | I5: =V5 -> 55 | N5: 0 | O5: 10 | V5: 55
A6: Air Filter | B6: 21715813 | C6: Air Filter | I6: =V6 -> 30 | N6: 0 | O6: 0 | V6: 30
A7: Air Filter | B7: 23883251 | C7: Air Filter | I7: =V7 -> 58 | V7: 58
A8: Air Filter | B8: 2515573C1 | C8: Air Filter | I8: =V8 -> 50 | N8: 0 | V8: 50
A9: Air Filter | B9: 2599273C92 | C9: Air Filter | I9: =V9 -> 70 | N9: 0 | V9: 70
A10: Air Filter | B10: 4329012482 | C10: Air Dryer Filter ( Webco ) | I10: =V10 -> 30 | N10: 20 | O10: 10 | V10: 30
A11: Air Filter | B11: 950011-G3 | C11: Air Filter | I11: =V11 -> 27 | N11: 0 | V11: 27
A12: Air Filter | B12: AC1001 | C12: Air Dryer Filter( TRP ) | I12: =V12 -> 25 | N12: 15 | O12: 10 | V12: 25
A13: Air Filter | B13: AD27747 | C13: Air Dryer Filter | I13: =V13 -> 30 | N13: 15 | O13: 10 | V13: 30
A14: Air Filter | B14: AD27750 | C14: Air Dryer Filter | I14: =V14 -> 30 | N14: 15 | O14: 10 | V14: 30
A15: Air Filter | B15: AF1651 | C15: Compressor Air Filter | N15: 8
A16: Air Filter | B16: AF25139M | C16: Air Filter | I16: =V16 -> 30 | V16: 30
A17: Air Filter | B17: AF25550 | C17: Air Filter | I17: =V17 -> 20 | N17: 0 | V17: 20
A18: Air Filter | B18: AF25707 | C18: Air Filter | I18: =V18 -> 30 | N18: 0 | V18: 30
A19: Air Filter | B19: AF25732 | C19: Air Filter | I19: =V19 -> 36 | N19: 0 | V19: 36
A20: Air Filter | B20: AF26163M | C20: Air Filter | I20: =V20 -> 30 | V20: 30
A21: Air Filter | B21: AF26268 | C21: Air Filter | I21: =V21 -> 25 | N21: 0 | V21: 25
A22: Air Filter | B22: AF26403 | C22: Air Filter | I22: =V22 -> 22 | N22: 0 | V22: 22
A23: Air Filter | B23: AF27690 | C23: Air Filter | I23: =V23 -> 30 | N23: 0 | V23: 30
A24: Air Filter | B24: AF27693 | C24: Air Filter | I24: =V24 -> 38 | N24: 0 | V24: 38
A25: Air Filter | B25: AF27905 | C25: Air Filter | I25: =V25 -> 56 | N25: 0 | V25: 56
A26: Air Filter | B26: AF27906 | C26: Air Filter | I26: =V26 -> 25 | N26: 0 | V26: 25
A27: Air Filter | B27: AF4878 | C27: Air Filter | I27: =V27 -> 32 | N27: 0 | V27: 32
A28: Air Filter | B28: AF890 | C28: Air Filter | I28: =V28 -> 35 | N28: 0 | V28: 35
A29: Air Filter | B29: AH8501 | C29: Air Filter | I29: =V29 -> 35 | N29: 0 | V29: 35
A30: Air Filter | B30: CA30132 | C30: Air Filter | I30: =V30 -> 48 | N30: 0 | V30: 48
A31: Air Filter | B31: CA4700 | C31: Air Filter | I31: =V31 -> 29 | N31: 0 | V31: 29
A32: Air Filter | B32: CA5368 | C32: Air Filter | I32: =V32 -> 31 | N32: 0 | V32: 31
... A61: Air Filter | B61: P540388 | C61: Air Filter | I61: =V61 -> 30 | N61: 0 | V61: 30
A62: Air Filter | B62: P544243 | C62: Air Filter | I62: 39
A63: Air Filter | B63: P549644 | C63: Air Filter | I63: =V63 -> 40 | N63: 0 | V63: 40
A64: Air Filter | B64: P600676 | C64: Air Filter | I64: =V64 -> 30 | N64: 0 | V64: 30
A65: Air Filter | B65: P606503 | C65: Air Filter | I65: =V65 -> 42 | N65: 0 | V65: 42
A66: Air Filter | B66: P606720 | C66: Air Filter | I66: =V66 -> 30 | N66: 0 | V66: 30
A67: Air Filter | B67: P607955 | C67: Air Filter | I67: =V67 -> 32 | N67: 0 | V67: 32
A68: Air Filter | B68: P607965 | C68: Air Filter | I68: =V68 -> 32 | N68: 0 | V68: 32
A69: Air Filter | B69: P610260 | C69: Air Filter | I69: =V69 -> 36 | N69: 0 | V69: 36
A70: Air Filter | B70: P611696 | C70: Air Filter | I70: =V70 -> 35 | N70: 0 | V70: 35
A71: Air Filter | B71: P613336 | C71: Air Filter | I71: =V71 -> 35 | N71: 0 | V71: 35
A72: Air Filter | B72: P614556 | C72: Air Filter | I72: =V72 -> 65 | N72: 0 | V72: 65
A73: Air Filter | B73: P614986 | C73: Air Filter | I73: =V73 -> 45 | N73: 0 | V73: 45
A74: Air Filter | B74: P616056 | C74: Air Filter | I74: =V74 -> 35 | N74: 0 | V74: 35
... A83: Air Filter | B83: P640017 | C83: Air Filter | I83: =V83 -> 70 | N83: 0 | V83: 70
A84: Air Filter | B84: P644827 | C84: Air Filter | I84: 50
A85: Air Filter | B85: P645114 | C85: Air Filter | I85: =V85 -> 35 | N85: 0 | V85: 35
A86: Air Filter | B86: P648156 | C86: Air Filter | I86: =V86 -> 70 | V86: 70
A87: Air Filter | B87: P780622 | C87: Air Filter | I87: =V87 -> 30 | N87: 0 | V87: 30
A88: Air Filter | B88: PA2333 | C88: Air Filter | I88: =V88 -> 36 | N88: 0 | V88: 36
A89: Air Filter | B89: PA2357 | C89: Air Filter | I89: =V89 -> 37 | N89: 0 | V89: 37
A90: Air Filter | B90: PA2493 | C90: Air Filter | I90: =V90 -> 39 | N90: 0 | V90: 39
A91: Air Filter | B91: PA2521 | C91: Air Filter | I91: =V91 -> 30 | N91: 0 | V91: 30
A92: Air Filter | B92: PA2525 | C92: Air Filter | I92: =V92 -> 37 | N92: 0 | V92: 37
A93: Air Filter | B93: PA2608 | C93: Air Filter | I93: =V93 -> 25 | N93: 0 | V93: 25
A94: Air Filter | B94: PA2642 | C94: Air Filter | I94: =V94 -> 30 | N94: 0 | V94: 30
A95: Air Filter | B95: PA2680 | C95: Air Filter | I95: =V95 -> 30 | N95: 0 | V95: 30
A96: Air Filter | B96: PA2703 | C96: Air Filter | I96: =V96 -> 34 | N96: 0 | V96: 34
A97: Air Filter | B97: PA2705 | C97: Air Filter | I97: =V97 -> 27 | N97: 0 | V97: 27
A98: Air Filter | B98: PA2732 | C98: Air Filter | I98: =V98 -> 27 | N98: 0 | V98: 27
... A122: Air Filter | B122: X011622 | C122: Air Filter | I122: =V122 -> 75 | N122: 0 | V122: 75
A123: Alliance | B123: N122 HBK4884 | C123: Fuel Separator Glass | F123: =S123 -> 15 | N123: 15 | O123: 8 | S123: 15
A124: Alliance | B124: N122 R50418 | C124: Fuel Separator | F124: =S124 -> 15 | N124: 11 | O124: 10 | S124: 15
A125: Alliance | B125: N122 R50422 | C125: Fuel Separator | F125: =S125 -> 15 | N125: 12 | O125: 10 | S125: 15
A126: Alliance | B126: N122 R50423 | C126: Fuel Separator | F126: =S126 -> 15 | N126: 11 | O126: 10 | S126: 15
A127: Alliance | B127: N122 R50550 | C127: Fuel Separator | F127: =S127 -> 15 | N127: 11 | O127: 10 | S127: 15
A128: Alliance | B128: N122 R50551 | C128: Fuel Separator | F128: =S128 -> 15 | N128: 11 | O128: 10 | S128: 15
A129: Alliance | B129: RK 21527 | C129: Fuel Separator Glass | F129: =S129 -> 10 | N129: 14 | O129: 8 | S129: 10
B130: 84311 | C130: Oil Filter | G130: 20
B131: 84312 | C131: Oil Filter | G131: 20
A132: Baldwin | B132: B495 | C132: Oil Filter | G132: 20 | N132: 8 | O132: 10 | P132: -5
A133: Baldwin | B133: BF1259 | C133: Fuel Filter | F133: =S133 -> 15 | N133: 9 | O133: 10 | S133: 15
B134: BF1330SP
A135: Baldwin | B135: BF1339SP | C135: Fuel Separator | F135: =S135 -> 15 | N135: 9 | O135: 10 | S135: 15
A136: Baldwin | B136: BF1348SP | C136: Fuel Separator | F136: =S136 -> 15 | N136: 9 | O136: 10 | S136: 15
B137: BF1355SP | F137: =S137 -> 15 | N137: 14 | O137: 15 | S137: 15
A138: Baldwin | B138: B40150
B139: CF194206
B140: 22-46891 | C140: Cabin Air Filter | J140: =W140 -> 20 | N140: 20 | W140: 20
B141: 23-15619
A142: Cab Filter | B142: 23567793 | C142: Cabin Air Filter | J142: =W142 -> 30 | N142: =W142 -> 30 | W142: 30
A143: Cab Filter | B143: 23582260 | C143: Cabin Air Filter | J143: =W143 -> 10 | N143: =W143 -> 10 | W143: 10
A144: Cab Filter | B144: AF26235 | C144: Cabin Air Filter | J144: =W144 -> 10 | N144: =W144 -> 10 | W144: 10
A145: Cab Filter | B145: AF26405 | C145: Cabin Air Filter | J145: =W145 -> 12 | N145: =W145 -> 12 | W145: 12
A146: Cab Filter | B146: AF26418 | C146: Cabin Air Filter | J146: =W146 -> 10 | N146: =W146 -> 10 | W146: 10
A147: Cab Filter | B147: AF26427 | C147: Cabin Air Filter | J147: =W147 -> 11 | N147: =W147 -> 11 | W147: 11
A148: Cab Filter | B148: AF26430 | C148: Cabin Air Filter | J148: =W148 -> 10 | N148: =W148 -> 10 | W148: 10
A149: Cab Filter | B149: AF26435 | C149: Cabin Air Filter | J149: =W149 -> 10 | N149: =W149 -> 10 | W149: 10
A150: Cab Filter | B150: AF26442 | C150: Cabin Air Filter | J150: =W150 -> 11 | N150: =W150 -> 11 | W150: 11
A151: Cab Filter | B151: AF26449 | C151: Cabin Air Filter | J151: =W151 -> 11 | N151: =W151 -> 11 | W151: 11
A152: Cab Filter | B152: AF27958 | C152: Cabin Air Filter | J152: =W152 -> 12 | N152: =W152 -> 12 | W152: 12
A153: Cab Filter | B153: AF55831 | C153: Cabin Air Filter | J153: =W153 -> 13 | N153: =W153 -> 13 | W153: 13
A154: Cab Filter | B154: AF55832 | C154: Cabin Air Filter | J154: =W154 -> 13 | N154: =W154 -> 13 | W154: 13
A155: Cab Filter | B155: AF55836 | C155: Cabin Air Filter | J155: =W155 -> 15 | N155: =W155 -> 15 | W155: 15
... A168: Cab Filter | B168: SR2000092 | C168: Cabin Air Filter | J168: =W168 -> 20 | N168: =W168 -> 20 | W168: 20
A169: Cat | B169: 1183619 | C169: Pan Plug | N169: 11 | O169: 10
A170: Cat | B170: 1210145 | C170: Pan Plug ORing | N170: 5
A171: Cat | B171: 1752949 | C171: Fuel Separator | F171: =S171 -> 6 | N171: 13 | O171: 20 | S171: 6
...

Sheet All Filter Sell Price
A1: Jan 1,2026
A2: Manufactur | B2: Part # | C2: Without Service Price | D2: Without Service Price | E2: With Service Price | F2: With Service Price | G2: Over Counter Price | H2: Over Counter Price | I2: Void Price | J2: Customer Supplies Filter
A3: Air Filter | B3: 03-36867-010 | C3: ='Price List'!C3+'Cost Source'!I3+'Cost Source'!O3 -> 410 | D3: =ROUNDUP(C3,0)-0.01 -> 409.99 | E3: ='Price List'!C3+'Cost Source'!V3 -> 400 | F3: =ROUNDUP(E3,0)-0.01 -> 399.99 | G3: =E3+'Cost Source'!N3 -> 400 | H3: =ROUNDUP(G3,0)-0.01 -> 399.99 | J3: 20
A4: Air Filter | B4: 03-42776-010 | C4: ='Price List'!C4+'Cost Source'!I4+'Cost Source'!O4 -> 180 | D4: =ROUNDUP(C4,0)-0.01 -> 179.99 | E4: ='Price List'!C4+'Cost Source'!V4 -> 170 | F4: =ROUNDUP(E4,0)-0.01 -> 169.99 | G4: =E4+'Cost Source'!N4 -> 170 | H4: =ROUNDUP(G4,0)-0.01 -> 169.99 | J4: 20
A5: Air Filter | B5: 03-43216-010 | C5: ='Price List'!C5+'Cost Source'!I5+'Cost Source'!O5 -> 230.31 | D5: =ROUNDUP(C5,0)-0.01 -> 230.99 | E5: ='Price List'!C5+'Cost Source'!V5 -> 220.31 | F5: =ROUNDUP(E5,0)-0.01 -> 220.99 | G5: =E5+'Cost Source'!N5 -> 220.31 | H5: =ROUNDUP(G5,0)-0.01 -> 220.99 | J5: 20
A6: Air Filter | B6: 21715813 | C6: ='Price List'!C6+'Cost Source'!I6+'Cost Source'!O6 -> 144.08 | D6: =ROUNDUP(C6,0)-0.01 -> 144.99 | E6: ='Price List'!C6+'Cost Source'!V6 -> 144.08 | F6: =ROUNDUP(E6,0)-0.01 -> 144.99 | G6: =E6+'Cost Source'!N6 -> 144.08 | H6: =ROUNDUP(G6,0)-0.01 -> 144.99 | J6: 10
A7: Air Filter | B7: 23883251 | C7: ='Price List'!C7+'Cost Source'!I7+'Cost Source'!O7 -> 359.78 | D7: =ROUNDUP(C7,0)-0.01 -> 359.99 | E7: ='Price List'!C7+'Cost Source'!V7 -> 359.78 | F7: =ROUNDUP(E7,0)-0.01 -> 359.99 | G7: ='Price List'!C7+'Cost Source'!V7 -> 359.78 | H7: =ROUNDUP(G7,0)-0.01 -> 359.99 | J7: 20
A8: Air Filter | B8: 2515573C1 | C8: ='Price List'!C8+'Cost Source'!I8+'Cost Source'!O8 -> 231.62 | D8: =ROUNDUP(C8,0)-0.01 -> 231.99 | E8: ='Price List'!C8+'Cost Source'!V8 -> 231.62 | F8: =ROUNDUP(E8,0)-0.01 -> 231.99 | G8: =E8+'Cost Source'!N8 -> 231.62 | H8: =ROUNDUP(G8,0)-0.01 -> 231.99 | J8: 10
A9: Air Filter | B9: 2599273C92 | C9: ='Price List'!C9+'Cost Source'!I9+'Cost Source'!O9 -> 661.98 | D9: =ROUNDUP(C9,0)-0.01 -> 661.99 | E9: ='Price List'!C9+'Cost Source'!V9 -> 661.98 | F9: =ROUNDUP(E9,0)-0.01 -> 661.99 | G9: =E9+'Cost Source'!N9 -> 661.98 | H9: =ROUNDUP(G9,0)-0.01 -> 661.99 | J9: 15
A10: Air Filter | B10: 4329012482 | C10: ='Price List'!C10+'Cost Source'!I10+'Cost Source'!O10 -> 135.69 | D10: =ROUNDUP(C10,0)-0.01 -> 135.99 | E10: ='Price List'!C10+'Cost Source'!V10 -> 125.69 | F10: =ROUNDUP(E10,0)-0.01 -> 125.99 | G10: ='Price List'!C10+'Cost Source'!N10 -> 115.69 | H10: =ROUNDUP(G10,0)-0.01 -> 115.99 | J10: 20
A11: Air Filter | B11: 950011-G3 | C11: ='Price List'!C11+'Cost Source'!I11+'Cost Source'!O11 -> 49.52 | D11: =ROUNDUP(C11,0)-0.01 -> 49.99 | E11: ='Price List'!C11+'Cost Source'!V11 -> 49.52 | F11: =ROUNDUP(E11,0)-0.01 -> 49.99 | G11: =E11+'Cost Source'!N11 -> 49.52 | H11: =ROUNDUP(G11,0)-0.01 -> 49.99 | J11: 10
A12: Air Filter | B12: AC1001 | C12: ='Price List'!C12+'Cost Source'!I12+'Cost Source'!O12 -> 105.95 | D12: =ROUNDUP(C12,0)-0.01 -> 105.99 | E12: ='Price List'!C12+'Cost Source'!V12 -> 95.95 | F12: =ROUNDUP(E12,0)-0.01 -> 95.99 | G12: ='Price List'!C12+'Cost Source'!N12 -> 85.95 | H12: =ROUNDUP(G12,0)-0.01 -> 85.99 | J12: 20
A13: Air Filter | B13: AD27747 | C13: ='Price List'!C13+'Cost Source'!I13+'Cost Source'!O13 -> 85.7696 | D13: =ROUNDUP(C13,0)-0.01 -> 85.99 | E13: ='Price List'!C13+'Cost Source'!V13 -> 75.7696 | F13: =ROUNDUP(E13,0)-0.01 -> 75.99 | G13: ='Price List'!C13+'Cost Source'!N13 -> 60.7696 | H13: =ROUNDUP(G13,0)-0.01 -> 60.99 | J13: 20
A14: Air Filter | B14: AD27750 | C14: ='Price List'!C14+'Cost Source'!I14+'Cost Source'!O14 -> 86.256 | D14: =ROUNDUP(C14,0)-0.01 -> 86.99 | E14: ='Price List'!C14+'Cost Source'!V14 -> 76.256 | F14: =ROUNDUP(E14,0)-0.01 -> 76.99 | G14: ='Price List'!C14+'Cost Source'!N14 -> 61.256 | H14: =ROUNDUP(G14,0)-0.01 -> 61.99 | J14: 20
A15: Air Filter | B15: AF1651 | G15: ='Price List'!C15+'Cost Source'!N15 -> 14.49
A16: Air Filter | B16: AF25139M | C16: ='Price List'!C16+'Cost Source'!I16+'Cost Source'!O16 -> 85.4176 | D16: =ROUNDUP(C16,0)-0.01 -> 85.99 | E16: ='Price List'!C16+'Cost Source'!V16 -> 85.4176 | F16: =ROUNDUP(E16,0)-0.01 -> 85.99 | G16: =E16+'Cost Source'!N16 -> 85.4176 | H16: =ROUNDUP(G16,0)-0.01 -> 85.99
A17: Air Filter | B17: AF25550 | C17: ='Price List'!C17+'Cost Source'!I17+'Cost Source'!O17 -> 33.2896 | D17: =ROUNDUP(C17,0)-0.01 -> 33.99 | E17: ='Price List'!C17+'Cost Source'!V17 -> 33.2896 | F17: =ROUNDUP(E17,0)-0.01 -> 33.99 | G17: =E17+'Cost Source'!N17 -> 33.2896 | H17: =ROUNDUP(G17,0)-0.01 -> 33.99 | J17: 10
A18: Air Filter | B18: AF25707 | C18: ='Price List'!C18+'Cost Source'!I18+'Cost Source'!O18 -> 84.2304 | D18: =ROUNDUP(C18,0)-0.01 -> 84.99 | E18: ='Price List'!C18+'Cost Source'!V18 -> 84.2304 | F18: =ROUNDUP(E18,0)-0.01 -> 84.99 | G18: =E18+'Cost Source'!N18 -> 84.2304 | H18: =ROUNDUP(G18,0)-0.01 -> 84.99 | J18: 10
A19: Air Filter | B19: AF25732 | C19: ='Price List'!C19+'Cost Source'!I19+'Cost Source'!O19 -> 85.8368 | D19: =ROUNDUP(C19,0)-0.01 -> 85.99 | E19: ='Price List'!C19+'Cost Source'!V19 -> 85.8368 | F19: =ROUNDUP(E19,0)-0.01 -> 85.99 | G19: =E19+'Cost Source'!N19 -> 85.8368 | H19: =ROUNDUP(G19,0)-0.01 -> 85.99 | J19: 10
A20: Air Filter | B20: AF26163M | C20: ='Price List'!C20+'Cost Source'!I20+'Cost Source'!O20 -> 89.776 | D20: =ROUNDUP(C20,0)-0.01 -> 89.99 | E20: ='Price List'!C20+'Cost Source'!V20 -> 89.776 | F20: =ROUNDUP(E20,0)-0.01 -> 89.99 | G20: =E20+'Cost Source'!N20 -> 89.776 | H20: =ROUNDUP(G20,0)-0.01 -> 89.99
A21: Air Filter | B21: AF26268 | C21: ='Price List'!C21+'Cost Source'!I21+'Cost Source'!O21 -> 69.6304 | D21: =ROUNDUP(C21,0)-0.01 -> 69.99 | E21: ='Price List'!C21+'Cost Source'!V21 -> 69.6304 | F21: =ROUNDUP(E21,0)-0.01 -> 69.99 | G21: =E21+'Cost Source'!N21 -> 69.6304 | H21: =ROUNDUP(G21,0)-0.01 -> 69.99 | J21: 10
A22: Air Filter | B22: AF26403 | C22: ='Price List'!C22+'Cost Source'!I22+'Cost Source'!O22 -> 46.2272 | D22: =ROUNDUP(C22,0)-0.01 -> 46.99 | E22: ='Price List'!C22+'Cost Source'!V22 -> 46.2272 | F22: =ROUNDUP(E22,0)-0.01 -> 46.99 | G22: =E22+'Cost Source'!N22 -> 46.2272 | H22: =ROUNDUP(G22,0)-0.01 -> 46.99 | J22: 10
A23: Air Filter | B23: AF27690 | C23: ='Price List'!C23+'Cost Source'!I23+'Cost Source'!O23 -> 77.7952 | D23: =ROUNDUP(C23,0)-0.01 -> 77.99 | E23: ='Price List'!C23+'Cost Source'!V23 -> 77.7952 | F23: =ROUNDUP(E23,0)-0.01 -> 77.99 | G23: =E23+'Cost Source'!N23 -> 77.7952 | H23: =ROUNDUP(G23,0)-0.01 -> 77.99 | J23: 10
A24: Air Filter | B24: AF27693 | C24: ='Price List'!C24+'Cost Source'!I24+'Cost Source'!O24 -> 69.3312 | D24: =ROUNDUP(C24,0)-0.01 -> 69.99 | E24: ='Price List'!C24+'Cost Source'!V24 -> 69.3312 | F24: =ROUNDUP(E24,0)-0.01 -> 69.99 | G24: =E24+'Cost Source'!N24 -> 69.3312 | H24: =ROUNDUP(G24,0)-0.01 -> 69.99 | J24: 10
A25: Air Filter | B25: AF27905 | C25: ='Price List'!C25+'Cost Source'!I25+'Cost Source'!O25 -> 103.136 | D25: =ROUNDUP(C25,0)-0.01 -> 103.99 | E25: ='Price List'!C25+'Cost Source'!V25 -> 103.136 | F25: =ROUNDUP(E25,0)-0.01 -> 103.99 | G25: =E25+'Cost Source'!N25 -> 103.136 | H25: =ROUNDUP(G25,0)-0.01 -> 103.99 | J25: 10
A26: Air Filter | B26: AF27906 | C26: ='Price List'!C26+'Cost Source'!I26+'Cost Source'!O26 -> 34.664 | D26: =ROUNDUP(C26,0)-0.01 -> 34.99 | E26: ='Price List'!C26+'Cost Source'!V26 -> 34.664 | F26: =ROUNDUP(E26,0)-0.01 -> 34.99 | G26: =E26+'Cost Source'!N26 -> 34.664 | H26: =ROUNDUP(G26,0)-0.01 -> 34.99 | J26: 10
A27: Air Filter | B27: AF4878 | C27: ='Price List'!C27+'Cost Source'!I27+'Cost Source'!O27 -> 60.544 | D27: =ROUNDUP(C27,0)-0.01 -> 60.99 | E27: ='Price List'!C27+'Cost Source'!V27 -> 60.544 | F27: =ROUNDUP(E27,0)-0.01 -> 60.99 | G27: =E27+'Cost Source'!N27 -> 60.544 | H27: =ROUNDUP(G27,0)-0.01 -> 60.99 | J27: 10
A28: Air Filter | B28: AF890 | C28: ='Price List'!C28+'Cost Source'!I28+'Cost Source'!O28 -> 104.296 | D28: =ROUNDUP(C28,0)-0.01 -> 104.99 | E28: ='Price List'!C28+'Cost Source'!V28 -> 104.296 | F28: =ROUNDUP(E28,0)-0.01 -> 104.99 | G28: =E28+'Cost Source'!N28 -> 104.296 | H28: =ROUNDUP(G28,0)-0.01 -> 104.99 | J28: 15
A29: Air Filter | B29: AH8501 | C29: ='Price List'!C29+'Cost Source'!I29+'Cost Source'!O29 -> 178.3376 | D29: =ROUNDUP(C29,0)-0.01 -> 178.99 | E29: ='Price List'!C29+'Cost Source'!V29 -> 178.3376 | F29: =ROUNDUP(E29,0)-0.01 -> 178.99 | G29: =E29+'Cost Source'!N29 -> 178.3376 | H29: =ROUNDUP(G29,0)-0.01 -> 178.99 | J29: 50
A30: Air Filter | B30: CA30132 | C30: ='Price List'!C30+'Cost Source'!I30+'Cost Source'!O30 -> 148.45 | D30: =ROUNDUP(C30,0)-0.01 -> 148.99 | E30: ='Price List'!C30+'Cost Source'!V30 -> 148.45 | F30: =ROUNDUP(E30,0)-0.01 -> 148.99 | G30: =E30+'Cost Source'!N30 -> 148.45 | H30: =ROUNDUP(G30,0)-0.01 -> 148.99
A31: Air Filter | B31: CA4700 | C31: ='Price List'!C31+'Cost Source'!I31+'Cost Source'!O31 -> 64.14 | D31: =ROUNDUP(C31,0)-0.01 -> 64.99 | E31: ='Price List'!C31+'Cost Source'!V31 -> 64.14 | F31: =ROUNDUP(E31,0)-0.01 -> 64.99 | G31: =E31+'Cost Source'!N31 -> 64.14 | H31: =ROUNDUP(G31,0)-0.01 -> 64.99
A32: Air Filter | B32: CA5368 | C32: ='Price List'!C32+'Cost Source'!I32+'Cost Source'!O32 -> 85.38 | D32: =ROUNDUP(C32,0)-0.01 -> 85.99 | E32: ='Price List'!C32+'Cost Source'!V32 -> 85.38 | F32: =ROUNDUP(E32,0)-0.01 -> 85.99 | G32: =E32+'Cost Source'!N32 -> 85.38 | H32: =ROUNDUP(G32,0)-0.01 -> 85.99
A33: Air Filter | B33: CA5500 | C33: ='Price List'!C33+'Cost Source'!I33+'Cost Source'!O33 -> 115.87 | D33: =ROUNDUP(C33,0)-0.01 -> 115.99 | E33: ='Price List'!C33+'Cost Source'!V33 -> 115.87 | F33: =ROUNDUP(E33,0)-0.01 -> 115.99 | G33: =E33+'Cost Source'!N33 -> 115.87 | H33: =ROUNDUP(G33,0)-0.01 -> 115.99
A34: Air Filter | B34: CA5790 | C34: ='Price List'!C34+'Cost Source'!I34+'Cost Source'!O34 -> 100.96 | D34: =ROUNDUP(C34,0)-0.01 -> 100.99 | E34: ='Price List'!C34+'Cost Source'!V34 -> 100.96 | F34: =ROUNDUP(E34,0)-0.01 -> 100.99 | G34: =E34+'Cost Source'!N34 -> 100.96 | H34: =ROUNDUP(G34,0)-0.01 -> 100.99
A35: Air Filter | B35: D37-1061 | C35: ='Price List'!C35+'Cost Source'!I35+'Cost Source'!O35 -> 377.43 | D35: =ROUNDUP(C35,0)-0.01 -> 377.99 | E35: ='Price List'!C35+'Cost Source'!V35 -> 377.43 | F35: =ROUNDUP(E35,0)-0.01 -> 377.99 | G35: =E35+'Cost Source'!N35 -> 377.43 | H35: =ROUNDUP(G35,0)-0.01 -> 377.99
A36: Air Filter | B36: ME073821 | C36: ='Price List'!C36+'Cost Source'!I36 -> 104.4 | D36: =ROUNDUP(C36,0)-0.01 -> 104.99 | E36: ='Price List'!C36+'Cost Source'!V36 -> 104.4 | F36: =ROUNDUP(E36,0)-0.01 -> 104.99 | G36: =E36+'Cost Source'!N36 -> 104.4 | H36: =ROUNDUP(G36,0)-0.01 -> 104.99
A37: Air Filter | B37: P129396 | C37: ='Price List'!C37+'Cost Source'!I37+'Cost Source'!O37 -> 108.9 | D37: =ROUNDUP(C37,0)-0.01 -> 108.99 | E37: ='Price List'!C37+'Cost Source'!V37 -> 108.9 | F37: =ROUNDUP(E37,0)-0.01 -> 108.99 | G37: =E37+'Cost Source'!N37 -> 108.9 | H37: =ROUNDUP(G37,0)-0.01 -> 108.99
A38: Air Filter | B38: P141317 | C38: ='Price List'!C38+'Cost Source'!I38+'Cost Source'!O38 -> 101.12 | D38: =ROUNDUP(C38,0)-0.01 -> 101.99 | E38: ='Price List'!C38+'Cost Source'!V38 -> 101.12 | F38: =ROUNDUP(E38,0)-0.01 -> 101.99 | G38: =E38+'Cost Source'!N38 -> 101.12 | H38: =ROUNDUP(G38,0)-0.01 -> 101.99 | J38: 15
A39: Air Filter | B39: P150695 | C39: ='Price List'!C39+'Cost Source'!I39+'Cost Source'!O39 -> 100.13 | D39: =ROUNDUP(C39,0)-0.01 -> 100.99 | E39: ='Price List'!C39+'Cost Source'!V39 -> 100.13 | F39: =ROUNDUP(E39,0)-0.01 -> 100.99 | G39: =E39+'Cost Source'!N39 -> 100.13 | H39: =ROUNDUP(G39,0)-0.01 -> 100.99
A40: Air Filter | B40: P151097 | C40: ='Price List'!C40+'Cost Source'!I40+'Cost Source'!O40 -> 105.76 | D40: =ROUNDUP(C40,0)-0.01 -> 105.99 | E40: ='Price List'!C40+'Cost Source'!V40 -> 105.76 | F40: =ROUNDUP(E40,0)-0.01 -> 105.99 | G40: =E40+'Cost Source'!N40 -> 105.76 | H40: =ROUNDUP(G40,0)-0.01 -> 105.99
A41: Air Filter | B41: P153551 | C41: ='Price List'!C41+'Cost Source'!I41+'Cost Source'!O41 -> 79.82 | D41: =ROUNDUP(C41,0)-0.01 -> 79.99 | E41: ='Price List'!C41+'Cost Source'!V41 -> 79.82 | F41: =ROUNDUP(E41,0)-0.01 -> 79.99 | G41: =E41+'Cost Source'!N41 -> 79.82 | H41: =ROUNDUP(G41,0)-0.01 -> 79.99
A42: Air Filter | B42: P154927 | C42: ='Price List'!C42+'Cost Source'!I42+'Cost Source'!O42 -> 120.7 | D42: =ROUNDUP(C42,0)-0.01 -> 120.99 | E42: ='Price List'!C42+'Cost Source'!V42 -> 120.7 | F42: =ROUNDUP(E42,0)-0.01 -> 120.99 | G42: =E42+'Cost Source'!N42 -> 120.7 | H42: =ROUNDUP(G42,0)-0.01 -> 120.99 | J42: 15
A43: Air Filter | B43: P181009 | C43: ='Price List'!C43+'Cost Source'!I43+'Cost Source'!O43 -> 97.14 | D43: =ROUNDUP(C43,0)-0.01 -> 97.99 | E43: ='Price List'!C43+'Cost Source'!V43 -> 97.14 | F43: =ROUNDUP(E43,0)-0.01 -> 97.99 | G43: =E43+'Cost Source'!N43 -> 97.14 | H43: =ROUNDUP(G43,0)-0.01 -> 97.99 | J43: 15
A44: Air Filter | B44: P181016 | C44: ='Price List'!C44+'Cost Source'!I44+'Cost Source'!O44 -> 103.63 | D44: =ROUNDUP(C44,0)-0.01 -> 103.99 | E44: ='Price List'!C44+'Cost Source'!V44 -> 103.63 | F44: =ROUNDUP(E44,0)-0.01 -> 103.99 | G44: =E44+'Cost Source'!N44 -> 103.63 | H44: =ROUNDUP(G44,0)-0.01 -> 103.99 | J44: 15
A45: Air Filter | B45: P181028 | C45: ='Price List'!C45+'Cost Source'!I45+'Cost Source'!O45 -> 70.4 | D45: =ROUNDUP(C45,0)-0.01 -> 70.99 | E45: ='Price List'!C45+'Cost Source'!V45 -> 70.4 | F45: =ROUNDUP(E45,0)-0.01 -> 70.99 | G45: =E45+'Cost Source'!N45 -> 70.4 | H45: =ROUNDUP(G45,0)-0.01 -> 70.99 | J45: 10
A46: Air Filter | B46: P181041 | C46: ='Price List'!C46+'Cost Source'!I46+'Cost Source'!O46 -> 80.26 | D46: =ROUNDUP(C46,0)-0.01 -> 80.99 | E46: ='Price List'!C46+'Cost Source'!V46 -> 80.26 | F46: =ROUNDUP(E46,0)-0.01 -> 80.99 | G46: =E46+'Cost Source'!N46 -> 80.26 | H46: =ROUNDUP(G46,0)-0.01 -> 80.99 | J46: 10
A47: Air Filter | B47: P181186 | C47: ='Price List'!C47+'Cost Source'!I47+'Cost Source'!O47 -> 114.66 | D47: =ROUNDUP(C47,0)-0.01 -> 114.99 | E47: ='Price List'!C47+'Cost Source'!V47 -> 114.66 | F47: =ROUNDUP(E47,0)-0.01 -> 114.99 | G47: =E47+'Cost Source'!N47 -> 114.66 | H47: =ROUNDUP(G47,0)-0.01 -> 114.99 | J47: 15
A48: Air Filter | B48: P181189 | C48: ='Price List'!C48+'Cost Source'!I48+'Cost Source'!O48 -> 108.64 | D48: =ROUNDUP(C48,0)-0.01 -> 108.99 | E48: ='Price List'!C48+'Cost Source'!V48 -> 108.64 | F48: =ROUNDUP(E48,0)-0.01 -> 108.99 | G48: =E48+'Cost Source'!N48 -> 108.64 | H48: =ROUNDUP(G48,0)-0.01 -> 108.99 | J48: 10
A49: Air Filter | B49: P521598 | C49: ='Price List'!C49+'Cost Source'!I49+'Cost Source'!O49 -> 104.39 | D49: =ROUNDUP(C49,0)-0.01 -> 104.99 | E49: ='Price List'!C49+'Cost Source'!V49 -> 104.39 | F49: =ROUNDUP(E49,0)-0.01 -> 104.99 | G49: =E49+'Cost Source'!N49 -> 104.39 | H49: =ROUNDUP(G49,0)-0.01 -> 104.99 | J49: 10
A50: Air Filter | B50: P522293 | C50: ='Price List'!C50+'Cost Source'!I50+'Cost Source'!O50 -> 98.11 | D50: =ROUNDUP(C50,0)-0.01 -> 98.99 | E50: ='Price List'!C50+'Cost Source'!V50 -> 98.11 | F50: =ROUNDUP(E50,0)-0.01 -> 98.99 | G50: =E50+'Cost Source'!N50 -> 98.11 | H50: =ROUNDUP(G50,0)-0.01 -> 98.99 | J50: 10
A51: Air Filter | B51: P527682 | C51: ='Price List'!C51+'Cost Source'!I51+'Cost Source'!O51 -> 83.55 | D51: =ROUNDUP(C51,0)-0.01 -> 83.99 | E51: ='Price List'!C51+'Cost Source'!V51 -> 83.55 | F51: =ROUNDUP(E51,0)-0.01 -> 83.99 | G51: =E51+'Cost Source'!N51 -> 83.55 | H51: =ROUNDUP(G51,0)-0.01 -> 83.99 | J51: 10
A52: Air Filter | B52: P532966 | C52: ='Price List'!C52+'Cost Source'!I52+'Cost Source'!O52 -> 73.72 | D52: =ROUNDUP(C52,0)-0.01 -> 73.99 | E52: ='Price List'!C52+'Cost Source'!V52 -> 73.72 | F52: =ROUNDUP(E52,0)-0.01 -> 73.99 | G52: =E52+'Cost Source'!N52 -> 73.72 | H52: =ROUNDUP(G52,0)-0.01 -> 73.99 | J52: 10
A53: Air Filter | B53: P533235 | C53: ='Price List'!C53+'Cost Source'!I53+'Cost Source'!O53 -> 81.88 | D53: =ROUNDUP(C53,0)-0.01 -> 81.99 | E53: ='Price List'!C53+'Cost Source'!V53 -> 81.88 | F53: =ROUNDUP(E53,0)-0.01 -> 81.99 | G53: =E53+'Cost Source'!N53 -> 81.88 | H53: =ROUNDUP(G53,0)-0.01 -> 81.99 | J53: 10
... A61: Air Filter | B61: P540388 | C61: ='Price List'!C61+'Cost Source'!I61+'Cost Source'!O61 -> 82.06 | D61: =ROUNDUP(C61,0)-0.01 -> 82.99 | E61: ='Price List'!C61+'Cost Source'!V61 -> 82.06 | F61: =ROUNDUP(E61,0)-0.01 -> 82.99 | G61: =E61+'Cost Source'!N61 -> 82.06 | H61: =ROUNDUP(G61,0)-0.01 -> 82.99 | J61: 10
A62: Air Filter | B62: P544243 | C62: ='Price List'!C62+'Cost Source'!I62 -> 103.01 | D62: =ROUNDUP(C62,0)-0.01 -> 103.99 | E62: ='Price List'!C62+'Cost Source'!I62 -> 103.01 | F62: =ROUNDUP(E62,0)-0.01 -> 103.99 | G62: ='Price List'!C62+'Cost Source'!I62 -> 103.01 | H62: =ROUNDUP(G62,0)-0.01 -> 103.99 | J62: 15
A63: Air Filter | B63: P549644 | C63: ='Price List'!C63+'Cost Source'!I63+'Cost Source'!O63 -> 91.08 | D63: =ROUNDUP(C63,0)-0.01 -> 91.99 | E63: ='Price List'!C63+'Cost Source'!V63 -> 91.08 | F63: =ROUNDUP(E63,0)-0.01 -> 91.99 | G63: =E63+'Cost Source'!N63 -> 91.08 | H63: =ROUNDUP(G63,0)-0.01 -> 91.99 | J63: 10
A64: Air Filter | B64: P600676 | C64: ='Price List'!C64+'Cost Source'!I64+'Cost Source'!O64 -> 89.89 | D64: =ROUNDUP(C64,0)-0.01 -> 89.99 | E64: ='Price List'!C64+'Cost Source'!V64 -> 89.89 | F64: =ROUNDUP(E64,0)-0.01 -> 89.99 | G64: =E64+'Cost Source'!N64 -> 89.89 | H64: =ROUNDUP(G64,0)-0.01 -> 89.99 | J64: 10
A65: Air Filter | B65: P606503 | C65: ='Price List'!C65+'Cost Source'!I65+'Cost Source'!O65 -> 93.2 | D65: =ROUNDUP(C65,0)-0.01 -> 93.99 | E65: ='Price List'!C65+'Cost Source'!V65 -> 93.2 | F65: =ROUNDUP(E65,0)-0.01 -> 93.99 | G65: =E65+'Cost Source'!N65 -> 93.2 | H65: =ROUNDUP(G65,0)-0.01 -> 93.99 | J65: 10
A66: Air Filter | B66: P606720 | C66: ='Price List'!C66+'Cost Source'!I66+'Cost Source'!O66 -> 87.98 | D66: =ROUNDUP(C66,0)-0.01 -> 87.99 | E66: ='Price List'!C66+'Cost Source'!V66 -> 87.98 | F66: =ROUNDUP(E66,0)-0.01 -> 87.99 | G66: =E66+'Cost Source'!N66 -> 87.98 | H66: =ROUNDUP(G66,0)-0.01 -> 87.99 | J66: 10
A67: Air Filter | B67: P607955 | C67: ='Price List'!C67+'Cost Source'!I67+'Cost Source'!O67 -> 86.51 | D67: =ROUNDUP(C67,0)-0.01 -> 86.99 | E67: ='Price List'!C67+'Cost Source'!V67 -> 86.51 | F67: =ROUNDUP(E67,0)-0.01 -> 86.99 | G67: =E67+'Cost Source'!N67 -> 86.51 | H67: =ROUNDUP(G67,0)-0.01 -> 86.99 | J67: 10
A68: Air Filter | B68: P607965 | C68: ='Price List'!C68+'Cost Source'!I68+'Cost Source'!O68 -> 113.64 | D68: =ROUNDUP(C68,0)-0.01 -> 113.99 | E68: ='Price List'!C68+'Cost Source'!V68 -> 113.64 | F68: =ROUNDUP(E68,0)-0.01 -> 113.99 | G68: =E68+'Cost Source'!N68 -> 113.64 | H68: =ROUNDUP(G68,0)-0.01 -> 113.99 | J68: 10
A69: Air Filter | B69: P610260 | C69: ='Price List'!C69+'Cost Source'!I69+'Cost Source'!O69 -> 94.75 | D69: =ROUNDUP(C69,0)-0.01 -> 94.99 | E69: ='Price List'!C69+'Cost Source'!V69 -> 94.75 | F69: =ROUNDUP(E69,0)-0.01 -> 94.99 | G69: =E69+'Cost Source'!N69 -> 94.75 | H69: =ROUNDUP(G69,0)-0.01 -> 94.99 | J69: 10
A70: Air Filter | B70: P611696 | C70: ='Price List'!C70+'Cost Source'!I70+'Cost Source'!O70 -> 287.6 | D70: =ROUNDUP(C70,0)-0.01 -> 287.99 | E70: ='Price List'!C70+'Cost Source'!V70 -> 287.6 | F70: =ROUNDUP(E70,0)-0.01 -> 287.99 | G70: =E70+'Cost Source'!N70 -> 287.6 | H70: =ROUNDUP(G70,0)-0.01 -> 287.99 | J70: 10
A71: Air Filter | B71: P613336 | C71: ='Price List'!C71+'Cost Source'!I71+'Cost Source'!O71 -> 94.2 | D71: =ROUNDUP(C71,0)-0.01 -> 94.99 | E71: ='Price List'!C71+'Cost Source'!V71 -> 94.2 | F71: =ROUNDUP(E71,0)-0.01 -> 94.99 | G71: =E71+'Cost Source'!N71 -> 94.2 | H71: =ROUNDUP(G71,0)-0.01 -> 94.99 | J71: 10
A72: Air Filter | B72: P614556 | C72: ='Price List'!C72+'Cost Source'!I72+'Cost Source'!O72 -> 129.84 | D72: =ROUNDUP(C72,0)-0.01 -> 129.99 | E72: ='Price List'!C72+'Cost Source'!V72 -> 129.84 | F72: =ROUNDUP(E72,0)-0.01 -> 129.99 | G72: =E72+'Cost Source'!N72 -> 129.84 | H72: =ROUNDUP(G72,0)-0.01 -> 129.99 | J72: 10
A73: Air Filter | B73: P614986 | C73: ='Price List'!C73+'Cost Source'!I73+'Cost Source'!O73 -> 254.28 | D73: =ROUNDUP(C73,0)-0.01 -> 254.99 | E73: ='Price List'!C73+'Cost Source'!V73 -> 254.28 | F73: =ROUNDUP(E73,0)-0.01 -> 254.99 | G73: =E73+'Cost Source'!N73 -> 254.28 | H73: =ROUNDUP(G73,0)-0.01 -> 254.99 | J73: 10
A74: Air Filter | B74: P616056 | C74: ='Price List'!C74+'Cost Source'!I74+'Cost Source'!O74 -> 167.5 | D74: =ROUNDUP(C74,0)-0.01 -> 167.99 | E74: ='Price List'!C74+'Cost Source'!V74 -> 167.5 | F74: =ROUNDUP(E74,0)-0.01 -> 167.99 | G74: =E74+'Cost Source'!N74 -> 167.5 | H74: =ROUNDUP(G74,0)-0.01 -> 167.99 | J74: 10
... A79: Air Filter | B79: P625287 | C79: ='Price List'!C79+'Cost Source'!I79+'Cost Source'!O79 -> 119.67 | D79: =ROUNDUP(C79,0)-0.01 -> 119.99 | E79: ='Price List'!C79+'Cost Source'!V79 -> 119.67 | F79: =ROUNDUP(E79,0)-0.01 -> 119.99 | G79: =E79+'Cost Source'!N79 -> 119.67 | H79: =ROUNDUP(G79,0)-0.01 -> 119.99 | J79: 15
A80: Air Filter | B80: P634517 | C80: ='Price List'!C80+'Cost Source'!I80+'Cost Source'!O80 -> 158.12 | D80: =ROUNDUP(C80,0)-0.01 -> 158.99 | E80: ='Price List'!C80+'Cost Source'!V80 -> 158.12 | F80: =ROUNDUP(E80,0)-0.01 -> 158.99 | G80: =E80+'Cost Source'!N80 -> 158.12 | H80: =ROUNDUP(G80,0)-0.01 -> 158.99
A81: Air Filter | B81: P637453 | C81: ='Price List'!C81+'Cost Source'!I81+'Cost Source'!O81 -> 139.72 | D81: =ROUNDUP(C81,0)-0.01 -> 139.99 | E81: ='Price List'!C81+'Cost Source'!V81 -> 139.72 | F81: =ROUNDUP(E81,0)-0.01 -> 139.99 | G81: =E81+'Cost Source'!N81 -> 139.72 | H81: =ROUNDUP(G81,0)-0.01 -> 139.99
A82: Air Filter | B82: P637454 | C82: ='Price List'!C82+'Cost Source'!I82+'Cost Source'!O82 -> 152.97 | D82: =ROUNDUP(C82,0)-0.01 -> 152.99 | E82: ='Price List'!C82+'Cost Source'!V82 -> 152.97 | F82: =ROUNDUP(E82,0)-0.01 -> 152.99 | G82: =E82+'Cost Source'!N82 -> 152.97 | H82: =ROUNDUP(G82,0)-0.01 -> 152.99 | J82: 15
A83: Air Filter | B83: P640017 | C83: ='Price List'!C83+'Cost Source'!I83 -> 313.38 | D83: =ROUNDUP(C83,0)-0.01 -> 313.99 | E83: ='Price List'!C83+'Cost Source'!V83 -> 313.38 | F83: =ROUNDUP(E83,0)-0.01 -> 313.99 | G83: =E83+'Cost Source'!N83 -> 313.38 | H83: =ROUNDUP(G83,0)-0.01 -> 313.99 | J83: 15
A84: Air Filter | B84: P644827 | C84: ='Price List'!C84+'Cost Source'!I84 -> 153.42 | D84: =ROUNDUP(C84,0)-0.01 -> 153.99 | E84: ='Price List'!C84+'Cost Source'!I84 -> 153.42 | F84: =ROUNDUP(E84,0)-0.01 -> 153.99 | G84: ='Price List'!C84+'Cost Source'!I84 -> 153.42 | H84: =ROUNDUP(G84,0)-0.01 -> 153.99 | J84: 25 | K84: Each
A85: Air Filter | B85: P645114 | C85: ='Price List'!C85+'Cost Source'!I85+'Cost Source'!O85 -> 89.48 | D85: =ROUNDUP(C85,0)-0.01 -> 89.99 | E85: ='Price List'!C85+'Cost Source'!V85 -> 89.48 | F85: =ROUNDUP(E85,0)-0.01 -> 89.99 | G85: =E85+'Cost Source'!N85 -> 89.48 | H85: =ROUNDUP(G85,0)-0.01 -> 89.99 | J85: 10
A86: Air Filter | B86: P648156 | C86: ='Price List'!C86+'Cost Source'!I86 -> 177.56 | D86: =ROUNDUP(C86,0)-0.01 -> 177.99 | E86: ='Price List'!C86+'Cost Source'!I86 -> 177.56 | F86: =ROUNDUP(E86,0)-0.01 -> 177.99 | G86: ='Price List'!C86+'Cost Source'!I86 -> 177.56 | H86: =ROUNDUP(G86,0)-0.01 -> 177.99
A87: Air Filter | B87: P780622 | C87: ='Price List'!C87+'Cost Source'!I87+'Cost Source'!O87 -> 100.74 | D87: =ROUNDUP(C87,0)-0.01 -> 100.99 | E87: ='Price List'!C87+'Cost Source'!V87 -> 100.74 | F87: =ROUNDUP(E87,0)-0.01 -> 100.99 | G87: =E87+'Cost Source'!N87 -> 100.74 | H87: =ROUNDUP(G87,0)-0.01 -> 100.99
A88: Air Filter | B88: PA2333 | C88: ='Price List'!C88+'Cost Source'!I88+'Cost Source'!O88 -> 69.44 | D88: =ROUNDUP(C88,0)-0.01 -> 69.99 | E88: ='Price List'!C88+'Cost Source'!V88 -> 69.44 | F88: =ROUNDUP(E88,0)-0.01 -> 69.99 | G88: =E88+'Cost Source'!N88 -> 69.44 | H88: =ROUNDUP(G88,0)-0.01 -> 69.99
A89: Air Filter | B89: PA2357 | C89: ='Price List'!C89+'Cost Source'!I89+'Cost Source'!O89 -> 97.05 | D89: =ROUNDUP(C89,0)-0.01 -> 97.99 | E89: ='Price List'!C89+'Cost Source'!V89 -> 97.05 | F89: =ROUNDUP(E89,0)-0.01 -> 97.99 | G89: =E89+'Cost Source'!N89 -> 97.05 | H89: =ROUNDUP(G89,0)-0.01 -> 97.99
A90: Air Filter | B90: PA2493 | C90: ='Price List'!C90+'Cost Source'!I90+'Cost Source'!O90 -> 98.95 | D90: =ROUNDUP(C90,0)-0.01 -> 98.99 | E90: ='Price List'!C90+'Cost Source'!V90 -> 98.95 | F90: =ROUNDUP(E90,0)-0.01 -> 98.99 | G90: =E90+'Cost Source'!N90 -> 98.95 | H90: =ROUNDUP(G90,0)-0.01 -> 98.99
A91: Air Filter | B91: PA2521 | C91: ='Price List'!C91+'Cost Source'!I91+'Cost Source'!O91 -> 68.83 | D91: =ROUNDUP(C91,0)-0.01 -> 68.99 | E91: ='Price List'!C91+'Cost Source'!V91 -> 68.83 | F91: =ROUNDUP(E91,0)-0.01 -> 68.99 | G91: =E91+'Cost Source'!N91 -> 68.83 | H91: =ROUNDUP(G91,0)-0.01 -> 68.99
A92: Air Filter | B92: PA2525 | C92: ='Price List'!C92+'Cost Source'!I92+'Cost Source'!O92 -> 69.14 | D92: =ROUNDUP(C92,0)-0.01 -> 69.99 | E92: ='Price List'!C92+'Cost Source'!V92 -> 69.14 | F92: =ROUNDUP(E92,0)-0.01 -> 69.99 | G92: =E92+'Cost Source'!N92 -> 69.14 | H92: =ROUNDUP(G92,0)-0.01 -> 69.99
A93: Air Filter | B93: PA2608 | C93: ='Price List'!C93+'Cost Source'!I93+'Cost Source'!O93 -> 79.15 | D93: =ROUNDUP(C93,0)-0.01 -> 79.99 | E93: ='Price List'!C93+'Cost Source'!V93 -> 79.15 | F93: =ROUNDUP(E93,0)-0.01 -> 79.99 | G93: =E93+'Cost Source'!N93 -> 79.15 | H93: =ROUNDUP(G93,0)-0.01 -> 79.99
A94: Air Filter | B94: PA2642 | C94: ='Price List'!C94+'Cost Source'!I94+'Cost Source'!O94 -> 104.55 | D94: =ROUNDUP(C94,0)-0.01 -> 104.99 | E94: ='Price List'!C94+'Cost Source'!V94 -> 104.55 | F94: =ROUNDUP(E94,0)-0.01 -> 104.99 | G94: =E94+'Cost Source'!N94 -> 104.55 | H94: =ROUNDUP(G94,0)-0.01 -> 104.99
A95: Air Filter | B95: PA2680 | C95: ='Price List'!C95+'Cost Source'!I95+'Cost Source'!O95 -> 98.44 | D95: =ROUNDUP(C95,0)-0.01 -> 98.99 | E95: ='Price List'!C95+'Cost Source'!V95 -> 98.44 | F95: =ROUNDUP(E95,0)-0.01 -> 98.99 | G95: =E95+'Cost Source'!N95 -> 98.44 | H95: =ROUNDUP(G95,0)-0.01 -> 98.99
A96: Air Filter | B96: PA2703 | C96: ='Price List'!C96+'Cost Source'!I96+'Cost Source'!O96 -> 95.5 | D96: =ROUNDUP(C96,0)-0.01 -> 95.99 | E96: ='Price List'!C96+'Cost Source'!V96 -> 95.5 | F96: =ROUNDUP(E96,0)-0.01 -> 95.99 | G96: =E96+'Cost Source'!N96 -> 95.5 | H96: =ROUNDUP(G96,0)-0.01 -> 95.99
A97: Air Filter | B97: PA2705 | C97: ='Price List'!C97+'Cost Source'!I97+'Cost Source'!O97 -> 76.81 | D97: =ROUNDUP(C97,0)-0.01 -> 76.99 | E97: ='Price List'!C97+'Cost Source'!V97 -> 76.81 | F97: =ROUNDUP(E97,0)-0.01 -> 76.99 | G97: =E97+'Cost Source'!N97 -> 76.81 | H97: =ROUNDUP(G97,0)-0.01 -> 76.99
A98: Air Filter | B98: PA2732 | C98: ='Price List'!C98+'Cost Source'!I98+'Cost Source'!O98 -> 95.44 | D98: =ROUNDUP(C98,0)-0.01 -> 95.99 | E98: ='Price List'!C98+'Cost Source'!V98 -> 95.44 | F98: =ROUNDUP(E98,0)-0.01 -> 95.99 | G98: =E98+'Cost Source'!N98 -> 95.44 | H98: =ROUNDUP(G98,0)-0.01 -> 95.99
... A122: Air Filter | B122: X011622 | C122: ='Price List'!C122+'Cost Source'!I122+'Cost Source'!O122 -> 210.83 | D122: =ROUNDUP(C122,0)-0.01 -> 210.99 | E122: ='Price List'!C122+'Cost Source'!V122 -> 210.83 | F122: =ROUNDUP(E122,0)-0.01 -> 210.99 | G122: =E122+'Cost Source'!N122 -> 210.83 | H122: =ROUNDUP(G122,0)-0.01 -> 210.99
A123: Alliance | B123: N122 HBK4884 | C123: ='Price List'!C123+'Cost Source'!F123+'Cost Source'!O123 -> 68.82 | D123: =ROUNDUP(C123,0)-0.01 -> 68.99 | E123: ='Price List'!C123+'Cost Source'!S123 -> 60.82 | F123: =ROUNDUP(E123,0)-0.01 -> 60.99 | G123: ='Price List'!C123+'Cost Source'!N123 -> 60.82 | H123: =ROUNDUP(G123,0)-0.01 -> 60.99
A124: Alliance | B124: N122 R50418 | C124: ='Price List'!C124+'Cost Source'!F124+'Cost Source'!O124 -> 50.3 | D124: =ROUNDUP(C124,0)-0.01 -> 50.99 | E124: ='Price List'!C124+'Cost Source'!S124 -> 40.3 | F124: =ROUNDUP(E124,0)-0.01 -> 40.99 | G124: ='Price List'!C124+'Cost Source'!N124 -> 36.3 | H124: =ROUNDUP(G124,0)-0.01 -> 36.99 | I124: ='Cost Source'!P124 -> 0 | J124: 15
A125: Alliance | B125: N122 R50422 | C125: ='Price List'!C125+'Cost Source'!F125+'Cost Source'!O125 -> 55.23 | D125: =ROUNDUP(C125,0)-0.01 -> 55.99 | E125: ='Price List'!C125+'Cost Source'!S125 -> 45.23 | F125: =ROUNDUP(E125,0)-0.01 -> 45.99 | G125: ='Price List'!C125+'Cost Source'!N125 -> 42.23 | H125: =ROUNDUP(G125,0)-0.01 -> 42.99 | I125: ='Cost Source'!P125 -> 0 | J125: 15
A126: Alliance | B126: N122 R50423 | C126: ='Price List'!C126+'Cost Source'!F126+'Cost Source'!O126 -> 53.49 | D126: =ROUNDUP(C126,0)-0.01 -> 53.99 | E126: ='Price List'!C126+'Cost Source'!S126 -> 43.49 | F126: =ROUNDUP(E126,0)-0.01 -> 43.99 | G126: ='Price List'!C126+'Cost Source'!N126 -> 39.49 | H126: =ROUNDUP(G126,0)-0.01 -> 39.99 | I126: ='Cost Source'!P126 -> 0 | J126: 15
A127: Alliance | B127: N122 R50550 | C127: ='Price List'!C127+'Cost Source'!F127+'Cost Source'!O127 -> 50.58 | D127: =ROUNDUP(C127,0)-0.01 -> 50.99 | E127: ='Price List'!C127+'Cost Source'!S127 -> 40.58 | F127: =ROUNDUP(E127,0)-0.01 -> 40.99 | G127: ='Price List'!C127+'Cost Source'!N127 -> 36.58 | H127: =ROUNDUP(G127,0)-0.01 -> 36.99 | I127: ='Cost Source'!P127 -> 0 | J127: 15
A128: Alliance | B128: N122 R50551 | C128: ='Price List'!C128+'Cost Source'!F128+'Cost Source'!O128 -> 50.2 | D128: =ROUNDUP(C128,0)-0.01 -> 50.99 | E128: ='Price List'!C128+'Cost Source'!S128 -> 40.2 | F128: =ROUNDUP(E128,0)-0.01 -> 40.99 | G128: ='Price List'!C128+'Cost Source'!N128 -> 36.2 | H128: =ROUNDUP(G128,0)-0.01 -> 36.99 | I128: ='Cost Source'!P128 -> 0 | J128: 15
A129: Alliance | B129: RK 21527 | C129: ='Price List'!C129+'Cost Source'!F129+'Cost Source'!O129 -> 62.33 | D129: =ROUNDUP(C129,0)-0.01 -> 62.99 | E129: ='Price List'!C129+'Cost Source'!S129 -> 54.33 | F129: =ROUNDUP(E129,0)-0.01 -> 54.99 | G129: ='Price List'!C129+'Cost Source'!N129 -> 58.33 | H129: =ROUNDUP(G129,0)-0.01 -> 58.99 | I129: ='Cost Source'!P129 -> 0 | J129: 15
B130: 84311 | I130: ='Cost Source'!P130 -> 0
B131: 84312 | I131: ='Cost Source'!P131 -> 0
A132: Baldwin | B132: B495 | C132: ='Price List'!C132+'Cost Source'!G132+'Cost Source'!O132 -> 39.31 | D132: =ROUNDUP(C132,0)-0.01 -> 39.99 | G132: ='Price List'!C132+'Cost Source'!N132 -> 17.31 | H132: =ROUNDUP(G132,0)-0.01 -> 17.99 | I132: ='Cost Source'!P132 -> -5
A133: Baldwin | B133: BF1259 | C133: ='Price List'!C133+'Cost Source'!F133+'Cost Source'!O133 -> 39.81 | D133: =ROUNDUP(C133,0)-0.01 -> 39.99 | E133: ='Price List'!C133+'Cost Source'!F133 -> 29.81 | F133: =ROUNDUP(E133,0)-0.01 -> 29.99 | G133: ='Price List'!C133+'Cost Source'!N133 -> 23.81 | H133: =ROUNDUP(G133,0)-0.01 -> 23.99 | I133: ='Cost Source'!P133 -> 0 | J133: 10
B134: BF1330SP | I134: ='Cost Source'!P134 -> 0 | J134: 15
...

Sheet Filter Cost
A1: STANDARD JOB LIST
F2: Filtre
A3: Auto Greaser Refill | F3: Cost
B4: FILTER
B5: Oil | C5: Oil | D5: Fuel | E5: Fuel
A6: C 7 / 10 / 3126 With Cat Filter | B6: 1R1807 | D6: 1R0751
B7: ='Price List'!C175 -> 25.78 | D7: ='Price List'!C174 -> 27.51 | F7: =SUM(B7:E7) -> 53.29 | G7: 53.29 | H7: =F7-G7 -> 0
A8: C 7 / 10 / 3126 With Fleetguard Filter | B8: LF667 | D8: FF5321
B9: ='Price List'!C500 -> 10.484 | D9: ='Price List'!C337 -> 11.3152 | F9: =SUM(B9:E9) -> 21.7992 | G9: 20.61 | H9: =F9-G9 -> 1.1892
A10: C 12 / 3406 With Cat Filter | B10: 1R0716 | D10: 1R0749
B11: ='Price List'!C172 -> 38.44 | D11: ='Price List'!C173 -> 32.14 | F11: =SUM(B11:E11) -> 70.58 | G11: 66.15 | H11: =F11-G11 -> 4.43
A12: C 12 / 3406 With Fleetguard Filter | B12: LF691A | D12: FF5319
B13: ='Price List'!C504 -> 16.8936 | D13: ='Price List'!C335 -> 14.1512 | F13: =SUM(B13:E13) -> 31.0448 | G13: 29.2 | H13: =F13-G13 -> 1.8448
A14: C 13 / 15 With Cat Filter | B14: 1R0716 | D14: 1R0749
B15: ='Price List'!C172 -> 38.44 | D15: ='Price List'!C173 -> 32.14 | F15: =SUM(B15:E15) -> 70.58 | G15: 66.15 | H15: =F15-G15 -> 4.43
A16: C 13 / 15 With Fleetguard Filter | B16: LF691A | D16: FF5319
B17: ='Price List'!C504 -> 16.8936 | D17: ='Price List'!C335 -> 14.1512 | F17: =SUM(B17:E17) -> 31.0448 | G17: 29.2 | H17: =F17-G17 -> 1.8448
A18: Cummins N14 | B18: LF3000
B19: ='Price List'!C472 -> 31.4312 | F19: =SUM(B19:E19) -> 31.4312 | G19: 30.05 | H19: =F19-G19 -> 1.3812
A20: Cummins 5.9L/6.7L | B20: LF3349
B21: ='Price List'!C478 -> 6.72 | F21: =SUM(B21:E21) -> 6.72 | G21: 6.36 | H21: =F21-G21 -> 0.36
A22: Cummins ISC / ISL | B22: LF9009 | D22: FF5636
B23: ='Price List'!C508 -> 32.6664 | D23: ='Price List'!C351 -> 18.144 | F23: =SUM(B23:E23) -> 50.8104 | G23: 48.5 | H23: =F23-G23 -> 2.3104
A24: Cummins ISB | B24: LF3970 | D24: FF5632
B25: ='Price List'!C498 -> 10.5184 | D25: ='Price List'!C350 -> 16.1696 | F25: =SUM(B25:E25) -> 26.688 | G25: 25.3 | H25: =F25-G25 -> 1.388
A26: Cummins ISM | B26: LF14000NN
B27: ='Price List'!C444 -> 39.8344 | F27: =SUM(B27:E27) -> 39.8344 | G27: 38.06 | H27: =F27-G27 -> 1.7744
A28: Cummins ISX | B28: LF14000NN | D28: FF5776
B29: ='Price List'!C444 -> 39.8344 | D29: ='Price List'!C354 -> 45.8152 | F29: =SUM(B29:E29) -> 85.6496 | G29: 81.78 | H29: =F29-G29 -> 3.8696
A30: Cummins M11 | B30: LF3000
B31: ='Price List'!C472 -> 31.4312 | F31: =SUM(B31:E31) -> 31.4312 | G31: 30.05 | H31: =F31-G31 -> 1.3812
A32: Detroit With Detroit Filter | B32: 23530573 | C32: 23530573 | D32: 23530706 | E32: 23530707
B33: ='Price List'!C201 -> 23.15 | C33: ='Price List'!C201 -> 23.15 | D33: ='Price List'!C202 -> 15.42 | E33: ='Price List'!C203 -> 15.9 | F33: =SUM(B33:E33) -> 77.62 | G33: 87.59 | H33: =F33-G33 -> -9.97
A34: Detroit With Detroit Filter (DD8) | B34: A9361807410 | D34: A9360900651
B35: ='Price List'!C242 -> 28.17 | D35: ='Price List'!C241 -> 140.68 | F35: =SUM(B35:E35) -> 168.85 | G35: 168.85 | H35: =F35-G35 -> 0
A36: Detroit With Detroit Filter (DD13,DD15,DD16) | B36: A4731800909 | D36: A4700903151
B37: ='Price List'!C239 -> 37 | D37: ='Price List'!C224 -> 100.79 | F37: =SUM(B37:E37) -> 137.79 | G37: 136.75 | H37: =F37-G37 -> 1.04
A38: Detroit With Fleetguard Filter (DD13,DD15.DD16) | B38: LF17511 | D38: FK13850-NN
B39: ='Price List'!C463 -> 30.6824 | D39: ='Price List'!C366 -> 83.3704 | F39: =SUM(B39:E39) -> 114.0528 | G39: 108.52 | H39: =F39-G39 -> 5.5328
A40: Detroit With Fleetguard | B40: LF3620 | C40: LF3620 | D40: FF5206 | E40: FF5207
B41: ='Price List'!C484 -> 14.8968 | C41: ='Price List'!C484 -> 14.8968 | D41: ='Price List'!C329 -> 7.4752 | E41: ='Price List'!C330 -> 8.1224 | F41: =SUM(B41:E41) -> 45.3912 | G41: 42.73 | H41: =F41-G41 -> 2.6612
A42: Duramax / Vortec 8100L | B42: LF16102
B43: ='Price List'!C449 -> 10.1024 | F43: =SUM(B43:E43) -> 10.1024 | G43: 9.36 | H43: =F43-G43 -> 0.7424
A44: F250 / F350 / F550 / F650 | B44: LF3630
B45: ='Price List'!C485 -> 14.4168 | F45: =SUM(B45:E45) -> 14.4168 | G45: 13.26 | H45: =F45-G45 -> 1.1568
A46: Hino | B46: 15613-E0110 | D46: 234011402
B47: ='Price List'!C533 -> 81.01 | D47: ='Price List'!C534 -> 14.99 | F47: =SUM(B47:E47) -> 96 | G47: 96 | H47: =F47-G47 -> 0
A48: Hino With Fleetguard | B48: LF16110 | D48: FF5138
B49: ='Price List'!C451 -> 17.8952 | D49: ='Price List'!C328 -> 9.5264 | F49: =SUM(B49:E49) -> 27.4216 | G49: 25.68 | H49: =F49-G49 -> 1.7416
A50: International | B50: LF9025 | D50: FS19684-E
B51: ='Price List'!C509 -> 39.1528 | D51: ='Price List'!C401 -> 14.416 | F51: =SUM(B51:E51) -> 53.5688 | G51: 50.78 | H51: =F51-G51 -> 2.7888
A52: International S13 | B52: 2523693C92 | D52: 112630N1
B53: ='Price List'!C548 -> 71.17 | D53: ='Price List'!C539 -> 107.63 | F53: =SUM(B53:E53) -> 178.8
A54: International Vista | B54: LF17531 | D54: FF5995
B55: ='Price List'!C467 -> 5.7728 | D55: ='Price List'!C362 -> 52.1 | F55: =SUM(B55:E55) -> 57.8728
A56: Isuzu With Fleetguard | B56: LF17537 | D56: FF5877
B57: ='Price List'!C468 -> 18.6976 | D57: ='Price List'!C358 -> 25.4432 | F57: =SUM(B57:E57) -> 44.1408 | G57: 41.95 | H57: =F57-G57 -> 2.1908
A58: Isuzu | B58: 2-90654-404-0 | D58: 2-94561-104-0
B59: ='Price List'!C563 -> 40.9 | D59: ='Price List'!C564 -> 28.07 | F59: =SUM(B59:E59) -> 68.97 | G59: 68.97 | H59: =F59-G59 -> 0
A60: MP 7 / MP8 With Fleetguard | B60: LF17503 | C60: LF17503 | D60: LF17502 | E60: FF4212800
B61: ='Price List'!C462 -> 18.0232 | C61: ='Price List'!C462 -> 18.0232 | D61: ='Price List'!C461 -> 20.8968 | E61: ='Price List'!C322 -> 29.6616 | F61: =SUM(B61:E61) -> 86.6048 | G61: 81.93 | H61: =F61-G61 -> 4.6748
A62: MP 7 / MP8 | B62: 23658111 | C62: 23658111 | D62: 21707135 | E62: 20912295
B63: ='Price List'!C582 -> 30.67 | C63: ='Price List'!C582 -> 30.67 | D63: ='Price List'!C576 -> 47.42 | E63: ='Price List'!C572 -> 64.74 | F63: =SUM(B63:E63) -> 173.5 | G63: 152.05 | H63: =F63-G63 -> 21.45
A64: Mack With Fleetguard Filter | B64: LF667 | C64: LF667 | D64: FF5381 | E64: FF5382
B65: ='Price List'!C500 -> 10.484 | C65: ='Price List'!C500 -> 10.484 | D65: ='Price List'!C342 -> 13.46 | E65: ='Price List'!C343 -> 15.956 | F65: =SUM(B65:E65) -> 50.384 | G65: 47.28 | H65: =F65-G65 -> 3.104
A66: Mack With Mack Filter | B66: 21939298 | C66: 21939298 | D66: 25502421 | E66: 25502422
B67: ='Price List'!C579 -> 34.45 | C67: ='Price List'!C579 -> 34.45 | D67: ='Price List'!C594 -> 37.91 | E67: ='Price List'!C595 -> 54.58 | F67: =SUM(B67:E67) -> 161.39 | G67: 161.39 | H67: =F67-G67 -> 0
A68: Max Force 7 | B68: 1899332C91 | D68: 1884207C92
B69: ='Price List'!C547 -> 95 | D69: ='Price List'!C546 -> 127.68 | F69: =SUM(B69:E69) -> 222.68 | G69: 139.18 | H69: =F69-G69 -> 83.5
A70: Max Force 7 With Fleetguard | B70: LF17515 | D70: FK22005
B71: ='Price List'!C465 -> 27.3928 | D71: ='Price List'!C367 -> 117.7832 | F71: =SUM(B71:E71) -> 145.176 | G71: 134.58 | H71: =F71-G71 -> 10.596
A72: Max Force 13 | B72: 3007498C94 | D72: 3004473C93
B73: ='Price List'!C555 -> 102.78 | D73: ='Price List'!C551 -> 61.91 | F73: =SUM(B73:E73) -> 164.69 | G73: 164.69 | H73: =F73-G73 -> 0
A74: Max Force 13 With Fleetguard | B74: LF17549 | D74: FS20087MX
B75: ='Price List'!C470 -> 54.304 | D75: ='Price List'!C421 -> 34.4992 | F75: =SUM(B75:E75) -> 88.8032 | G75: 83.07 | H75: =F75-G75 -> 5.7332
A76: Mercedes Benz 4000 | B76: 1802909 | D76: 5410900151
B77: ='Price List'!C620 -> 25.09 | D77: ='Price List'!C625 -> 24.92 | F77: =SUM(B77:E77) -> 50.01 | G77: 59.4 | H77: =F77-G77 -> -9.39
A78: Mercedes Benz 4000 With Fleeguard Filter | B78: LF16046 | D78: FF5405
B79: ='Price List'!C448 -> 21.396 | D79: ='Price List'!C344 -> 20.0456 | F79: =SUM(B79:E79) -> 41.4416 | G79: 38.99 | H79: =F79-G79 -> 2.4516
A80: Mercedes Benz 900 | B80: A9061800209 | D80: 901551
B81: ='Price List'!C632 -> 18.79 | D81: ='Price List'!C618 -> 28.76 | F81: =SUM(B81:E81) -> 47.55 | G81: 47.55 | H81: =F81-G81 -> 0
A82: Mercedes Benz 900 With Fleetguard Filter | B82: LF3914 | D82: FF5380
B83: ='Price List'!C495 -> 15.0568 | D83: ='Price List'!C341 -> 18.4192 | F83: =SUM(B83:E83) -> 33.476 | G83: 31.13 | H83: =F83-G83 -> 2.346
A84: Mercedes Benz Sprinter
A86: Mitsubishi | B86: QY009004 | D86: ME306306
B87: ='Price List'!C644 -> 37.84 | D87: ='Price List'!C635 -> 35.4 | F87: =SUM(B87:E87) -> 73.24 | G87: 73.24 | H87: =F87-G87 -> 0
A88: Mitsubishi With Fleetguard | B88: LF3586 | D88: FF5795
B89: ='Price List'!C483 -> 30.0488 | D89: ='Price List'!C355 -> 23.8568 | F89: =SUM(B89:E89) -> 53.9056 | H89: =F89-G89 -> 53.9056
A90: Navistar | B90: LF3883 | D90: FF5269
B91: ='Price List'!C494 -> 24.4648 | D91: ='Price List'!C332 -> 13.5616 | F91: =SUM(B91:E91) -> 38.0264 | G91: 35.6 | H91: =F91-G91 -> 2.4264
A92: Paccar | B92: 1948921PE | D92: 2277129PE
B93: ='Price List'!C684 -> 69.06 | D93: ='Price List'!C693 -> 92.99 | F93: =SUM(B93:E93) -> 162.05 | G93: 148.06 | H93: =F93-G93 -> 13.99
A94: Paccer With Fleetguard | B94: LF16233 | D94: FF252
B95: ='Price List'!C455 -> 34.372 | D95: ='Price List'!C319 -> 45.4752 | F95: =SUM(B95:E95) -> 79.8472 | G95: 75.4 | H95: =F95-G95 -> 4.4472
A96: Paccer Small | B96: LF3970 | D96: FF5632
B97: ='Price List'!C498 -> 10.5184 | D97: ='Price List'!C350 -> 16.1696 | F97: =SUM(B97:E97) -> 26.688 | G97: 25.3 | H97: =F97-G97 -> 1.388
A98: Volvo With Fleetguard | B98: LF17503 | C98: LF17503 | D98: LF17502 | E98: FF4212800
B99: ='Price List'!C462 -> 18.0232 | C99: ='Price List'!C462 -> 18.0232 | D99: ='Price List'!C461 -> 20.8968 | E99: ='Price List'!C322 -> 29.6616 | F99: =SUM(B99:E99) -> 86.6048 | G99: 81.93 | H99: =F99-G99 -> 4.6748
A100: Volvo With Volvo Filter | B100: 23658092 | C100: 23658092 | D100: 21707132 | E100: 23920469
B101: ='Price List'!C798 -> 29.24 | C101: ='Price List'!C798 -> 29.24 | D101: ='Price List'!C790 -> 45.24 | E101: ='Price List'!C800 -> 62.57 | F101: =SUM(B101:E101) -> 166.29 | G101: 158.12 | H101: =F101-G101 -> 8.17

Sheet 15W40
A1: STANDARD JOB LIST | B1: 15W40 | G1: 4.2 | H1: 0.05
B2: selling | C2: cost | E2: Filtre | F2: Litre | G2: Oil | H2: Fuel | I2: Profit | J2: Cost % | K2: Profit %
A3: Auto Greaser Refill | B3: 39.99 | E3: Cost | G3: Cost | H3: Grease | L3: Last Month | M3: Profit Diff | N3: Last Month | O3: Last Month
A4: Jan 1,2026 | G4: =G1+H1 -> 4.25 | J4: 1 | L4: Profit | N4: Price | O4: Price Diff
A6: C 7 / 10 / 3126 With Cat Filter | B6: 265.99 | C6: =E6+G6+H6 -> 167.54 | E6: ='Filter Cost'!F7 -> 53.29 | F6: 25 | G6: =F6*G4 -> 106.25 | H6: 8 | I6: =B6-C6 -> 98.45 | J6: =C6/B6 -> 0.6298733 | K6: =1-J6 -> 0.3701267 | L6: 98.45 | M6: =I6-L6 -> 0 | N6: 265.99 | O6: =B6-N6 -> 0
A7: C 7 / 10 / 3126 With Fleetguard Filter | B7: 243.99 | C7: =E7+G7+H7 -> 136.0492 | E7: ='Filter Cost'!F9 -> 21.7992 | F7: 25 | G7: =F7*G4 -> 106.25 | H7: 8 | I7: =B7-C7 -> 107.9408 | J7: =C7/B7 -> 0.55760154 | K7: =1-J7 -> 0.44239846 | L7: 106.69 | M7: =I7-L7 -> 1.2508 | N7: 243.99 | O7: =B7-N7 -> 0
A9: C 12 / 3406 With Cat Filter | B9: 334.99 | C9: =E9+G9+H9 -> 240.08 | E9: ='Filter Cost'!F11 -> 70.58 | F9: 38 | G9: =F9*G4 -> 161.5 | H9: 8 | I9: =B9-C9 -> 94.91 | J9: =C9/B9 -> 0.71667811 | K9: =1-J9 -> 0.28332189 | L9: 94.91 | M9: =I9-L9 -> 0 | N9: 334.99 | O9: =B9-N9 -> 0
A10: C 12 / 3406 With Fleetguard Filter | B10: 293.99 | C10: =E10+G10+H10 -> 200.5448 | E10: ='Filter Cost'!F13 -> 31.0448 | F10: 38 | G10: =F10*G4 -> 161.5 | H10: 8 | I10: =B10-C10 -> 93.4452 | J10: =C10/B10 -> 0.68214837 | K10: =1-J10 -> 0.31785163 | L10: 93.35 | M10: =I10-L10 -> 0.0952 | N10: 293.99 | O10: =B10-N10 -> 0
A12: C 13 / 15 With Cat Filter | B12: 354.99 | C12: =E12+G12+H12 -> 261.33 | E12: ='Filter Cost'!F15 -> 70.58 | F12: 43 | G12: =F12*G4 -> 182.75 | H12: 8 | I12: =B12-C12 -> 93.66 | J12: =C12/B12 -> 0.73616158 | K12: =1-J12 -> 0.26383842 | L12: 93.66 | M12: =I12-L12 -> 0 | N12: 354.99 | O12: =B12-N12 -> 0
A13: C 13 / 15 With Fleetguard Filter | B13: 313.99 | C13: =E13+G13+H13 -> 221.7948 | E13: ='Filter Cost'!F17 -> 31.0448 | F13: 43 | G13: =F13*G4 -> 182.75 | H13: 8 | I13: =B13-C13 -> 92.1952 | J13: =C13/B13 -> 0.70637536 | K13: =1-J13 -> 0.29362464 | L13: 92.1 | M13: =I13-L13 -> 0.0952 | N13: 313.99 | O13: =B13-N13 -> 0
A15: Cummins N14 | B15: 301.99 | C15: =E15+G15+H15 -> 209.4312 | E15: ='Filter Cost'!F19 -> 31.4312 | F15: 40 | G15: =F15*G4 -> 170 | H15: 8 | I15: =B15-C15 -> 92.5588 | J15: =C15/B15 -> 0.69350376 | K15: =1-J15 -> 0.30649624 | L15: 92.46 | M15: =I15-L15 -> 0.0988 | N15: 301.99 | O15: =B15-N15 -> 0
A16: Cummins 5.9L/6.7L | B16: 170.99 | C16: =E16+G16+H16 -> 74.22 | E16: ='Filter Cost'!F21 -> 6.72 | F16: 14 | G16: =F16*G4 -> 59.5 | H16: 8 | I16: =B16-C16 -> 96.77 | J16: =C16/B16 -> 0.43406047 | K16: =1-J16 -> 0.56593953 | L16: 96.81 | M16: =I16-L16 -> -0.04 | N16: 170.99 | O16: =B16-N16 -> 0
A17: Cummins ISC / ISL | B17: 257.99 | C17: =E17+G17+H17 -> 165.0604 | E17: ='Filter Cost'!F23 -> 50.8104 | F17: 25 | G17: =F17*G4 -> 106.25 | H17: 8 | I17: =B17-C17 -> 92.9296 | J17: =C17/B17 -> 0.63979379 | K17: =1-J17 -> 0.36020621 | L17: 92.86 | M17: =I17-L17 -> 0.0696 | N17: 257.99 | O17: =B17-N17 -> 0
A18: Cummins ISB | B18: 255.99 | C18: =E18+G18+H18 -> 140.938 | E18: ='Filter Cost'!F25 -> 26.688 | F18: 25 | G18: =F18*G4 -> 106.25 | H18: 8 | I18: =B18-C18 -> 115.052 | J18: =C18/B18 -> 0.55056057 | K18: =1-J18 -> 0.44943943 | L18: 115.07 | M18: =I18-L18 -> -0.018 | N18: 255.99 | O18: =B18-N18 -> 0
A19: Cummins ISM | B19: 292.99 | C19: =E19+G19+H19 -> 200.8344 | E19: ='Filter Cost'!F27 -> 39.8344 | F19: 36 | G19: =F19*G4 -> 153 | H19: 8 | I19: =B19-C19 -> 92.1556 | J19: =C19/B19 -> 0.68546503 | K19: =1-J19 -> 0.31453497 | L19: 92.03 | M19: =I19-L19 -> 0.1256 | N19: 292.99 | O19: =B19-N19 -> 0
A20: Cummins ISX / X15 | B20: 378.99 | C20: =E20+G20+H20 -> 280.6496 | E20: ='Filter Cost'!F29 -> 85.6496 | F20: 44 | G20: =F20*G4 -> 187 | H20: 8 | I20: =B20-C20 -> 98.3404 | J20: =C20/B20 -> 0.7405198 | K20: =1-J20 -> 0.2594802 | L20: 98.06 | M20: =I20-L20 -> 0.2804 | N20: 378.99 | O20: =B20-N20 -> 0
A21: Cummins M11 | B21: 275.99 | C21: =E21+G21+H21 -> 183.9312 | E21: ='Filter Cost'!F31 -> 31.4312 | F21: 34 | G21: =F21*G4 -> 144.5 | H21: 8 | I21: =B21-C21 -> 92.0588 | J21: =C21/B21 -> 0.66644154 | K21: =1-J21 -> 0.33355846 | L21: 91.96 | M21: =I21-L21 -> 0.0988 | N21: 275.99 | O21: =B21-N21 -> 0
A23: Detroit With Detroit Filter | B23: 349.99 | C23: =E23+G23+H23 -> 247.12 | E23: ='Filter Cost'!F33 -> 77.62 | F23: 38 | G23: =F23*G4 -> 161.5 | H23: 8 | I23: =B23-C23 -> 102.87 | J23: =C23/B23 -> 0.70607732 | K23: =1-J23 -> 0.29392268 | L23: 105.87 | M23: =I23-L23 -> -3 | N23: 352.99 | O23: =B23-N23 -> -3
A24: Detroit With Detroit Filter (DD8) | B24: 409.99 | C24: =E24+G24+H24 -> 312.85 | E24: ='Filter Cost'!F35 -> 168.85 | F24: 32 | G24: =F24*G4 -> 136 | H24: 8 | I24: =B24-C24 -> 97.14 | J24: =C24/B24 -> 0.76306739 | K24: =1-J24 -> 0.23693261 | L24: 97.14 | M24: =I24-L24 -> 0 | N24: 409.99 | O24: =B24-N24 -> 0
A25: Detroit With Detroit Filter (DD13,DD15,DD16) | B25: 415.99 | C25: =E25+G25+H25 -> 324.29 | E25: ='Filter Cost'!F37 -> 137.79 | F25: 42 | G25: =F25*G4 -> 178.5 | H25: 8 | I25: =B25-C25 -> 91.7 | J25: =C25/B25 -> 0.77956201 | K25: =1-J25 -> 0.22043799 | L25: 90.84 | M25: =I25-L25 -> 0.86 | N25: 415.99 | O25: =B25-N25 -> 0
A26: Detroit With Fleetguard Filter (DD13,DD15.DD16) | B26: 393.99 | C26: =E26+G26+H26 -> 300.5528 | E26: ='Filter Cost'!F39 -> 114.0528 | F26: 42 | G26: =F26*G4 -> 178.5 | H26: 8 | I26: =B26-C26 -> 93.4372 | J26: =C26/B26 -> 0.76284373 | K26: =1-J26 -> 0.23715627 | L26: 92.77 | M26: =I26-L26 -> 0.6672 | N26: 393.99 | O26: =B26-N26 -> 0
A27: Detroit With Fleetguard | B27: 302.99 | C27: =E27+G27+H27 -> 214.8912 | E27: ='Filter Cost'!F41 -> 45.3912 | F27: 38 | G27: =F27*G4 -> 161.5 | H27: 8 | I27: =B27-C27 -> 88.0988 | J27: =C27/B27 -> 0.70923529 | K27: =1-J27 -> 0.29076471 | L27: 90.07 | M27: =I27-L27 -> -1.9712 | N27: 304.99 | O27: =B27-N27 -> -2
A28: Duramax / Vortec 8100L | B28: 170.99 | C28: =E28+G28+H28 -> 77.6024 | E28: ='Filter Cost'!F43 -> 10.1024 | F28: 14 | G28: =F28*G4 -> 59.5 | H28: 8 | I28: =B28-C28 -> 93.3876 | J28: =C28/B28 -> 0.45384175 | K28: =1-J28 -> 0.54615825 | L28: 93.45 | M28: =I28-L28 -> -0.0624 | N28: 170.99 | O28: =B28-N28 -> 0
A30: F250 / F350 / F550 / F650 | B30: 170.99 | C30: =E30+G30+H30 -> 81.9168 | E30: ='Filter Cost'!F45 -> 14.4168 | F30: 14 | G30: =F30*G4 -> 59.5 | H30: 8 | I30: =B30-C30 -> 89.0732 | J30: =C30/B30 -> 0.47907363 | K30: =1-J30 -> 0.52092637 | L30: 89.16 | M30: =I30-L30 -> -0.0868 | N30: 170.99 | O30: =B30-N30 -> 0
A32: Hino | B32: 269.99 | C32: =E32+G32+H32 -> 163.5 | E32: ='Filter Cost'!F47 -> 96 | F32: 14 | G32: =F32*G4 -> 59.5 | H32: 8 | I32: =B32-C32 -> 106.49 | J32: =C32/B32 -> 0.60557798 | K32: =1-J32 -> 0.39442202 | L32: 106.49 | M32: =I32-L32 -> 0 | N32: 269.99 | O32: =B32-N32 -> 0
A33: Hino With Fleetguard | B33: 199.99 | C33: =E33+G33+H33 -> 94.9216 | E33: ='Filter Cost'!F49 -> 27.4216 | F33: 14 | G33: =F33*G4 -> 59.5 | H33: 8 | I33: =B33-C33 -> 105.0684 | J33: =C33/B33 -> 0.47463173 | K33: =1-J33 -> 0.52536827 | L33: 105.24 | M33: =I33-L33 -> -0.1716 | N33: 199.99 | O33: =B33-N33 -> 0
A35: International | B35: 265.99 | C35: =E35+G35+H35 -> 172.0688 | E35: ='Filter Cost'!F51 -> 53.5688 | F35: 26 | G35: =F35*G4 -> 110.5 | H35: 8 | I35: =B35-C35 -> 93.9212 | J35: =C35/B35 -> 0.64689951 | K35: =1-J35 -> 0.35310049 | L35: 94.15 | M35: =I35-L35 -> -0.2288 | N35: 265.99 | O35: =B35-N35 -> 0
A36: International S13 | B36: 499.99 | C36: =E36+G36+H36 -> 382.3 | E36: ='Filter Cost'!F53 -> 178.8 | F36: 46 | G36: =F36*G4 -> 195.5 | H36: 8 | I36: =B36-C36 -> 117.69 | J36: =C36/B36 -> 0.76461529 | K36: =1-J36 -> 0.23538471 | L36: 117.69
A37: International Vista | B37: 249.99 | C37: =E37+G37+H37 -> 125.3728 | E37: ='Filter Cost'!F55 -> 57.8728 | F37: 14 | G37: =F37*G4 -> 59.5 | H37: 8 | I37: =B37-C37 -> 124.6172 | J37: =C37/B37 -> 0.50151126 | K37: =1-J37 -> 0.49848874
A38: Isuzu With Fleetguard Filter | B38: 215.99 | C38: =E38+G38+H38 -> 111.6408 | E38: ='Filter Cost'!F57 -> 44.1408 | F38: 14 | G38: =F38*G4 -> 59.5 | H38: 8 | I38: =B38-C38 -> 104.3492 | J38: =C38/B38 -> 0.51687949 | K38: =1-J38 -> 0.48312051 | L38: 104.51 | M38: =I38-L38 -> -0.1608 | N38: 215.99 | O38: =B38-N38 -> 0
A39: Isuzu | B39: 275.99 | C39: =E39+G39+H39 -> 136.47 | E39: ='Filter Cost'!F59 -> 68.97 | F39: 14 | G39: =F39*G4 -> 59.5 | H39: 8 | I39: =B39-C39 -> 139.52 | J39: =C39/B39 -> 0.49447444 | K39: =1-J39 -> 0.50552556 | L39: 139.52 | M39: =I39-L39 -> 0 | N39: 275.99 | O39: =B39-N39 -> 0
A41: MP 7 / MP8 With Fleetguard | B41: 363.99 | C41: =E41+G41+H41 -> 256.1048 | E41: ='Filter Cost'!F61 -> 86.6048 | F41: 38 | G41: =F41*G4 -> 161.5 | H41: 8 | I41: =B41-C41 -> 107.8852 | J41: =C41/B41 -> 0.70360395 | K41: =1-J41 -> 0.29639605 | L41: 108.06 | M41: =I41-L41 -> -0.1748 | N41: 363.99 | O41: =B41-N41 -> 0
A42: MP 7 / MP8 With Mack | B42: 434.99 | C42: =E42+G42+H42 -> 343 | E42: ='Filter Cost'!F63 -> 173.5 | F42: 38 | G42: =F42*G4 -> 161.5 | H42: 8 | I42: =B42-C42 -> 91.99 | J42: =C42/B42 -> 0.78852387 | K42: =1-J42 -> 0.21147613 | L42: 84.75 | M42: =I42-L42 -> 7.24 | N42: 419.99 | O42: =B42-N42 -> 15
A43: MP 7/MP8/ MP10 With Fleetguard ( 52L) | B43: 436.99 | C43: =E43+G43+H43 -> 328.3548 | E43: ='Filter Cost'!F61 -> 86.6048 | F43: 55 | G43: =F43*G4 -> 233.75 | H43: 8 | I43: =B43-C43 -> 108.6352 | J43: =C43/B43 -> 0.75140118 | K43: =1-J43 -> 0.24859882 | L43: 108.81 | M43: =I43-L43 -> -0.1748 | N43: 436.99 | O43: =B43-N43 -> 0
A44: MP 7/MP8/ MP10 With Mack (52L) | B44: 509.99 | C44: =E44+G44+H44 -> 415.25 | E44: ='Filter Cost'!F63 -> 173.5 | F44: 55 | G44: =F44*G4 -> 233.75 | H44: 8 | I44: =B44-C44 -> 94.74 | J44: =C44/B44 -> 0.81423165 | K44: =1-J44 -> 0.18576835 | L44: 87.5 | M44: =I44-L44 -> 7.24 | N44: 494.99 | O44: =B44-N44 -> 15
A45: Mack With Fleetguard Filter | B45: 317.99 | C45: =E45+G45+H45 -> 219.884 | E45: ='Filter Cost'!F65 -> 50.384 | F45: 38 | G45: =F45*G4 -> 161.5 | H45: 8 | I45: =B45-C45 -> 98.106 | J45: =C45/B45 -> 0.69148086 | K45: =1-J45 -> 0.30851914 | L45: 98.22 | M45: =I45-L45 -> -0.114 | N45: 317.99 | O45: =B45-N45 -> 0
A46: Mack With Fleetguard Filter(52L) | B46: 377.99 | C46: =E46+G46+H46 -> 279.384 | E46: ='Filter Cost'!F65 -> 50.384 | F46: 52 | G46: =F46*G4 -> 221 | H46: 8 | I46: =B46-C46 -> 98.606 | J46: =C46/B46 -> 0.73913066 | K46: =1-J46 -> 0.26086934 | L46: 98.72 | M46: =I46-L46 -> -0.114 | N46: 377.99 | O46: =B46-N46 -> 0
A47: Mack With Mack Filter | B47: 426.99 | C47: =E47+G47+H47 -> 330.89 | E47: ='Filter Cost'!F67 -> 161.39 | F47: 38 | G47: =F47*G4 -> 161.5 | H47: 8 | I47: =B47-C47 -> 96.1 | J47: =C47/B47 -> 0.77493618 | K47: =1-J47 -> 0.22506382 | L47: 96.1 | M47: =I47-L47 -> 0 | N47: 426.99 | O47: =B47-N47 -> 0
A48: Mack With Mack Filter( 52L ) | B48: 489.99 | C48: =E48+G48+H48 -> 390.39 | E48: ='Filter Cost'!F67 -> 161.39 | F48: 52 | G48: =F48*G4 -> 221 | H48: 8 | I48: =B48-C48 -> 99.6 | J48: =C48/B48 -> 0.79673055 | K48: =1-J48 -> 0.20326945 | L48: 99.6 | M48: =I48-L48 -> 0 | N48: 489.99 | O48: =B48-N48 -> 0
A50: Max Force 7 / 9 / 10 | B50: 435.99 | C50: =E50+G50+H50 -> 341.18 | E50: ='Filter Cost'!F69 -> 222.68 | F50: 26 | G50: =F50*G4 -> 110.5 | H50: 8 | I50: =B50-C50 -> 94.81 | J50: =C50/B50 -> 0.78254088 | K50: =1-J50 -> 0.21745912 | L50: 95.31 | M50: =I50-L50 -> -0.5 | N50: 352.99 | O50: =B50-N50 -> 83 | P50: Fleetguard and OEM Price
A51: Max Force 7 / 9 / 10 With Fleetguard | B51: 356.99 | C51: =E51+G51+H51 -> 263.676 | E51: ='Filter Cost'!F71 -> 145.176 | F51: 26 | G51: =F51*G4 -> 110.5 | H51: 8 | I51: =B51-C51 -> 93.314 | J51: =C51/B51 -> 0.73860892 | K51: =1-J51 -> 0.26139108 | L51: 94.25 | M51: =I51-L51 -> -0.936 | N51: 356.99 | O51: =B51-N51 -> 0
A52: Max Force 13 | B52: 434.99 | C52: =E52+G52+H52 -> 334.19 | E52: ='Filter Cost'!F73 -> 164.69 | F52: 38 | G52: =F52*G4 -> 161.5 | H52: 8 | I52: =B52-C52 -> 100.8 | J52: =C52/B52 -> 0.76827053 | K52: =1-J52 -> 0.23172947 | L52: 100.8 | M52: =I52-L52 -> 0 | N52: 434.99 | O52: =B52-N52 -> 0
A53: Max Force 13 With Fleetguard | B53: 356.99 | C53: =E53+G53+H53 -> 258.3032 | E53: ='Filter Cost'!F75 -> 88.8032 | F53: 38 | G53: =F53*G4 -> 161.5 | H53: 8 | I53: =B53-C53 -> 98.6868 | J53: =C53/B53 -> 0.72355864 | K53: =1-J53 -> 0.27644136 | L53: 94.44 | M53: =I53-L53 -> 4.2468 | N53: 351.99 | O53: =B53-N53 -> 5
A55: Mercedes Benz 4000 | B55: 364.99 | C55: =E55+G55+H55 -> 257.76 | E55: ='Filter Cost'!F77 -> 50.01 | F55: 47 | G55: =F55*G4 -> 199.75 | H55: 8 | I55: =B55-C55 -> 107.23 | J55: =C55/B55 -> 0.70621113 | K55: =1-J55 -> 0.29378887 | L55: 107.23 | M55: =I55-L55 -> 0 | N55: 364.99 | O55: =B55-N55 -> 0
A56: Mercedes Benz 4000 With Fleeguard Filter | B56: 342.99 | C56: =E56+G56+H56 -> 249.1916 | E56: ='Filter Cost'!F79 -> 41.4416 | F56: 47 | G56: =F56*G4 -> 199.75 | H56: 8 | I56: =B56-C56 -> 93.7984 | J56: =C56/B56 -> 0.7265273 | K56: =1-J56 -> 0.2734727 | L56: 94.06 | M56: =I56-L56 -> -0.2616 | N56: 342.99 | O56: =B56-N56 -> 0
A57: Mercedes Benz 900 | B57: 279.99 | C57: =E57+G57+H57 -> 166.05 | E57: ='Filter Cost'!F81 -> 47.55 | F57: 26 | G57: =F57*G4 -> 110.5 | H57: 8 | I57: =B57-C57 -> 113.94 | J57: =C57/B57 -> 0.59305689 | K57: =1-J57 -> 0.40694311 | L57: 113.94 | M57: =I57-L57 -> 0 | N57: 279.99 | O57: =B57-N57 -> 0
A58: Mercedes Benz 900 With Fleetguard Filter | B58: 241.99 | C58: =E58+G58+H58 -> 151.976 | E58: ='Filter Cost'!F83 -> 33.476 | F58: 26 | G58: =F58*G4 -> 110.5 | H58: 8 | I58: =B58-C58 -> 90.014 | J58: =C58/B58 -> 0.62802595 | K58: =1-J58 -> 0.37197405 | L58: 90.22 | M58: =I58-L58 -> -0.206 | N58: 241.99 | O58: =B58-N58 -> 0
A59: Mercedes Benz Sprinter | B59: 219.99 | C59: =E59+G59+H59 -> 110 | E59: ='Filter Cost'!F85 -> 0 | F59: 24 | G59: =F59*G4 -> 102 | H59: 8 | I59: =B59-C59 -> 109.99 | J59: =C59/B59 -> 0.50002273 | K59: =1-J59 -> 0.49997727 | L59: 211.99 | M59: =I59-L59 -> -102 | N59: 219.99 | O59: =B59-N59 -> 0
A60: Mitsubushi | B60: 229.99 | C60: =E60+G60+H60 -> 136.49 | E60: ='Filter Cost'!F87 -> 73.24 | F60: 13 | G60: =F60*G4 -> 55.25 | H60: 8 | I60: =B60-C60 -> 93.5 | J60: =C60/B60 -> 0.59346059 | K60: =1-J60 -> 0.40653941 | L60: 93.5 | M60: =I60-L60 -> 0 | N60: 229.99 | O60: =B60-N60 -> 0
A63: Navistar | B63: 246.99 | C63: =E63+G63+H63 -> 156.5264 | E63: ='Filter Cost'!F91 -> 38.0264 | F63: 26 | G63: =F63*G4 -> 110.5 | H63: 8 | I63: =B63-C63 -> 90.4636 | J63: =C63/B63 -> 0.63373578 | K63: =1-J63 -> 0.36626422 | L63: 90.63 | M63: =I63-L63 -> -0.1664 | N63: 246.99 | O63: =B63-N63 -> 0
A65: Paccer | B65: 458.99 | C65: =E65+G65+H65 -> 365.55 | E65: ='Filter Cost'!F93 -> 162.05 | F65: 46 | G65: =F65*G4 -> 195.5 | H65: 8 | I65: =B65-C65 -> 93.44 | J65: =C65/B65 -> 0.79642258 | K65: =1-J65 -> 0.20357742 | L65: 83.44 | M65: =I65-L65 -> 10 | N65: 448.99 | O65: =B65-N65 -> 10
A66: Paccer With Fleetguard | B66: 379.99 | C66: =E66+G66+H66 -> 283.3472 | E66: ='Filter Cost'!F95 -> 79.8472 | F66: 46 | G66: =F66*G4 -> 195.5 | H66: 8 | I66: =B66-C66 -> 96.6428 | J66: =C66/B66 -> 0.74567015 | K66: =1-J66 -> 0.25432985 | L66: 97.06 | M66: =I66-L66 -> -0.4172 | N66: 379.99 | O66: =B66-N66 -> 0
A67: Paccer Small | B67: 229.99 | C67: =E67+G67+H67 -> 136.688 | E67: ='Filter Cost'!F97 -> 26.688 | F67: 24 | G67: =F67*G4 -> 102 | H67: 8 | I67: =B67-C67 -> 93.302 | J67: =C67/B67 -> 0.59432149 | K67: =1-J67 -> 0.40567851 | L67: 93.32 | M67: =I67-L67 -> -0.018 | N67: 229.99 | O67: =B67-N67 -> 0
A69: Volvo With Fleetguard | B69: 345.99 | C69: =E69+G69+H69 -> 239.1048 | E69: ='Filter Cost'!F99 -> 86.6048 | F69: 34 | G69: =F69*G4 -> 144.5 | H69: 8 | I69: =B69-C69 -> 106.8852 | J69: =C69/B69 -> 0.69107431 | K69: =1-J69 -> 0.30892569 | L69: 107.06 | M69: =I69-L69 -> -0.1748 | N69: 345.99 | O69: =B69-N69 -> 0
A70: Volvo With Fleetguard(D16 42L) | B70: 379.99 | C70: =E70+G70+H70 -> 273.1048 | E70: ='Filter Cost'!F99 -> 86.6048 | F70: 42 | G70: =F70*G4 -> 178.5 | H70: 8 | I70: =B70-C70 -> 106.8852 | J70: =C70/B70 -> 0.71871576 | K70: =1-J70 -> 0.28128424 | L70: 107.06 | M70: =I70-L70 -> -0.1748 | N70: 379.99 | O70: =B70-N70 -> 0
A71: Volvo With Fleetguard(D16 52L) | B71: 424.99 | C71: =E71+G71+H71 -> 315.6048 | E71: ='Filter Cost'!F99 -> 86.6048 | F71: 52 | G71: =F71*G4 -> 221 | H71: 8 | I71: =B71-C71 -> 109.3852 | J71: =C71/B71 -> 0.742617 | K71: =1-J71 -> 0.257383 | L71: 109.56 | M71: =I71-L71 -> -0.1748 | N71: 424.99 | O71: =B71-N71 -> 0
A72: Volvo With Volvo Filter | B72: 414.99 | C72: =E72+G72+H72 -> 318.79 | E72: ='Filter Cost'!F101 -> 166.29 | F72: 34 | G72: =F72*G4 -> 144.5 | H72: 8 | I72: =B72-C72 -> 96.2 | J72: =C72/B72 -> 0.76818719 | K72: =1-J72 -> 0.23181281 | L72: 106.65 | M72: =I72-L72 -> -10.45 | N72: 414.99 | O72: =B72-N72 -> 0
A73: Volvo With Volvo Filter (D16 42L) | B73: 449.99 | C73: =E73+G73+H73 -> 352.79 | E73: ='Filter Cost'!F101 -> 166.29 | F73: 42 | G73: =F73*G4 -> 178.5 | H73: 8 | I73: =B73-C73 -> 97.2 | J73: =C73/B73 -> 0.7839952 | K73: =1-J73 -> 0.2160048 | L73: 107.65 | M73: =I73-L73 -> -10.45 | N73: 449.99 | O73: =B73-N73 -> 0
A74: Volvo With Volvo Filter (D16 52L) | B74: 492.99 | C74: =E74+G74+H74 -> 395.29 | E74: ='Filter Cost'!F101 -> 166.29 | F74: 52 | G74: =F74*G4 -> 221 | H74: 8 | I74: =B74-C74 -> 97.7 | J74: =C74/B74 -> 0.80182154 | K74: =1-J74 -> 0.19817846 | L74: 108.15 | M74: =I74-L74 -> -10.45 | N74: 492.99 | O74: =B74-N74 -> 0
K76: =SUM(K6:K74)/53 -> 0.33595552
A78: Nanak Shahi ( 15W40 ) Det 60 | B78: =B27-75 -> 227.99 | C78: 229.99
A79: J & J Trans ( T6 ) DD15 | B79: ='T6'!B25-95 -> 458.27 | C79: 485.99
A80: 2071607 Ont ( 15W40 ) ISX | B80: =B20-70 -> 308.99 | C80: 274.99
A85: Cummins ISX / X12 / 15
A86: LF14000 | B86: 38.06 | C86: 37
A87: FF5776 | B87: 43.12 | C87: 19.36
A88: FF5825 | B88: 50.18
A89: FF5971 | B89: 62.82
A90: QTL1010 | B90: 3 | C90: 3
A91: QTL1011 | B91: 2.64 | C91: 2.64
A92: Grease | B92: 8 | C92: 8
A93: Oil | B93: 4.25 | C93: 187
C95: =SUM(C86:C93) -> 257
A97: FF2200 | B97: 19.59
A101: 23658092 | B101: 27.93
A102: 23658092 | B102: 27.93
A103: 21707132 | B103: 45.24
A104: 22480372 | B104: 36.57
A105: 23920469 | B105: 59.23
A106: 23151592 | B106: 27.58
A107: 23151592 | B107: 27.58
A108: 4.30 Oil | B108: =4.3*34 -> 146.2
A109: Fuel | B109: 1.78
A110: 4 Filter MHSW | B110: 6
A111: 3 Filter MHSW | B111: 4.5
A113: Oil MHSW | B113: 2.04
A114: Grease | B114: 8
G115: 439.99
B116: Cost | D116: Fro
A117: Regular 4 oil Fuel 0372 | B117: =B101+B102+B103+B104+B108+B109+B110+B113+B114 -> 301.69 | C117: 20 | D117: =G115-B117-C117 -> 118.3
A118: Regular 4 oil Fuel 0469 | B118: =B101+B102+B103+B105+B108+B109+B110+B113+B114 -> 324.35 | D118: =G115-B118-C118 -> 115.64
A120: New 3 Fuel | B120: =B106+B107+B105+B108+B109+B111+B113+B114 -> 276.91 | D120: =G115-B120-C120 -> 163.08

Sheet 15W40 Gallon
A1: STANDARD JOB LIST | B1: 15W40 | G1: 5.67 | H1: 0.05 | L1: 8--20 | M1: 10
B2: selling | C2: cost | E2: Filtre | F2: Litre | G2: Oil | H2: Fuel | I2: Profit | J2: Cost | K2: Profit | L2: 21--38 | M2: 15
A3: Auto Greaser Refill | E3: Cost | G3: Cost | H3: Grease | L3: 39--46 | M3: 20
G4: =G1+H1 -> 5.72 | J4: 1 | L4: 47& UP | M4: 25
M5: Price Diff | N5: Cost Diff
A6: C 7 / 10 / 3126 With Cat Filter | B6: ='15W40'!B6+('15W40 Gallon'!G4-'15W40'!G4)*'15W40 Gallon'!F6+'15W40 Gallon'!M2 -> 317.74 | C6: =E6+G6+H6 -> 204.29 | E6: ='15W40'!E6 -> 53.29 | F6: ='15W40'!F6 -> 25 | G6: =F6*G4 -> 143 | H6: 8 | I6: =B6-C6 -> 113.45 | J6: =C6/B6 -> 0.64294706 | K6: =1-J6 -> 0.35705294 | M6: =B6-'15W40'!B6 -> 51.75 | N6: =C6-'15W40'!C6 -> 36.75
A7: C 7 / 10 / 3126 With Fleetguard Filter | B7: ='15W40'!B7+('15W40 Gallon'!G4-'15W40'!G4)*'15W40 Gallon'!F7+'15W40 Gallon'!M2 -> 295.74 | C7: =E7+G7+H7 -> 172.7992 | E7: ='15W40'!E7 -> 21.7992 | F7: ='15W40'!F7 -> 25 | G7: =F7*G4 -> 143 | H7: 8 | I7: =B7-C7 -> 122.9408 | J7: =C7/B7 -> 0.58429431 | K7: =1-J7 -> 0.41570569 | M7: =B7-'15W40'!B7 -> 51.75 | N7: =C7-'15W40'!C7 -> 36.75
A9: C 12 / 3406 With Cat Filter | B9: ='15W40'!B9+('15W40 Gallon'!G4-'15W40'!G4)*'15W40 Gallon'!F9+'15W40 Gallon'!M2 -> 405.85 | C9: =E9+G9+H9 -> 295.94 | E9: ='15W40'!E9 -> 70.58 | F9: ='15W40'!F9 -> 38 | G9: =F9*G4 -> 217.36 | H9: 8 | I9: =B9-C9 -> 109.91 | J9: =C9/B9 -> 0.72918566 | K9: =1-J9 -> 0.27081434 | M9: =B9-'15W40'!B9 -> 70.86 | N9: =C9-'15W40'!C9 -> 55.86
A10: C 12 / 3406 With Fleetguard Filter | B10: ='15W40'!B10+('15W40 Gallon'!G4-'15W40'!G4)*'15W40 Gallon'!F10+'15W40 Gallon'!M2 -> 364.85 | C10: =E10+G10+H10 -> 256.4048 | E10: ='15W40'!E10 -> 31.0448 | F10: ='15W40'!F10 -> 38 | G10: =F10*G4 -> 217.36 | H10: 8 | I10: =B10-C10 -> 108.4452 | J10: =C10/B10 -> 0.70276771 | K10: =1-J10 -> 0.29723229 | M10: =B10-'15W40'!B10 -> 70.86 | N10: =C10-'15W40'!C10 -> 55.86
A12: C 13 / 15 With Cat Filter | B12: ='15W40'!B12+('15W40 Gallon'!G4-'15W40'!G4)*'15W40 Gallon'!F12+'15W40 Gallon'!M3 -> 438.2 | C12: =E12+G12+H12 -> 324.54 | E12: ='15W40'!E12 -> 70.58 | F12: ='15W40'!F12 -> 43 | G12: =F12*G4 -> 245.96 | H12: 8 | I12: =B12-C12 -> 113.66 | J12: =C12/B12 -> 0.74062072 | K12: =1-J12 -> 0.25937928 | M12: =B12-'15W40'!B12 -> 83.21 | N12: =C12-'15W40'!C12 -> 63.21
A13: C 13 / 15 With Fleetguard Filter | B13: ='15W40'!B13+('15W40 Gallon'!G4-'15W40'!G4)*'15W40 Gallon'!F13+'15W40 Gallon'!M3 -> 397.2 | C13: =E13+G13+H13 -> 285.0048 | E13: ='15W40'!E13 -> 31.0448 | F13: ='15W40'!F13 -> 43 | G13: =F13*G4 -> 245.96 | H13: 8 | I13: =B13-C13 -> 112.1952 | J13: =C13/B13 -> 0.71753474 | K13: =1-J13 -> 0.28246526 | M13: =B13-'15W40'!B13 -> 83.21 | N13: =C13-'15W40'!C13 -> 63.21
A15: Cummins N14 | B15: ='15W40'!B15+('15W40 Gallon'!G4-'15W40'!G4)*'15W40 Gallon'!F15+'15W40 Gallon'!M3 -> 380.79 | C15: =E15+G15+H15 -> 268.2312 | E15: ='15W40'!E15 -> 31.4312 | F15: ='15W40'!F15 -> 40 | G15: =F15*G4 -> 228.8 | H15: 8 | I15: =B15-C15 -> 112.5588 | J15: =C15/B15 -> 0.70440715 | K15: =1-J15 -> 0.29559285 | M15: =B15-'15W40'!B15 -> 78.8 | N15: =C15-'15W40'!C15 -> 58.8
A16: Cummins 5.9L/6.7L | B16: ='15W40'!B16+('15W40 Gallon'!G4-'15W40'!G4)*'15W40 Gallon'!F16+'15W40 Gallon'!M1 -> 201.57 | C16: =E16+G16+H16 -> 94.8 | E16: ='15W40'!E16 -> 6.72 | F16: ='15W40'!F16 -> 14 | G16: =F16*G4 -> 80.08 | H16: 8 | I16: =B16-C16 -> 106.77 | J16: =C16/B16 -> 0.47030808 | K16: =1-J16 -> 0.52969192 | M16: =B16-'15W40'!B16 -> 30.58 | N16: =C16-'15W40'!C16 -> 20.58
A17: Cummins ISC / ISL | B17: ='15W40'!B17+('15W40 Gallon'!G4-'15W40'!G4)*'15W40 Gallon'!F17+'15W40 Gallon'!M2 -> 309.74 | C17: =E17+G17+H17 -> 201.8104 | E17: ='15W40'!E17 -> 50.8104 | F17: ='15W40'!F17 -> 25 | G17: =F17*G4 -> 143 | H17: 8 | I17: =B17-C17 -> 107.9296 | J17: =C17/B17 -> 0.65154775 | K17: =1-J17 -> 0.34845225 | M17: =B17-'15W40'!B17 -> 51.75 | N17: =C17-'15W40'!C17 -> 36.75
A18: Cummins ISB | B18: ='15W40'!B18+('15W40 Gallon'!G4-'15W40'!G4)*'15W40 Gallon'!F18+'15W40 Gallon'!M2 -> 307.74 | C18: =E18+G18+H18 -> 177.688 | E18: ='15W40'!E18 -> 26.688 | F18: ='15W40'!F18 -> 25 | G18: =F18*G4 -> 143 | H18: 8 | I18: =B18-C18 -> 130.052 | J18: =C18/B18 -> 0.5773965 | K18: =1-J18 -> 0.4226035 | M18: =B18-'15W40'!B18 -> 51.75 | N18: =C18-'15W40'!C18 -> 36.75
A19: Cummins ISM | B19: ='15W40'!B19+('15W40 Gallon'!G4-'15W40'!G4)*'15W40 Gallon'!F19+'15W40 Gallon'!M2 -> 360.91 | C19: =E19+G19+H19 -> 253.7544 | E19: ='15W40'!E19 -> 39.8344 | F19: ='15W40'!F19 -> 36 | G19: =F19*G4 -> 205.92 | H19: 8 | I19: =B19-C19 -> 107.1556 | J19: =C19/B19 -> 0.70309606 | K19: =1-J19 -> 0.29690394 | M19: =B19-'15W40'!B19 -> 67.92 | N19: =C19-'15W40'!C19 -> 52.92
A20: Cummins ISX | B20: ='15W40'!B20+('15W40 Gallon'!G4-'15W40'!G4)*'15W40 Gallon'!F20+'15W40 Gallon'!M3 -> 463.67 | C20: =E20+G20+H20 -> 345.3296 | E20: ='15W40'!E20 -> 85.6496 | F20: ='15W40'!F20 -> 44 | G20: =F20*G4 -> 251.68 | H20: 8 | I20: =B20-C20 -> 118.3404 | J20: =C20/B20 -> 0.74477452 | K20: =1-J20 -> 0.25522548 | M20: =B20-'15W40'!B20 -> 84.68 | N20: =C20-'15W40'!C20 -> 64.68
A21: Cummins M11 | B21: ='15W40'!B21+('15W40 Gallon'!G4-'15W40'!G4)*'15W40 Gallon'!F21+'15W40 Gallon'!M2 -> 340.97 | C21: =E21+G21+H21 -> 233.9112 | E21: ='15W40'!E21 -> 31.4312 | F21: ='15W40'!F21 -> 34 | G21: =F21*G4 -> 194.48 | H21: 8 | I21: =B21-C21 -> 107.0588 | J21: =C21/B21 -> 0.68601695 | K21: =1-J21 -> 0.31398305 | M21: =B21-'15W40'!B21 -> 64.98 | N21: =C21-'15W40'!C21 -> 49.98
A23: Detroit With Detroit Filter | B23: ='15W40'!B23+('15W40 Gallon'!G4-'15W40'!G4)*'15W40 Gallon'!F23+'15W40 Gallon'!M2 -> 420.85 | C23: =E23+G23+H23 -> 302.98 | E23: ='15W40'!E23 -> 77.62 | F23: ='15W40'!F23 -> 38 | G23: =F23*G4 -> 217.36 | H23: 8 | I23: =B23-C23 -> 117.87 | J23: =C23/B23 -> 0.71992396 | K23: =1-J23 -> 0.28007604 | M23: =B23-'15W40'!B23 -> 70.86 | N23: =C23-'15W40'!C23 -> 55.86
A24: Detroit With Detroit Filter (DD8) | B24: ='15W40'!B24+('15W40 Gallon'!G4-'15W40'!G4)*'15W40 Gallon'!F24+'15W40 Gallon'!M2 -> 472.03 | C24: =E24+G24+H24 -> 359.89 | E24: ='15W40'!E24 -> 168.85 | F24: ='15W40'!F24 -> 32 | G24: =F24*G4 -> 183.04 | H24: 8 | I24: =B24-C24 -> 112.14 | J24: =C24/B24 -> 0.76243035 | K24: =1-J24 -> 0.23756965 | M24: =B24-'15W40'!B24 -> 62.04 | N24: =C24-'15W40'!C24 -> 47.04
A25: Detroit With Detroit Filter (DD13,DD15,DD16) | B25: ='15W40'!B25+('15W40 Gallon'!G4-'15W40'!G4)*'15W40 Gallon'!F25+'15W40 Gallon'!M3 -> 497.73 | C25: =E25+G25+H25 -> 386.03 | E25: ='15W40'!E25 -> 137.79 | F25: ='15W40'!F25 -> 42 | G25: =F25*G4 -> 240.24 | H25: 8 | I25: =B25-C25 -> 111.7 | J25: =C25/B25 -> 0.77558114 | K25: =1-J25 -> 0.22441886 | M25: =B25-'15W40'!B25 -> 81.74 | N25: =C25-'15W40'!C25 -> 61.74
A26: Detroit With Fleetguard Filter (DD13,DD15.DD16) | B26: ='15W40'!B26+('15W40 Gallon'!G4-'15W40'!G4)*'15W40 Gallon'!F26+'15W40 Gallon'!M3 -> 475.73 | C26: =E26+G26+H26 -> 362.2928 | E26: ='15W40'!E26 -> 114.0528 | F26: ='15W40'!F26 -> 42 | G26: =F26*G4 -> 240.24 | H26: 8 | I26: =B26-C26 -> 113.4372 | J26: =C26/B26 -> 0.7615513 | K26: =1-J26 -> 0.2384487 | M26: =B26-'15W40'!B26 -> 81.74 | N26: =C26-'15W40'!C26 -> 61.74
A27: Detroit With Fleetguard | B27: ='15W40'!B27+('15W40 Gallon'!G4-'15W40'!G4)*'15W40 Gallon'!F27+'15W40 Gallon'!M2 -> 373.85 | C27: =E27+G27+H27 -> 270.7512 | E27: ='15W40'!E27 -> 45.3912 | F27: ='15W40'!F27 -> 38 | G27: =F27*G4 -> 217.36 | H27: 8 | I27: =B27-C27 -> 103.0988 | J27: =C27/B27 -> 0.72422415 | K27: =1-J27 -> 0.27577585 | M27: =B27-'15W40'!B27 -> 70.86 | N27: =C27-'15W40'!C27 -> 55.86
A28: Duramax / Vortec 8100L | B28: ='15W40'!B28+('15W40 Gallon'!G4-'15W40'!G4)*'15W40 Gallon'!F28+'15W40 Gallon'!M1 -> 201.57 | C28: =E28+G28+H28 -> 98.1824 | E28: ='15W40'!E28 -> 10.1024 | F28: ='15W40'!F28 -> 14 | G28: =F28*G4 -> 80.08 | H28: 8 | I28: =B28-C28 -> 103.3876 | J28: =C28/B28 -> 0.48708836 | K28: =1-J28 -> 0.51291164 | M28: =B28-'15W40'!B28 -> 30.58 | N28: =C28-'15W40'!C28 -> 20.58
A30: F250 / F350 / F550 / F650 | B30: ='15W40'!B30+('15W40 Gallon'!G4-'15W40'!G4)*'15W40 Gallon'!F30+'15W40 Gallon'!M1 -> 201.57 | C30: =E30+G30+H30 -> 102.4968 | E30: ='15W40'!E30 -> 14.4168 | F30: ='15W40'!F30 -> 14 | G30: =F30*G4 -> 80.08 | H30: 8 | I30: =B30-C30 -> 99.0732 | J30: =C30/B30 -> 0.50849234 | K30: =1-J30 -> 0.49150766 | M30: =B30-'15W40'!B30 -> 30.58 | N30: =C30-'15W40'!C30 -> 20.58
A32: Hino | B32: ='15W40'!B32+('15W40 Gallon'!G4-'15W40'!G4)*'15W40 Gallon'!F32+'15W40 Gallon'!M1 -> 300.57 | C32: =E32+G32+H32 -> 184.08 | E32: ='15W40'!E32 -> 96 | F32: ='15W40'!F32 -> 14 | G32: =F32*G4 -> 80.08 | H32: 8 | I32: =B32-C32 -> 116.49 | J32: =C32/B32 -> 0.61243637 | K32: =1-J32 -> 0.38756363 | M32: =B32-'15W40'!B32 -> 30.58 | N32: =C32-'15W40'!C32 -> 20.58
A33: Hino With Fleetguard | B33: ='15W40'!B33+('15W40 Gallon'!G4-'15W40'!G4)*'15W40 Gallon'!F33+'15W40 Gallon'!M1 -> 230.57 | C33: =E33+G33+H33 -> 115.5016 | E33: ='15W40'!E33 -> 27.4216 | F33: ='15W40'!F33 -> 14 | G33: =F33*G4 -> 80.08 | H33: 8 | I33: =B33-C33 -> 115.0684 | J33: =C33/B33 -> 0.50093941 | K33: =1-J33 -> 0.49906059 | M33: =B33-'15W40'!B33 -> 30.58 | N33: =C33-'15W40'!C33 -> 20.58
A35: International | B35: ='15W40'!B35+('15W40 Gallon'!G4-'15W40'!G4)*'15W40 Gallon'!F35+'15W40 Gallon'!M2 -> 319.21 | C35: =E35+G35+H35 -> 210.2888 | E35: ='15W40'!E35 -> 53.5688 | F35: ='15W40'!F35 -> 26 | G35: =F35*G4 -> 148.72 | H35: 8 | I35: =B35-C35 -> 108.9212 | J35: =C35/B35 -> 0.65877886 | K35: =1-J35 -> 0.34122114 | M35: =B35-'15W40'!B35 -> 53.22 | N35: =C35-'15W40'!C35 -> 38.22
A36: International S13 | B36: ='15W40'!B36+('15W40 Gallon'!G4-'15W40'!G4)*'15W40 Gallon'!F36+'15W40 Gallon'!M3 -> 587.61 | C36: =E36+G36+H36 -> 449.92 | E36: ='15W40'!E36 -> 178.8 | F36: ='15W40'!F36 -> 46 | G36: =F36*G4 -> 263.12 | H36: 8 | I36: =B36-C36 -> 137.69 | J36: =C36/B36 -> 0.76567792 | K36: =1-J36 -> 0.23432208 | N36: =C36-'15W40'!C36 -> 67.62
A37: International Vista | B37: ='15W40'!B37+('15W40 Gallon'!G4-'15W40'!G4)*'15W40 Gallon'!F37+'15W40 Gallon'!M4 -> 295.57 | C37: =E37+G37+H37 -> 145.9528 | E37: ='15W40'!E37 -> 57.8728 | F37: ='15W40'!F37 -> 14 | G37: =F37*G4 -> 80.08 | H37: 8 | I37: =B37-C37 -> 149.6172 | J37: =C37/B37 -> 0.49380113 | K37: =1-J37 -> 0.50619887
A38: Isuzu With Fleetguard Filter | B38: ='15W40'!B38+('15W40 Gallon'!G4-'15W40'!G4)*'15W40 Gallon'!F38+'15W40 Gallon'!M1 -> 246.57 | C38: =E38+G38+H38 -> 132.2208 | E38: ='15W40'!E38 -> 44.1408 | F38: ='15W40'!F38 -> 14 | G38: =F38*G4 -> 80.08 | H38: 8 | I38: =B38-C38 -> 114.3492 | J38: =C38/B38 -> 0.53624042 | K38: =1-J38 -> 0.46375958 | M38: =B38-'15W40'!B38 -> 30.58 | N38: =C38-'15W40'!C38 -> 20.58
A39: Isuzu | B39: ='15W40'!B39+('15W40 Gallon'!G4-'15W40'!G4)*'15W40 Gallon'!F39+'15W40 Gallon'!M1 -> 306.57 | C39: =E39+G39+H39 -> 157.05 | E39: ='15W40'!E39 -> 68.97 | F39: ='15W40'!F39 -> 14 | G39: =F39*G4 -> 80.08 | H39: 8 | I39: =B39-C39 -> 149.52 | J39: =C39/B39 -> 0.51228105 | K39: =1-J39 -> 0.48771895 | N39: =C39-'15W40'!C39 -> 20.58
A41: MP 7 / MP8 With Fleetguard Filter | B41: ='15W40'!B41+('15W40 Gallon'!G4-'15W40'!G4)*'15W40 Gallon'!F41+'15W40 Gallon'!M2 -> 434.85 | C41: =E41+G41+H41 -> 311.9648 | E41: ='15W40'!E41 -> 86.6048 | F41: ='15W40'!F41 -> 38 | G41: =F41*G4 -> 217.36 | H41: 8 | I41: =B41-C41 -> 122.8852 | J41: =C41/B41 -> 0.71740784 | K41: =1-J41 -> 0.28259216 | M41: =B41-'15W40'!B41 -> 70.86 | N41: =C41-'15W40'!C41 -> 55.86
A42: MP 7 / MP8 With Mack Filter | B42: ='15W40'!B42+('15W40 Gallon'!G4-'15W40'!G4)*'15W40 Gallon'!F42+'15W40 Gallon'!M2 -> 505.85 | C42: =E42+G42+H42 -> 398.86 | E42: ='15W40'!E42 -> 173.5 | F42: ='15W40'!F42 -> 38 | G42: =F42*G4 -> 217.36 | H42: 8 | I42: =B42-C42 -> 106.99 | J42: =C42/B42 -> 0.78849461 | K42: =1-J42 -> 0.21150539 | M42: =B42-'15W40'!B42 -> 70.86 | N42: =C42-'15W40'!C42 -> 55.86
A43: MP 7/MP8/ MP10 With Fleetguard ( 52L) | B43: ='15W40'!B43+('15W40 Gallon'!G4-'15W40'!G4)*'15W40 Gallon'!F43+'15W40 Gallon'!M4 -> 542.84 | C43: =E43+G43+H43 -> 409.2048 | E43: ='15W40'!E41 -> 86.6048 | F43: ='15W40'!F43 -> 55 | G43: =F43*G4 -> 314.6 | H43: 8 | I43: =B43-C43 -> 133.6352 | J43: =C43/B43 -> 0.75382212 | K43: =1-J43 -> 0.24617788 | M43: =B43-'15W40'!B43 -> 105.85 | N43: =C43-'15W40'!C43 -> 80.85
A44: MP 7/MP8/ MP10 With Mack (52L) | B44: ='15W40'!B44+('15W40 Gallon'!G4-'15W40'!G4)*'15W40 Gallon'!F44+'15W40 Gallon'!M4 -> 615.84 | C44: =E44+G44+H44 -> 496.1 | E44: ='15W40'!E44 -> 173.5 | F44: ='15W40'!F44 -> 55 | G44: =F44*G4 -> 314.6 | H44: 8 | I44: =B44-C44 -> 119.74 | J44: =C44/B44 -> 0.80556638 | K44: =1-J44 -> 0.19443362 | M44: =B44-'15W40'!B44 -> 105.85 | N44: =C44-'15W40'!C44 -> 80.85
A45: Mack With Fleetguard Filter | B45: ='15W40'!B45+('15W40 Gallon'!G4-'15W40'!G4)*'15W40 Gallon'!F45+'15W40 Gallon'!M2 -> 388.85 | C45: =E45+G45+H45 -> 275.744 | E45: ='15W40'!E45 -> 50.384 | F45: ='15W40'!F45 -> 38 | G45: =F45*G4 -> 217.36 | H45: 8 | I45: =B45-C45 -> 113.106 | J45: =C45/B45 -> 0.70912691 | K45: =1-J45 -> 0.29087309 | M45: =B45-'15W40'!B45 -> 70.86 | N45: =C45-'15W40'!C45 -> 55.86
A46: Mack With Fleetguard Filter(52L) | B46: ='15W40'!B46+('15W40 Gallon'!G4-'15W40'!G4)*'15W40 Gallon'!F46+'15W40 Gallon'!M4 -> 479.43 | C46: =E46+G46+H46 -> 355.824 | E46: ='15W40'!E46 -> 50.384 | F46: ='15W40'!F46 -> 52 | G46: =F46*G4 -> 297.44 | H46: 8 | I46: =B46-C46 -> 123.606 | J46: =C46/B46 -> 0.74218134 | K46: =1-J46 -> 0.25781866 | M46: =B46-'15W40'!B46 -> 101.44 | N46: =C46-'15W40'!C46 -> 76.44
A47: Mack With Mack Filter | B47: ='15W40'!B47+('15W40 Gallon'!G4-'15W40'!G4)*'15W40 Gallon'!F47+'15W40 Gallon'!M2 -> 497.85 | C47: =E47+G47+H47 -> 386.75 | E47: ='15W40'!E47 -> 161.39 | F47: ='15W40'!F47 -> 38 | G47: =F47*G4 -> 217.36 | H47: 8 | I47: =B47-C47 -> 111.1 | J47: =C47/B47 -> 0.77684041 | K47: =1-J47 -> 0.22315959 | M47: =B47-'15W40'!B47 -> 70.86 | N47: =C47-'15W40'!C47 -> 55.86
A48: Mack With Mack Filter( 52L ) | B48: ='15W40'!B48+('15W40 Gallon'!G4-'15W40'!G4)*'15W40 Gallon'!F48+'15W40 Gallon'!M4 -> 591.43 | C48: =E48+G48+H48 -> 466.83 | E48: ='15W40'!E48 -> 161.39 | F48: ='15W40'!F48 -> 52 | G48: =F48*G4 -> 297.44 | H48: 8 | I48: =B48-C48 -> 124.6 | J48: =C48/B48 -> 0.78932418 | K48: =1-J48 -> 0.21067582 | M48: =B48-'15W40'!B48 -> 101.44 | N48: =C48-'15W40'!C48 -> 76.44
A50: Max Force 7 | B50: ='15W40'!B50+('15W40 Gallon'!G4-'15W40'!G4)*'15W40 Gallon'!F50+'15W40 Gallon'!M2 -> 489.21 | C50: =E50+G50+H50 -> 379.4 | E50: ='15W40'!E50 -> 222.68 | F50: ='15W40'!F50 -> 26 | G50: =F50*G4 -> 148.72 | H50: 8 | I50: =B50-C50 -> 109.81 | J50: =C50/B50 -> 0.77553607 | K50: =1-J50 -> 0.22446393 | M50: =B50-'15W40'!B50 -> 53.22 | N50: =C50-'15W40'!C50 -> 38.22
A51: Max Force 7 With Fleetguard | B51: ='15W40'!B51+('15W40 Gallon'!G4-'15W40'!G4)*'15W40 Gallon'!F51+'15W40 Gallon'!M2 -> 410.21 | C51: =E51+G51+H51 -> 301.896 | E51: ='15W40'!E51 -> 145.176 | F51: ='15W40'!F51 -> 26 | G51: =F51*G4 -> 148.72 | H51: 8 | I51: =B51-C51 -> 108.314 | J51: =C51/B51 -> 0.73595475 | K51: =1-J51 -> 0.26404525 | M51: =B51-'15W40'!B51 -> 53.22 | N51: =C51-'15W40'!C51 -> 38.22
A52: Max Force 13 | B52: ='15W40'!B52+('15W40 Gallon'!G4-'15W40'!G4)*'15W40 Gallon'!F52+'15W40 Gallon'!M2 -> 505.85 | C52: =E52+G52+H52 -> 390.05 | E52: ='15W40'!E52 -> 164.69 | F52: ='15W40'!F52 -> 38 | G52: =F52*G4 -> 217.36 | H52: 8 | I52: =B52-C52 -> 115.8 | J52: =C52/B52 -> 0.77107838 | K52: =1-J52 -> 0.22892162 | M52: =B52-'15W40'!B52 -> 70.86 | N52: =C52-'15W40'!C52 -> 55.86
A53: Max Force 13 With Fleetguard | B53: ='15W40'!B53+('15W40 Gallon'!G4-'15W40'!G4)*'15W40 Gallon'!F53+'15W40 Gallon'!M2 -> 427.85 | C53: =E53+G53+H53 -> 314.1632 | E53: ='15W40'!E53 -> 88.8032 | F53: ='15W40'!F53 -> 38 | G53: =F53*G4 -> 217.36 | H53: 8 | I53: =B53-C53 -> 113.6868 | J53: =C53/B53 -> 0.73428351 | K53: =1-J53 -> 0.26571649 | M53: =B53-'15W40'!B53 -> 70.86 | N53: =C53-'15W40'!C53 -> 55.86
A55: Mercedes Benz 4000 | B55: ='15W40'!B55+('15W40 Gallon'!G4-'15W40'!G4)*'15W40 Gallon'!F55+'15W40 Gallon'!M3 -> 454.08 | C55: =E55+G55+H55 -> 326.85 | E55: ='15W40'!E55 -> 50.01 | F55: ='15W40'!F55 -> 47 | G55: =F55*G4 -> 268.84 | H55: 8 | I55: =B55-C55 -> 127.23 | J55: =C55/B55 -> 0.71980708 | K55: =1-J55 -> 0.28019292 | M55: =B55-'15W40'!B55 -> 89.09 | N55: =C55-'15W40'!C55 -> 69.09
A56: Mercedes Benz 4000 With Fleeguard Filter | B56: ='15W40'!B56+('15W40 Gallon'!G4-'15W40'!G4)*'15W40 Gallon'!F56+'15W40 Gallon'!M3 -> 432.08 | C56: =E56+G56+H56 -> 318.2816 | E56: ='15W40'!E56 -> 41.4416 | F56: ='15W40'!F56 -> 47 | G56: =F56*G4 -> 268.84 | H56: 8 | I56: =B56-C56 -> 113.7984 | J56: =C56/B56 -> 0.73662655 | K56: =1-J56 -> 0.26337345 | M56: =B56-'15W40'!B56 -> 89.09 | N56: =C56-'15W40'!C56 -> 69.09
A57: Mercedes Benz 900 | B57: ='15W40'!B57+('15W40 Gallon'!G4-'15W40'!G4)*'15W40 Gallon'!F57+'15W40 Gallon'!M2 -> 333.21 | C57: =E57+G57+H57 -> 204.27 | E57: ='15W40'!E57 -> 47.55 | F57: ='15W40'!F57 -> 26 | G57: =F57*G4 -> 148.72 | H57: 8 | I57: =B57-C57 -> 128.94 | J57: =C57/B57 -> 0.61303682 | K57: =1-J57 -> 0.38696318 | M57: =B57-'15W40'!B57 -> 53.22 | N57: =C57-'15W40'!C57 -> 38.22
A58: Mercedes Benz 900 With Fleetguard Filter | B58: ='15W40'!B58+('15W40 Gallon'!G4-'15W40'!G4)*'15W40 Gallon'!F58+'15W40 Gallon'!M2 -> 295.21 | C58: =E58+G58+H58 -> 190.196 | E58: ='15W40'!E58 -> 33.476 | F58: ='15W40'!F58 -> 26 | G58: =F58*G4 -> 148.72 | H58: 8 | I58: =B58-C58 -> 105.014 | J58: =C58/B58 -> 0.64427357 | K58: =1-J58 -> 0.35572643 | M58: =B58-'15W40'!B58 -> 53.22 | N58: =C58-'15W40'!C58 -> 38.22
A59: Mercedes Benz Sprinter | B59: ='15W40'!B59+('15W40 Gallon'!G4-'15W40'!G4)*'15W40 Gallon'!F59+'15W40 Gallon'!M2 -> 270.27 | C59: =E59+G59+H59 -> 145.28 | E59: ='15W40'!E59 -> 0 | F59: ='15W40'!F59 -> 24 | G59: =F59*G4 -> 137.28 | H59: 8 | I59: =B59-C59 -> 124.99 | J59: =C59/B59 -> 0.53753654 | K59: =1-J59 -> 0.46246346 | M59: =B59-'15W40'!B59 -> 50.28 | N59: =C59-'15W40'!C59 -> 35.28
A60: Mitsubushi | B60: ='15W40'!B60+('15W40 Gallon'!G4-'15W40'!G4)*'15W40 Gallon'!F60+'15W40 Gallon'!M1 -> 259.1 | C60: =E60+G60+H60 -> 155.6 | E60: ='15W40'!E60 -> 73.24 | F60: ='15W40'!F60 -> 13 | G60: =F60*G4 -> 74.36 | H60: 8 | I60: =B60-C60 -> 103.5 | J60: =C60/B60 -> 0.60054033 | K60: =1-J60 -> 0.39945967 | M60: =B60-'15W40'!B60 -> 29.11 | N60: =C60-'15W40'!C60 -> 19.11
A63: Navistar | B63: ='15W40'!B63+('15W40 Gallon'!G4-'15W40'!G4)*'15W40 Gallon'!F63+'15W40 Gallon'!M2 -> 300.21 | C63: =E63+G63+H63 -> 194.7464 | E63: ='15W40'!E63 -> 38.0264 | F63: ='15W40'!F63 -> 26 | G63: =F63*G4 -> 148.72 | H63: 8 | I63: =B63-C63 -> 105.4636 | J63: =C63/B63 -> 0.64870058 | K63: =1-J63 -> 0.35129942 | M63: =B63-'15W40'!B63 -> 53.22 | N63: =C63-'15W40'!C63 -> 38.22
A65: Paccer | B65: ='15W40'!B65+('15W40 Gallon'!G4-'15W40'!G4)*'15W40 Gallon'!F65+'15W40 Gallon'!M3 -> 546.61 | C65: =E65+G65+H65 -> 433.17 | E65: ='15W40'!E65 -> 162.05 | F65: ='15W40'!F65 -> 46 | G65: =F65*G4 -> 263.12 | H65: 8 | I65: =B65-C65 -> 113.44 | J65: =C65/B65 -> 0.79246629 | K65: =1-J65 -> 0.20753371 | M65: =B65-'15W40'!B65 -> 87.62 | N65: =C65-'15W40'!C65 -> 67.62
A66: Paccer With Fleetguard | B66: ='15W40'!B66+('15W40 Gallon'!G4-'15W40'!G4)*'15W40 Gallon'!F66+'15W40 Gallon'!M3 -> 467.61 | C66: =E66+G66+H66 -> 350.9672 | E66: ='15W40'!E66 -> 79.8472 | F66: ='15W40'!F66 -> 46 | G66: =F66*G4 -> 263.12 | H66: 8 | I66: =B66-C66 -> 116.6428 | J66: =C66/B66 -> 0.75055538 | K66: =1-J66 -> 0.24944462 | M66: =B66-'15W40'!B66 -> 87.62 | N66: =C66-'15W40'!C66 -> 67.62
A67: Paccer Small | B67: ='15W40'!B67+('15W40 Gallon'!G4-'15W40'!G4)*'15W40 Gallon'!F67+'15W40 Gallon'!M2 -> 280.27 | C67: =E67+G67+H67 -> 171.968 | E67: ='15W40'!E67 -> 26.688 | F67: ='15W40'!F67 -> 24 | G67: =F67*G4 -> 137.28 | H67: 8 | I67: =B67-C67 -> 108.302 | J67: =C67/B67 -> 0.61357976 | K67: =1-J67 -> 0.38642024 | M67: =B67-'15W40'!B67 -> 50.28 | N67: =C67-'15W40'!C67 -> 35.28
A69: Volvo With Fleetguard | B69: ='15W40'!B69+('15W40 Gallon'!G4-'15W40'!G4)*'15W40 Gallon'!F69+'15W40 Gallon'!M2 -> 410.97 | C69: =E69+G69+H69 -> 289.0848 | E69: ='15W40'!E69 -> 86.6048 | F69: ='15W40'!F69 -> 34 | G69: =F69*G4 -> 194.48 | H69: 8 | I69: =B69-C69 -> 121.8852 | J69: =C69/B69 -> 0.70342069 | K69: =1-J69 -> 0.29657931 | M69: =B69-'15W40'!B69 -> 64.98 | N69: =C69-'15W40'!C69 -> 49.98
A70: Volvo With Fleetguard(D16 42L) | B70: ='15W40'!B70+('15W40 Gallon'!G4-'15W40'!G4)*'15W40 Gallon'!F70+'15W40 Gallon'!M3 -> 461.73 | C70: =E70+G70+H70 -> 334.8448 | E70: ='15W40'!E70 -> 86.6048 | F70: ='15W40'!F70 -> 42 | G70: =F70*G4 -> 240.24 | H70: 8 | I70: =B70-C70 -> 126.8852 | J70: =C70/B70 -> 0.72519611 | K70: =1-J70 -> 0.27480389 | M70: =B70-'15W40'!B70 -> 81.74 | N70: =C70-'15W40'!C70 -> 61.74
A71: Volvo With Fleetguard(D16 52L) | B71: ='15W40'!B71+('15W40 Gallon'!G4-'15W40'!G4)*'15W40 Gallon'!F71+'15W40 Gallon'!M4 -> 526.43 | C71: =E71+G71+H71 -> 392.0448 | E71: ='15W40'!E71 -> 86.6048 | F71: ='15W40'!F71 -> 52 | G71: =F71*G4 -> 297.44 | H71: 8 | I71: =B71-C71 -> 134.3852 | J71: =C71/B71 -> 0.74472351 | K71: =1-J71 -> 0.25527649 | M71: =B71-'15W40'!B71 -> 101.44 | N71: =C71-'15W40'!C71 -> 76.44
A72: Volvo With Volvo Filter | B72: ='15W40'!B72+('15W40 Gallon'!G4-'15W40'!G4)*'15W40 Gallon'!F72+'15W40 Gallon'!M2 -> 479.97 | C72: =E72+G72+H72 -> 368.77 | E72: ='15W40'!E72 -> 166.29 | F72: ='15W40'!F72 -> 34 | G72: =F72*G4 -> 194.48 | H72: 8 | I72: =B72-C72 -> 111.2 | J72: =C72/B72 -> 0.76831885 | K72: =1-J72 -> 0.23168115 | M72: =B72-'15W40'!B72 -> 64.98 | N72: =C72-'15W40'!C72 -> 49.98
A73: Volvo With Volvo Filter (D16 42L) | B73: ='15W40'!B73+('15W40 Gallon'!G4-'15W40'!G4)*'15W40 Gallon'!F73+'15W40 Gallon'!M3 -> 531.73 | C73: =E73+G73+H73 -> 414.53 | E73: ='15W40'!E73 -> 166.29 | F73: ='15W40'!F73 -> 42 | G73: =F73*G4 -> 240.24 | H73: 8 | I73: =B73-C73 -> 117.2 | J73: =C73/B73 -> 0.77958738 | K73: =1-J73 -> 0.22041262 | M73: =B73-'15W40'!B73 -> 81.74 | N73: =C73-'15W40'!C73 -> 61.74
A74: Volvo With Volvo Filter (D16 52L) | B74: ='15W40'!B74+('15W40 Gallon'!G4-'15W40'!G4)*'15W40 Gallon'!F74+'15W40 Gallon'!M4 -> 594.43 | C74: =E74+G74+H74 -> 471.73 | E74: ='15W40'!E74 -> 166.29 | F74: ='15W40'!F74 -> 52 | G74: =F74*G4 -> 297.44 | H74: 8 | I74: =B74-C74 -> 122.7 | J74: =C74/B74 -> 0.79358377 | K74: =1-J74 -> 0.20641623 | M74: =B74-'15W40'!B74 -> 101.44 | N74: =C74-'15W40'!C74 -> 76.44

Sheet 10W30
A1: STANDARD JOB LIST | B1: 10W30 | C1: Delo | G1: ='Oil Price'!C25 -> 4.41 | H1: 0.05 | L1: 8--20 | M1: 15
B2: selling | C2: cost | E2: Filtre | F2: Litre | G2: Oil | H2: Fuel | I2: Profit | J2: Cost | K2: Profit | L2: 21--38 | M2: 25
A3: Auto Greaser Refill | E3: Cost | G3: Cost | H3: Grease | L3: 39--46 | M3: 30
G4: =G1+H1 -> 4.46 | J4: 1 | L4: 47& UP | M4: 35
A6: C 7 / 10 / 3126 With Cat Filter | B6: ='15W40'!B6+M2 -> 290.99 | C6: =E6+G6+H6 -> 172.79 | E6: ='15W40'!E6 -> 53.29 | F6: ='15W40'!F6 -> 25 | G6: =F6*G4 -> 111.5 | H6: 8 | I6: =B6-C6 -> 118.2 | J6: =C6/B6 -> 0.59380047 | K6: =1-J6 -> 0.40619953
A7: C 7 / 10 / 3126 With Fleetguard Filter | B7: ='15W40'!B7+M2 -> 268.99 | C7: =E7+G7+H7 -> 141.2992 | E7: ='15W40'!E7 -> 21.7992 | F7: ='15W40'!F7 -> 25 | G7: =F7*G4 -> 111.5 | H7: 8 | I7: =B7-C7 -> 127.6908 | J7: =C7/B7 -> 0.52529536 | K7: =1-J7 -> 0.47470464
A9: C 12 / 3406 With Cat Filter | B9: ='15W40'!B9+M2 -> 359.99 | C9: =E9+G9+H9 -> 248.06 | E9: ='15W40'!E9 -> 70.58 | F9: ='15W40'!F9 -> 38 | G9: =F9*G4 -> 169.48 | H9: 8 | I9: =B9-C9 -> 111.93 | J9: =C9/B9 -> 0.6890747 | K9: =1-J9 -> 0.3109253
A10: C 12 / 3406 With Fleetguard Filter | B10: ='15W40'!B10+M2 -> 318.99 | C10: =E10+G10+H10 -> 208.5248 | E10: ='15W40'!E10 -> 31.0448 | F10: ='15W40'!F10 -> 38 | G10: =F10*G4 -> 169.48 | H10: 8 | I10: =B10-C10 -> 110.4652 | J10: =C10/B10 -> 0.65370325 | K10: =1-J10 -> 0.34629675
A12: C 13 / 15 With Cat Filter | B12: ='15W40'!B12+M3 -> 384.99 | C12: =E12+G12+H12 -> 270.36 | E12: ='15W40'!E12 -> 70.58 | F12: ='15W40'!F12 -> 43 | G12: =F12*G4 -> 191.78 | H12: 8 | I12: =B12-C12 -> 114.63 | J12: =C12/B12 -> 0.70225201 | K12: =1-J12 -> 0.29774799
A13: C 13 / 15 With Fleetguard Filter | B13: ='15W40'!B13+M3 -> 343.99 | C13: =E13+G13+H13 -> 230.8248 | E13: ='15W40'!E13 -> 31.0448 | F13: ='15W40'!F13 -> 43 | G13: =F13*G4 -> 191.78 | H13: 8 | I13: =B13-C13 -> 113.1652 | J13: =C13/B13 -> 0.67102183 | K13: =1-J13 -> 0.32897817
A15: Cummins N14 | B15: ='15W40'!B15+M3 -> 331.99 | C15: =E15+G15+H15 -> 217.8312 | E15: ='15W40'!E15 -> 31.4312 | F15: ='15W40'!F15 -> 40 | G15: =F15*G4 -> 178.4 | H15: 8 | I15: =B15-C15 -> 114.1588 | J15: =C15/B15 -> 0.65613784 | K15: =1-J15 -> 0.34386216
A16: Cummins 5.9L/6.7L | B16: ='15W40'!B16+M1 -> 185.99 | C16: =E16+G16+H16 -> 77.16 | E16: ='15W40'!E16 -> 6.72 | F16: ='15W40'!F16 -> 14 | G16: =F16*G4 -> 62.44 | H16: 8 | I16: =B16-C16 -> 108.83 | J16: =C16/B16 -> 0.41486101 | K16: =1-J16 -> 0.58513899
A17: Cummins ISC / ISL | B17: ='15W40'!B17+M2 -> 282.99 | C17: =E17+G17+H17 -> 170.3104 | E17: ='15W40'!E17 -> 50.8104 | F17: ='15W40'!F17 -> 25 | G17: =F17*G4 -> 111.5 | H17: 8 | I17: =B17-C17 -> 112.6796 | J17: =C17/B17 -> 0.6018248 | K17: =1-J17 -> 0.3981752
A18: Cummins ISB | B18: ='15W40'!B18+'10W30'!M2 -> 280.99 | C18: =E18+G18+H18 -> 146.188 | E18: ='15W40'!E18 -> 26.688 | F18: ='15W40'!F18 -> 25 | G18: =F18*G4 -> 111.5 | H18: 8 | I18: =B18-C18 -> 134.802 | J18: =C18/B18 -> 0.52026051 | K18: =1-J18 -> 0.47973949
A19: Cummins ISM | B19: ='15W40'!B19+M2 -> 317.99 | C19: =E19+G19+H19 -> 208.3944 | E19: ='15W40'!E19 -> 39.8344 | F19: ='15W40'!F19 -> 36 | G19: =F19*G4 -> 160.56 | H19: 8 | I19: =B19-C19 -> 109.5956 | J19: =C19/B19 -> 0.65534891 | K19: =1-J19 -> 0.34465109
A20: Cummins ISX | B20: ='15W40'!B20+M3 -> 408.99 | C20: =E20+G20+H20 -> 289.8896 | E20: ='15W40'!E20 -> 85.6496 | F20: ='15W40'!F20 -> 44 | G20: =F20*G4 -> 196.24 | H20: 8 | I20: =B20-C20 -> 119.1004 | J20: =C20/B20 -> 0.70879386 | K20: =1-J20 -> 0.29120614
A21: Cummins M11 | B21: ='15W40'!B21+M2 -> 300.99 | C21: =E21+G21+H21 -> 191.0712 | E21: ='15W40'!E21 -> 31.4312 | F21: ='15W40'!F21 -> 34 | G21: =F21*G4 -> 151.64 | H21: 8 | I21: =B21-C21 -> 109.9188 | J21: =C21/B21 -> 0.63480913 | K21: =1-J21 -> 0.36519087
A23: Detroit With Detroit Filter | B23: ='15W40'!B23+M2 -> 374.99 | C23: =E23+G23+H23 -> 255.1 | E23: ='15W40'!E23 -> 77.62 | F23: ='15W40'!F23 -> 38 | G23: =F23*G4 -> 169.48 | H23: 8 | I23: =B23-C23 -> 119.89 | J23: =C23/B23 -> 0.68028481 | K23: =1-J23 -> 0.31971519
A24: Detroit With Detroit Filter (DD8) | B24: ='15W40'!B24+M2 -> 434.99 | C24: =E24+G24+H24 -> 319.57 | E24: ='15W40'!E24 -> 168.85 | F24: ='15W40'!F24 -> 32 | G24: =F24*G4 -> 142.72 | H24: 8 | I24: =B24-C24 -> 115.42 | J24: =C24/B24 -> 0.73466057 | K24: =1-J24 -> 0.26533943
A25: Detroit With Detroit Filter (DD13,DD15,DD16) | B25: ='15W40'!B25+M3 -> 445.99 | C25: =E25+G25+H25 -> 333.11 | E25: ='15W40'!E25 -> 137.79 | F25: ='15W40'!F25 -> 42 | G25: =F25*G4 -> 187.32 | H25: 8 | I25: =B25-C25 -> 112.88 | J25: =C25/B25 -> 0.74690015 | K25: =1-J25 -> 0.25309985
A26: Detroit With Fleetguard Filter (DD13,DD15.DD16) | B26: ='15W40'!B26+'10W30'!M3 -> 423.99 | C26: =E26+G26+H26 -> 309.3728 | E26: ='15W40'!E26 -> 114.0528 | F26: ='15W40'!F26 -> 42 | G26: =F26*G4 -> 187.32 | H26: 8 | I26: =B26-C26 -> 114.6172 | J26: =C26/B26 -> 0.72967004 | K26: =1-J26 -> 0.27032996
A27: Detroit With Fleetguard | B27: ='15W40'!B27+M2 -> 327.99 | C27: =E27+G27+H27 -> 222.8712 | E27: ='15W40'!E27 -> 45.3912 | F27: ='15W40'!F27 -> 38 | G27: =F27*G4 -> 169.48 | H27: 8 | I27: =B27-C27 -> 105.1188 | J27: =C27/B27 -> 0.67950608 | K27: =1-J27 -> 0.32049392
A28: Duramax / Vortec 8100L | B28: ='15W40'!B28+M1 -> 185.99 | C28: =E28+G28+H28 -> 80.5424 | E28: ='15W40'!E28 -> 10.1024 | F28: ='15W40'!F28 -> 14 | G28: =F28*G4 -> 62.44 | H28: 8 | I28: =B28-C28 -> 105.4476 | J28: =C28/B28 -> 0.43304694 | K28: =1-J28 -> 0.56695306
A30: F250 / F350 / F550 / F650 | B30: ='15W40'!B30+M1 -> 185.99 | C30: =E30+G30+H30 -> 84.8568 | E30: ='15W40'!E30 -> 14.4168 | F30: ='15W40'!F30 -> 14 | G30: =F30*G4 -> 62.44 | H30: 8 | I30: =B30-C30 -> 101.1332 | J30: =C30/B30 -> 0.45624388 | K30: =1-J30 -> 0.54375612
A32: Hino | B32: ='15W40'!B32+M1 -> 284.99 | C32: =E32+G32+H32 -> 166.44 | E32: ='15W40'!E32 -> 96 | F32: ='15W40'!F32 -> 14 | G32: =F32*G4 -> 62.44 | H32: 8 | I32: =B32-C32 -> 118.55 | J32: =C32/B32 -> 0.58402049 | K32: =1-J32 -> 0.41597951
A33: Hino With Fleetguard | B33: ='15W40'!B33+M1 -> 214.99 | C33: =E33+G33+H33 -> 97.8616 | E33: ='15W40'!E33 -> 27.4216 | F33: ='15W40'!F33 -> 14 | G33: =F33*G4 -> 62.44 | H33: 8 | I33: =B33-C33 -> 117.1284 | J33: =C33/B33 -> 0.4551914 | K33: =1-J33 -> 0.5448086
A35: International | B35: ='15W40'!B35+M2 -> 290.99 | C35: =E35+G35+H35 -> 177.5288 | E35: ='15W40'!E35 -> 53.5688 | F35: ='15W40'!F35 -> 26 | G35: =F35*G4 -> 115.96 | H35: 8 | I35: =B35-C35 -> 113.4612 | J35: =C35/B35 -> 0.61008557 | K35: =1-J35 -> 0.38991443
A36: International S13 | B36: ='15W40'!B36+M3 -> 529.99 | C36: =E36+G36+H36 -> 391.96 | E36: ='15W40'!E36 -> 178.8 | F36: ='15W40'!F36 -> 46 | G36: =F36*G4 -> 205.16 | H36: 8 | I36: =B36-C36 -> 138.03 | J36: =C36/B36 -> 0.73956112 | K36: =1-J36 -> 0.26043888
A37: International Vista | B37: ='15W40'!B37+M1 -> 264.99 | C37: =E37+G37+H37 -> 128.3128 | E37: ='15W40'!E37 -> 57.8728 | F37: ='15W40'!F37 -> 14 | G37: =F37*G4 -> 62.44 | H37: 8 | I37: =B37-C37 -> 136.6772 | J37: =C37/B37 -> 0.48421752 | K37: =1-J37 -> 0.51578248
A38: Isuzu With Fleetguard Filter | B38: ='15W40'!B38+M1 -> 230.99 | C38: =E38+G38+H38 -> 114.5808 | E38: ='15W40'!E38 -> 44.1408 | F38: ='15W40'!F38 -> 14 | G38: =F38*G4 -> 62.44 | H38: 8 | I38: =B38-C38 -> 116.4092 | J38: =C38/B38 -> 0.49604225 | K38: =1-J38 -> 0.50395775
A39: Isuzu | B39: ='15W40'!B39+M1 -> 290.99 | C39: =E39+G39+H39 -> 139.41 | E39: ='15W40'!E39 -> 68.97 | F39: ='15W40'!F39 -> 14 | G39: =F39*G4 -> 62.44 | H39: 8 | I39: =B39-C39 -> 151.58 | J39: =C39/B39 -> 0.47908863 | K39: =1-J39 -> 0.52091137
A41: MP 7 / MP8 With Fleetguard | B41: ='15W40'!B41+M2 -> 388.99 | C41: =E41+G41+H41 -> 264.0848 | E41: ='15W40'!E41 -> 86.6048 | F41: ='15W40'!F41 -> 38 | G41: =F41*G4 -> 169.48 | H41: 8 | I41: =B41-C41 -> 124.9052 | J41: =C41/B41 -> 0.67889869 | K41: =1-J41 -> 0.32110131
A42: MP 7 / MP8 | B42: ='15W40'!B42+M2 -> 459.99 | C42: =E42+G42+H42 -> 350.98 | E42: ='15W40'!E42 -> 173.5 | F42: ='15W40'!F42 -> 38 | G42: =F42*G4 -> 169.48 | H42: 8 | I42: =B42-C42 -> 109.01 | J42: =C42/B42 -> 0.76301659 | K42: =1-J42 -> 0.23698341
A43: MP 7/MP8/ MP10 With Fleetguard ( 52L) | B43: ='15W40'!B43+'10W30'!M4 -> 471.99 | C43: =E43+G43+H43 -> 339.9048 | E43: ='15W40'!E43 -> 86.6048 | F43: ='15W40'!F43 -> 55 | G43: =F43*G4 -> 245.3 | H43: 8 | I43: =B43-C43 -> 132.0852 | J43: =C43/B43 -> 0.72015255 | K43: =1-J43 -> 0.27984745
A44: MP 7/MP8/ MP10 With Mack (52L) | B44: ='15W40'!B44+'10W30'!M4 -> 544.99 | C44: =E44+G44+H44 -> 426.8 | E44: ='15W40'!E44 -> 173.5 | F44: ='15W40'!F44 -> 55 | G44: =F44*G4 -> 245.3 | H44: 8 | I44: =B44-C44 -> 118.19 | J44: =C44/B44 -> 0.78313364 | K44: =1-J44 -> 0.21686636
A45: Mack With Fleetguard Filter | B45: ='15W40'!B45+M2 -> 342.99 | C45: =E45+G45+H45 -> 227.864 | E45: ='15W40'!E45 -> 50.384 | F45: ='15W40'!F45 -> 38 | G45: =F45*G4 -> 169.48 | H45: 8 | I45: =B45-C45 -> 115.126 | J45: =C45/B45 -> 0.6643459 | K45: =1-J45 -> 0.3356541
A46: Mack With Fleetguard Filter(52L) | B46: ='15W40'!B46+M4 -> 412.99 | C46: =E46+G46+H46 -> 290.304 | E46: ='15W40'!E46 -> 50.384 | F46: ='15W40'!F46 -> 52 | G46: =F46*G4 -> 231.92 | H46: 8 | I46: =B46-C46 -> 122.686 | J46: =C46/B46 -> 0.70293227 | K46: =1-J46 -> 0.29706773
A47: Mack With Mack Filter | B47: ='15W40'!B47+M2 -> 451.99 | C47: =E47+G47+H47 -> 338.87 | E47: ='15W40'!E47 -> 161.39 | F47: ='15W40'!F47 -> 38 | G47: =F47*G4 -> 169.48 | H47: 8 | I47: =B47-C47 -> 113.12 | J47: =C47/B47 -> 0.74972898 | K47: =1-J47 -> 0.25027102
A48: Mack With Mack Filter( 52L ) | B48: ='15W40'!B48+M4 -> 524.99 | C48: =E48+G48+H48 -> 401.31 | E48: ='15W40'!E48 -> 161.39 | F48: ='15W40'!F48 -> 52 | G48: =F48*G4 -> 231.92 | H48: 8 | I48: =B48-C48 -> 123.68 | J48: =C48/B48 -> 0.76441456 | K48: =1-J48 -> 0.23558544
A50: Max Force 7 | B50: ='15W40'!B50+M2 -> 460.99 | C50: =E50+G50+H50 -> 346.64 | E50: ='15W40'!E50 -> 222.68 | F50: ='15W40'!F50 -> 26 | G50: =F50*G4 -> 115.96 | H50: 8 | I50: =B50-C50 -> 114.35 | J50: =C50/B50 -> 0.7519469 | K50: =1-J50 -> 0.2480531
A51: Max Force 7 With Fleetguard | B51: ='15W40'!B51+'10W30'!M2 -> 381.99 | C51: =E51+G51+H51 -> 269.136 | E51: ='15W40'!E51 -> 145.176 | F51: ='15W40'!F51 -> 26 | G51: =F51*G4 -> 115.96 | H51: 8 | I51: =B51-C51 -> 112.854 | J51: =C51/B51 -> 0.70456295 | K51: =1-J51 -> 0.29543705
A52: Max Force 13 | B52: ='15W40'!B52+M2 -> 459.99 | C52: =E52+G52+H52 -> 342.17 | E52: ='15W40'!E52 -> 164.69 | F52: ='15W40'!F52 -> 38 | G52: =F52*G4 -> 169.48 | H52: 8 | I52: =B52-C52 -> 117.82 | J52: =C52/B52 -> 0.743864 | K52: =1-J52 -> 0.256136
A53: Max Force 13 With Fleetguard | B53: ='15W40'!B53+'10W30'!M2 -> 381.99 | C53: =E53+G53+H53 -> 266.2832 | E53: ='15W40'!E53 -> 88.8032 | F53: ='15W40'!F53 -> 38 | G53: =F53*G4 -> 169.48 | H53: 8 | I53: =B53-C53 -> 115.7068 | J53: =C53/B53 -> 0.69709469 | K53: =1-J53 -> 0.30290531
A55: Mercedes Benz 4000 | B55: ='15W40'!B55+M3 -> 394.99 | C55: =E55+G55+H55 -> 267.63 | E55: ='15W40'!E55 -> 50.01 | F55: ='15W40'!F55 -> 47 | G55: =F55*G4 -> 209.62 | H55: 8 | I55: =B55-C55 -> 127.36 | J55: =C55/B55 -> 0.67756146 | K55: =1-J55 -> 0.32243854
A56: Mercedes Benz 4000 With Fleeguard Filter | B56: ='15W40'!B56+M3 -> 372.99 | C56: =E56+G56+H56 -> 259.0616 | E56: ='15W40'!E56 -> 41.4416 | F56: ='15W40'!F56 -> 47 | G56: =F56*G4 -> 209.62 | H56: 8 | I56: =B56-C56 -> 113.9284 | J56: =C56/B56 -> 0.69455374 | K56: =1-J56 -> 0.30544626
A57: Mercedes Benz 900 | B57: ='15W40'!B57+M2 -> 304.99 | C57: =E57+G57+H57 -> 171.51 | E57: ='15W40'!E57 -> 47.55 | F57: ='15W40'!F57 -> 26 | G57: =F57*G4 -> 115.96 | H57: 8 | I57: =B57-C57 -> 133.48 | J57: =C57/B57 -> 0.56234631 | K57: =1-J57 -> 0.43765369
A58: Mercedes Benz 900 With Fleetguard Filter | B58: ='15W40'!B58+M2 -> 266.99 | C58: =E58+G58+H58 -> 157.436 | E58: ='15W40'!E58 -> 33.476 | F58: ='15W40'!F58 -> 26 | G58: =F58*G4 -> 115.96 | H58: 8 | I58: =B58-C58 -> 109.554 | J58: =C58/B58 -> 0.58967003 | K58: =1-J58 -> 0.41032997
A59: Mercedes Benz Sprinter | B59: ='15W40'!B59+M2 -> 244.99 | C59: =E59+G59+H59 -> 115.04 | E59: ='15W40'!E59 -> 0 | F59: ='15W40'!F59 -> 24 | G59: =F59*G4 -> 107.04 | H59: 8 | I59: =B59-C59 -> 129.95 | J59: =C59/B59 -> 0.46957019 | K59: =1-J59 -> 0.53042981
A60: Mitsubishi | B60: ='15W40'!B60+M1 -> 244.99 | C60: =E60+G60+H60 -> 139.22 | E60: ='15W40'!E60 -> 73.24 | F60: ='15W40'!F60 -> 13 | G60: =F60*G4 -> 57.98 | H60: 8 | I60: =B60-C60 -> 105.77 | J60: =C60/B60 -> 0.56826809 | K60: =1-J60 -> 0.43173191
A63: Navistar | B63: ='15W40'!B63+M2 -> 271.99 | C63: =E63+G63+H63 -> 161.9864 | E63: ='15W40'!E63 -> 38.0264 | F63: ='15W40'!F63 -> 26 | G63: =F63*G4 -> 115.96 | H63: 8 | I63: =B63-C63 -> 110.0036 | J63: =C63/B63 -> 0.59556013 | K63: =1-J63 -> 0.40443987
A65: Paccer | B65: ='15W40'!B65+M3 -> 488.99 | C65: =E65+G65+H65 -> 375.21 | E65: ='15W40'!E65 -> 162.05 | F65: ='15W40'!F65 -> 46 | G65: =F65*G4 -> 205.16 | H65: 8 | I65: =B65-C65 -> 113.78 | J65: =C65/B65 -> 0.76731631 | K65: =1-J65 -> 0.23268369
A66: Paccer With Fleetguard | B66: ='15W40'!B66+M3 -> 409.99 | C66: =E66+G66+H66 -> 293.0072 | E66: ='15W40'!E66 -> 79.8472 | F66: ='15W40'!F66 -> 46 | G66: =F66*G4 -> 205.16 | H66: 8 | I66: =B66-C66 -> 116.9828 | J66: =C66/B66 -> 0.71466914 | K66: =1-J66 -> 0.28533086
A67: Paccer Small | B67: ='15W40'!B67+M2 -> 254.99 | C67: =E67+G67+H67 -> 141.728 | E67: ='15W40'!E67 -> 26.688 | F67: ='15W40'!F67 -> 24 | G67: =F67*G4 -> 107.04 | H67: 8 | I67: =B67-C67 -> 113.262 | J67: =C67/B67 -> 0.55581788 | K67: =1-J67 -> 0.44418212
A69: Volvo With Fleetguard | B69: ='15W40'!B69+M2 -> 370.99 | C69: =E69+G69+H69 -> 246.2448 | E69: ='15W40'!E69 -> 86.6048 | F69: ='15W40'!F69 -> 34 | G69: =F69*G4 -> 151.64 | H69: 8 | I69: =B69-C69 -> 124.7452 | J69: =C69/B69 -> 0.66375051 | K69: =1-J69 -> 0.33624949
A70: Volvo With Fleetguard(D16 42L) | B70: ='15W40'!B70+M3 -> 409.99 | C70: =E70+G70+H70 -> 281.9248 | E70: ='15W40'!E70 -> 86.6048 | F70: ='15W40'!F70 -> 42 | G70: =F70*G4 -> 187.32 | H70: 8 | I70: =B70-C70 -> 128.0652 | J70: =C70/B70 -> 0.68763824 | K70: =1-J70 -> 0.31236176
A71: Volvo With Fleetguard(D16 52L) | B71: ='15W40'!B71+M4 -> 459.99 | C71: =E71+G71+H71 -> 326.5248 | E71: ='15W40'!E71 -> 86.6048 | F71: ='15W40'!F71 -> 52 | G71: =F71*G4 -> 231.92 | H71: 8 | I71: =B71-C71 -> 133.4652 | J71: =C71/B71 -> 0.70985195 | K71: =1-J71 -> 0.29014805
A72: Volvo With Volvo Filter | B72: ='15W40'!B72+M2 -> 439.99 | C72: =E72+G72+H72 -> 325.93 | E72: ='15W40'!E72 -> 166.29 | F72: ='15W40'!F72 -> 34 | G72: =F72*G4 -> 151.64 | H72: 8 | I72: =B72-C72 -> 114.06 | J72: =C72/B72 -> 0.74076684 | K72: =1-J72 -> 0.25923316
A73: Volvo With Volvo Filter (D16 42L) | B73: ='15W40'!B73+M3 -> 479.99 | C73: =E73+G73+H73 -> 361.61 | E73: ='15W40'!E73 -> 166.29 | F73: ='15W40'!F73 -> 42 | G73: =F73*G4 -> 187.32 | H73: 8 | I73: =B73-C73 -> 118.38 | J73: =C73/B73 -> 0.75336986 | K73: =1-J73 -> 0.24663014
A74: Volvo With Volvo Filter (D16 52L) | B74: ='15W40'!B74+M4 -> 527.99 | C74: =E74+G74+H74 -> 406.21 | E74: ='15W40'!E74 -> 166.29 | F74: ='15W40'!F74 -> 52 | G74: =F74*G4 -> 231.92 | H74: 8 | I74: =B74-C74 -> 121.78 | J74: =C74/B74 -> 0.76935169 | K74: =1-J74 -> 0.23064831
K76: =SUM(K6:K74)/53 -> 0.36641779

Sheet 10W30 Gallon
A1: STANDARD JOB LIST | B1: 10W30 Gallon | D1: Delo | G1: ='Oil Price'!F25 -> 6.3835979 | H1: 0.05 | L1: 8--20 | M1: 10
B2: selling | C2: cost | E2: Filtre | F2: Litre | G2: Oil | H2: Fuel | I2: Profit | J2: Cost | K2: Profit | L2: 21--38 | M2: 15
A3: Auto Greaser Refill | E3: Cost | G3: Cost | H3: Grease | L3: 39--46 | M3: 20 | N3: Price Diff | O3: Cost Diff
G4: =G1+H1 -> 6.4335979 | J4: 1 | L4: 47& UP | M4: 25
A6: C 7 / 10 / 3126 With Cat Filter | B6: ='10W30'!B6+('10W30 Gallon'!G4-'10W30'!G4)*'10W30 Gallon'!F6+'10W30 Gallon'!M2 -> 355.32995 | C6: =E6+G6+H6 -> 222.12995 | E6: ='15W40'!E6 -> 53.29 | F6: ='15W40'!F6 -> 25 | G6: =F6*G4 -> 160.83995 | H6: 8 | I6: =B6-C6 -> 133.2 | J6: =C6/B6 -> 0.62513714 | K6: =1-J6 -> 0.37486286 | N6: =B6-'10W30'!B6 -> 64.339947 | O6: =C6-'10W30'!C6 -> 49.339947
A7: C 7 / 10 / 3126 With Fleetguard Filter | B7: ='10W30'!B7+('10W30 Gallon'!G4-'10W30'!G4)*'10W30 Gallon'!F7+'10W30 Gallon'!M2 -> 333.32995 | C7: =E7+G7+H7 -> 190.63915 | E7: ='15W40'!E7 -> 21.7992 | F7: ='15W40'!F7 -> 25 | G7: =F7*G4 -> 160.83995 | H7: 8 | I7: =B7-C7 -> 142.6908 | J7: =C7/B7 -> 0.57192325 | K7: =1-J7 -> 0.42807675 | N7: =B7-'10W30'!B7 -> 64.339947 | O7: =C7-'10W30'!C7 -> 49.339947
A9: C 12 / 3406 With Cat Filter | B9: ='10W30'!B9+('10W30 Gallon'!G4-'10W30'!G4)*'10W30 Gallon'!F9+'10W30 Gallon'!M2 -> 449.98672 | C9: =E9+G9+H9 -> 323.05672 | E9: ='15W40'!E9 -> 70.58 | F9: ='15W40'!F9 -> 38 | G9: =F9*G4 -> 244.47672 | H9: 8 | I9: =B9-C9 -> 126.93 | J9: =C9/B9 -> 0.71792501 | K9: =1-J9 -> 0.28207499 | N9: =B9-'10W30'!B9 -> 89.99672 | O9: =C9-'10W30'!C9 -> 74.99672
A10: C 12 / 3406 With Fleetguard Filter | B10: ='10W30'!B10+('10W30 Gallon'!G4-'10W30'!G4)*'10W30 Gallon'!F10+'10W30 Gallon'!M2 -> 408.98672 | C10: =E10+G10+H10 -> 283.52152 | E10: ='15W40'!E10 -> 31.0448 | F10: ='15W40'!F10 -> 38 | G10: =F10*G4 -> 244.47672 | H10: 8 | I10: =B10-C10 -> 125.4652 | J10: =C10/B10 -> 0.69322916 | K10: =1-J10 -> 0.30677084 | N10: =B10-'10W30'!B10 -> 89.99672 | O10: =C10-'10W30'!C10 -> 74.99672
A12: C 13 / 15 With Cat Filter | B12: ='10W30'!B12+('10W30 Gallon'!G4-'10W30'!G4)*'10W30 Gallon'!F12+'10W30 Gallon'!M3 -> 489.85471 | C12: =E12+G12+H12 -> 355.22471 | E12: ='15W40'!E12 -> 70.58 | F12: ='15W40'!F12 -> 43 | G12: =F12*G4 -> 276.64471 | H12: 8 | I12: =B12-C12 -> 134.63 | J12: =C12/B12 -> 0.72516341 | K12: =1-J12 -> 0.27483659 | N12: =B12-'10W30'!B12 -> 104.86471 | O12: =C12-'10W30'!C12 -> 84.864709
A13: C 13 / 15 With Fleetguard Filter | B13: ='10W30'!B13+('10W30 Gallon'!G4-'10W30'!G4)*'10W30 Gallon'!F13+'10W30 Gallon'!M3 -> 448.85471 | C13: =E13+G13+H13 -> 315.68951 | E13: ='15W40'!E13 -> 31.0448 | F13: ='15W40'!F13 -> 43 | G13: =F13*G4 -> 276.64471 | H13: 8 | I13: =B13-C13 -> 133.1652 | J13: =C13/B13 -> 0.70332226 | K13: =1-J13 -> 0.29667774 | N13: =B13-'10W30'!B13 -> 104.86471 | O13: =C13-'10W30'!C13 -> 84.864709
A15: Cummins N14 | B15: ='10W30'!B15+('10W30 Gallon'!G4-'10W30'!G4)*'10W30 Gallon'!F15+'10W30 Gallon'!M3 -> 430.93392 | C15: =E15+G15+H15 -> 296.77512 | E15: ='15W40'!E15 -> 31.4312 | F15: ='15W40'!F15 -> 40 | G15: =F15*G4 -> 257.34392 | H15: 8 | I15: =B15-C15 -> 134.1588 | J15: =C15/B15 -> 0.68867895 | K15: =1-J15 -> 0.31132105 | N15: =B15-'10W30'!B15 -> 98.943915 | O15: =C15-'10W30'!C15 -> 78.943915
A16: Cummins 5.9L/6.7L | B16: ='10W30'!B16+('10W30 Gallon'!G4-'10W30'!G4)*'10W30 Gallon'!F16+'10W30 Gallon'!M1 -> 223.62037 | C16: =E16+G16+H16 -> 104.79037 | E16: ='15W40'!E16 -> 6.72 | F16: ='15W40'!F16 -> 14 | G16: =F16*G4 -> 90.07037 | H16: 8 | I16: =B16-C16 -> 118.83 | J16: =C16/B16 -> 0.46860834 | K16: =1-J16 -> 0.53139166 | N16: =B16-'10W30'!B16 -> 37.63037 | O16: =C16-'10W30'!C16 -> 27.63037
A17: Cummins ISC / ISL | B17: ='10W30'!B17+('10W30 Gallon'!G4-'10W30'!G4)*'10W30 Gallon'!F17+'10W30 Gallon'!M2 -> 347.32995 | C17: =E17+G17+H17 -> 219.65035 | E17: ='15W40'!E17 -> 50.8104 | F17: ='15W40'!F17 -> 25 | G17: =F17*G4 -> 160.83995 | H17: 8 | I17: =B17-C17 -> 127.6796 | J17: =C17/B17 -> 0.6323968 | K17: =1-J17 -> 0.3676032 | N17: =B17-'10W30'!B17 -> 64.339947 | O17: =C17-'10W30'!C17 -> 49.339947
A18: Cummins ISB | B18: ='10W30'!B18+('10W30 Gallon'!G4-'10W30'!G4)*'10W30 Gallon'!F18+'10W30 Gallon'!M2 -> 345.32995 | C18: =E18+G18+H18 -> 195.52795 | E18: ='15W40'!E18 -> 26.688 | F18: ='15W40'!F18 -> 25 | G18: =F18*G4 -> 160.83995 | H18: 8 | I18: =B18-C18 -> 149.802 | J18: =C18/B18 -> 0.56620617 | K18: =1-J18 -> 0.43379383 | N18: =B18-'10W30'!B18 -> 64.339947 | O18: =C18-'10W30'!C18 -> 49.339947
A19: Cummins ISM | B19: ='10W30'!B19+('10W30 Gallon'!G4-'10W30'!G4)*'10W30 Gallon'!F19+'10W30 Gallon'!M2 -> 404.03952 | C19: =E19+G19+H19 -> 279.44392 | E19: ='15W40'!E19 -> 39.8344 | F19: ='15W40'!F19 -> 36 | G19: =F19*G4 -> 231.60952 | H19: 8 | I19: =B19-C19 -> 124.5956 | J19: =C19/B19 -> 0.69162522 | K19: =1-J19 -> 0.30837478 | N19: =B19-'10W30'!B19 -> 86.049524 | O19: =C19-'10W30'!C19 -> 71.049524
A20: Cummins ISX | B20: ='10W30'!B20+('10W30 Gallon'!G4-'10W30'!G4)*'10W30 Gallon'!F20+'10W30 Gallon'!M3 -> 515.82831 | C20: =E20+G20+H20 -> 376.72791 | E20: ='15W40'!E20 -> 85.6496 | F20: ='15W40'!F20 -> 44 | G20: =F20*G4 -> 283.07831 | H20: 8 | I20: =B20-C20 -> 139.1004 | J20: =C20/B20 -> 0.73033585 | K20: =1-J20 -> 0.26966415 | N20: =B20-'10W30'!B20 -> 106.83831 | O20: =C20-'10W30'!C20 -> 86.838307
A21: Cummins M11 | B21: ='10W30'!B21+('10W30 Gallon'!G4-'10W30'!G4)*'10W30 Gallon'!F21+'10W30 Gallon'!M2 -> 383.09233 | C21: =E21+G21+H21 -> 258.17353 | E21: ='15W40'!E21 -> 31.4312 | F21: ='15W40'!F21 -> 34 | G21: =F21*G4 -> 218.74233 | H21: 8 | I21: =B21-C21 -> 124.9188 | J21: =C21/B21 -> 0.67391986 | K21: =1-J21 -> 0.32608014 | N21: =B21-'10W30'!B21 -> 82.102328 | O21: =C21-'10W30'!C21 -> 67.102328
A23: Detroit With Detroit Filter | B23: ='10W30'!B23+('10W30 Gallon'!G4-'10W30'!G4)*'10W30 Gallon'!F23+'10W30 Gallon'!M2 -> 464.98672 | C23: =E23+G23+H23 -> 330.09672 | E23: ='15W40'!E23 -> 77.62 | F23: ='15W40'!F23 -> 38 | G23: =F23*G4 -> 244.47672 | H23: 8 | I23: =B23-C23 -> 134.89 | J23: =C23/B23 -> 0.70990569 | K23: =1-J23 -> 0.29009431 | N23: =B23-'10W30'!B23 -> 89.99672 | O23: =C23-'10W30'!C23 -> 74.99672
A24: Detroit With Detroit Filter (DD8) | B24: ='10W30'!B24+('10W30 Gallon'!G4-'10W30'!G4)*'10W30 Gallon'!F24+'10W30 Gallon'!M2 -> 513.14513 | C24: =E24+G24+H24 -> 382.72513 | E24: ='15W40'!E24 -> 168.85 | F24: ='15W40'!F24 -> 32 | G24: =F24*G4 -> 205.87513 | H24: 8 | I24: =B24-C24 -> 130.42 | J24: =C24/B24 -> 0.74584188 | K24: =1-J24 -> 0.25415812 | N24: =B24-'10W30'!B24 -> 78.155132 | O24: =C24-'10W30'!C24 -> 63.155132
A25: Detroit With Detroit Filter (DD13,DD15,DD16) | B25: ='10W30'!B25+('10W30 Gallon'!G4-'10W30'!G4)*'10W30 Gallon'!F25+'10W30 Gallon'!M3 -> 548.88111 | C25: =E25+G25+H25 -> 416.00111 | E25: ='15W40'!E25 -> 137.79 | F25: ='15W40'!F25 -> 42 | G25: =F25*G4 -> 270.21111 | H25: 8 | I25: =B25-C25 -> 132.88 | J25: =C25/B25 -> 0.7579075 | K25: =1-J25 -> 0.2420925 | N25: =B25-'10W30'!B25 -> 102.89111 | O25: =C25-'10W30'!C25 -> 82.891111
A26: Detroit With Fleetguard Filter (DD13,DD15.DD16) | B26: ='10W30'!B26+('10W30 Gallon'!G4-'10W30'!G4)*'10W30 Gallon'!F26+'10W30 Gallon'!M3 -> 526.88111 | C26: =E26+G26+H26 -> 392.26391 | E26: ='15W40'!E26 -> 114.0528 | F26: ='15W40'!F26 -> 42 | G26: =F26*G4 -> 270.21111 | H26: 8 | I26: =B26-C26 -> 134.6172 | J26: =C26/B26 -> 0.74450175 | K26: =1-J26 -> 0.25549825 | N26: =B26-'10W30'!B26 -> 102.89111 | O26: =C26-'10W30'!C26 -> 82.891111
A27: Detroit With Fleetguard | B27: ='10W30'!B27+('10W30 Gallon'!G4-'10W30'!G4)*'10W30 Gallon'!F27+'10W30 Gallon'!M2 -> 417.98672 | C27: =E27+G27+H27 -> 297.86792 | E27: ='15W40'!E27 -> 45.3912 | F27: ='15W40'!F27 -> 38 | G27: =F27*G4 -> 244.47672 | H27: 8 | I27: =B27-C27 -> 120.1188 | J27: =C27/B27 -> 0.71262532 | K27: =1-J27 -> 0.28737468 | N27: =B27-'10W30'!B27 -> 89.99672 | O27: =C27-'10W30'!C27 -> 74.99672
A28: Duramax / Vortec 8100L | B28: ='10W30'!B28+('10W30 Gallon'!G4-'10W30'!G4)*'10W30 Gallon'!F28+'10W30 Gallon'!M1 -> 223.62037 | C28: =E28+G28+H28 -> 108.17277 | E28: ='15W40'!E28 -> 10.1024 | F28: ='15W40'!F28 -> 14 | G28: =F28*G4 -> 90.07037 | H28: 8 | I28: =B28-C28 -> 115.4476 | J28: =C28/B28 -> 0.48373397 | K28: =1-J28 -> 0.51626603 | N28: =B28-'10W30'!B28 -> 37.63037 | O28: =C28-'10W30'!C28 -> 27.63037
A30: F250 / F350 / F550 / F650 | B30: ='10W30'!B30+('10W30 Gallon'!G4-'10W30'!G4)*'10W30 Gallon'!F30+'10W30 Gallon'!M1 -> 223.62037 | C30: =E30+G30+H30 -> 112.48717 | E30: ='15W40'!E30 -> 14.4168 | F30: ='15W40'!F30 -> 14 | G30: =F30*G4 -> 90.07037 | H30: 8 | I30: =B30-C30 -> 111.1332 | J30: =C30/B30 -> 0.50302739 | K30: =1-J30 -> 0.49697261 | N30: =B30-'10W30'!B30 -> 37.63037 | O30: =C30-'10W30'!C30 -> 27.63037
A32: Hino | B32: ='10W30'!B32+('10W30 Gallon'!G4-'10W30'!G4)*'10W30 Gallon'!F32+'10W30 Gallon'!M1 -> 322.62037 | C32: =E32+G32+H32 -> 194.07037 | E32: ='15W40'!E32 -> 96 | F32: ='15W40'!F32 -> 14 | G32: =F32*G4 -> 90.07037 | H32: 8 | I32: =B32-C32 -> 128.55 | J32: =C32/B32 -> 0.60154407 | K32: =1-J32 -> 0.39845593 | N32: =B32-'10W30'!B32 -> 37.63037 | O32: =C32-'10W30'!C32 -> 27.63037
A33: Hino With Fleetguard | B33: ='10W30'!B33+('10W30 Gallon'!G4-'10W30'!G4)*'10W30 Gallon'!F33+'10W30 Gallon'!M1 -> 252.62037 | C33: =E33+G33+H33 -> 125.49197 | E33: ='15W40'!E33 -> 27.4216 | F33: ='15W40'!F33 -> 14 | G33: =F33*G4 -> 90.07037 | H33: 8 | I33: =B33-C33 -> 127.1284 | J33: =C33/B33 -> 0.49676109 | K33: =1-J33 -> 0.50323891 | N33: =B33-'10W30'!B33 -> 37.63037 | O33: =C33-'10W30'!C33 -> 27.63037
A35: International | B35: ='10W30'!B35+('10W30 Gallon'!G4-'10W30'!G4)*'10W30 Gallon'!F35+'10W30 Gallon'!M2 -> 357.30354 | C35: =E35+G35+H35 -> 228.84234 | E35: ='15W40'!E35 -> 53.5688 | F35: ='15W40'!F35 -> 26 | G35: =F35*G4 -> 167.27354 | H35: 8 | I35: =B35-C35 -> 128.4612 | J35: =C35/B35 -> 0.6404704 | K35: =1-J35 -> 0.3595296 | N35: =B35-'10W30'!B35 -> 66.313545 | O35: =C35-'10W30'!C35 -> 51.313545
A36: International S13 | B36: ='10W30'!B36+('10W30 Gallon'!G4-'10W30'!G4)*'10W30 Gallon'!F36+'10W30 Gallon'!M3 -> 640.7755 | C36: =E36+G36+H36 -> 482.7455 | E36: ='15W40'!E36 -> 178.8 | F36: ='15W40'!F36 -> 46 | G36: =F36*G4 -> 295.9455 | H36: 8 | I36: =B36-C36 -> 158.03 | J36: =C36/B36 -> 0.75337696 | K36: =1-J36 -> 0.24662304 | O36: =C36-'10W30'!C36 -> 90.785503
A37: International Vista | B37: ='10W30'!B37+('10W30 Gallon'!G4-'10W30'!G4)*'10W30 Gallon'!F37+'10W30 Gallon'!M1 -> 302.62037 | C37: =E37+G37+H37 -> 155.94317 | E37: ='15W40'!E37 -> 57.8728 | F37: ='15W40'!F37 -> 14 | G37: =F37*G4 -> 90.07037 | H37: 8 | I37: =B37-C37 -> 146.6772 | J37: =C37/B37 -> 0.51530956 | K37: =1-J37 -> 0.48469044
A38: Isuzu With Fleetguard Filter | B38: ='10W30'!B38+('10W30 Gallon'!G4-'10W30'!G4)*'10W30 Gallon'!F38+'10W30 Gallon'!M1 -> 268.62037 | C38: =E38+G38+H38 -> 142.21117 | E38: ='15W40'!E38 -> 44.1408 | F38: ='15W40'!F38 -> 14 | G38: =F38*G4 -> 90.07037 | H38: 8 | I38: =B38-C38 -> 126.4092 | J38: =C38/B38 -> 0.5294132 | K38: =1-J38 -> 0.4705868 | N38: =B38-'10W30'!B38 -> 37.63037 | O38: =C38-'10W30'!C38 -> 27.63037
A39: Isuzu | B39: ='10W30'!B39+('10W30 Gallon'!G4-'10W30'!G4)*'10W30 Gallon'!F39+'10W30 Gallon'!M1 -> 328.62037 | C39: =E39+G39+H39 -> 167.04037 | E39: ='15W40'!E39 -> 68.97 | F39: ='15W40'!F39 -> 14 | G39: =F39*G4 -> 90.07037 | H39: 8 | I39: =B39-C39 -> 161.58 | J39: =C39/B39 -> 0.50830802 | K39: =1-J39 -> 0.49169198 | O39: =C39-'10W30'!C39 -> 27.63037
A41: MP 7 / MP8 With Fleetguard | B41: ='10W30'!B41+('10W30 Gallon'!G4-'10W30'!G4)*'10W30 Gallon'!F41+'10W30 Gallon'!M2 -> 478.98672 | C41: =E41+G41+H41 -> 339.08152 | E41: ='15W40'!E41 -> 86.6048 | F41: ='15W40'!F41 -> 38 | G41: =F41*G4 -> 244.47672 | H41: 8 | I41: =B41-C41 -> 139.9052 | J41: =C41/B41 -> 0.70791424 | K41: =1-J41 -> 0.29208576 | N41: =B41-'10W30'!B41 -> 89.99672 | O41: =C41-'10W30'!C41 -> 74.99672
A42: MP 7 / MP8 With Mack | B42: ='10W30'!B42+('10W30 Gallon'!G4-'10W30'!G4)*'10W30 Gallon'!F42+'10W30 Gallon'!M2 -> 549.98672 | C42: =E42+G42+H42 -> 425.97672 | E42: ='15W40'!E42 -> 173.5 | F42: ='15W40'!F42 -> 38 | G42: =F42*G4 -> 244.47672 | H42: 8 | I42: =B42-C42 -> 124.01 | J42: =C42/B42 -> 0.77452183 | K42: =1-J42 -> 0.22547817 | N42: =B42-'10W30'!B42 -> 89.99672 | O42: =C42-'10W30'!C42 -> 74.99672
A43: MP 7/MP8/ MP10 With Fleetguard ( 52L) | B43: ='10W30'!B43+('10W30 Gallon'!G4-'10W30'!G4)*'10W30 Gallon'!F43+'10W30 Gallon'!M3 -> 600.53788 | C43: =E43+G43+H43 -> 448.45268 | E43: ='15W40'!E43 -> 86.6048 | F43: ='15W40'!F43 -> 55 | G43: =F43*G4 -> 353.84788 | H43: 8 | I43: =B43-C43 -> 152.0852 | J43: =C43/B43 -> 0.7467517 | K43: =1-J43 -> 0.2532483 | O43: =C43-'10W30'!C43 -> 108.54788
A44: MP 7/MP8/ MP10 With Mack (52L) | B44: ='10W30'!B44+('10W30 Gallon'!G4-'10W30'!G4)*'10W30 Gallon'!F44+'10W30 Gallon'!M3 -> 673.53788 | C44: =E44+G44+H44 -> 535.34788 | E44: ='15W40'!E44 -> 173.5 | F44: ='15W40'!F44 -> 55 | G44: =F44*G4 -> 353.84788 | H44: 8 | I44: =B44-C44 -> 138.19 | J44: =C44/B44 -> 0.79482965 | K44: =1-J44 -> 0.20517035 | O44: =C44-'10W30'!C44 -> 108.54788
A45: Mack With Fleetguard Filter | B45: ='10W30'!B45+('10W30 Gallon'!G4-'10W30'!G4)*'10W30 Gallon'!F45+'10W30 Gallon'!M3 -> 437.98672 | C45: =E45+G45+H45 -> 302.86072 | E45: ='15W40'!E45 -> 50.384 | F45: ='15W40'!F45 -> 38 | G45: =F45*G4 -> 244.47672 | H45: 8 | I45: =B45-C45 -> 135.126 | J45: =C45/B45 -> 0.6914838 | K45: =1-J45 -> 0.3085162 | N45: =B45-'10W30'!B45 -> 94.99672 | O45: =C45-'10W30'!C45 -> 74.99672
A46: Mack With Fleetguard Filter(52L) | B46: ='10W30'!B46+('10W30 Gallon'!G4-'10W30'!G4)*'10W30 Gallon'!F46+'10W30 Gallon'!M4 -> 540.61709 | C46: =E46+G46+H46 -> 392.93109 | E46: ='15W40'!E46 -> 50.384 | F46: ='15W40'!F46 -> 52 | G46: =F46*G4 -> 334.54709 | H46: 8 | I46: =B46-C46 -> 147.686 | J46: =C46/B46 -> 0.72681959 | K46: =1-J46 -> 0.27318041 | N46: =B46-'10W30'!B46 -> 127.62709 | O46: =C46-'10W30'!C46 -> 102.62709
A47: Mack With Mack Filter | B47: ='10W30'!B47+('10W30 Gallon'!G4-'10W30'!G4)*'10W30 Gallon'!F47+'10W30 Gallon'!M2 -> 541.98672 | C47: =E47+G47+H47 -> 413.86672 | E47: ='15W40'!E47 -> 161.39 | F47: ='15W40'!F47 -> 38 | G47: =F47*G4 -> 244.47672 | H47: 8 | I47: =B47-C47 -> 128.12 | J47: =C47/B47 -> 0.76361044 | K47: =1-J47 -> 0.23638956 | N47: =B47-'10W30'!B47 -> 89.99672 | O47: =C47-'10W30'!C47 -> 74.99672
A48: Mack With Mack Filter( 52L ) | B48: ='10W30'!B48+('10W30 Gallon'!G4-'10W30'!G4)*'10W30 Gallon'!F48+'10W30 Gallon'!M4 -> 652.61709 | C48: =E48+G48+H48 -> 503.93709 | E48: ='15W40'!E48 -> 161.39 | F48: ='15W40'!F48 -> 52 | G48: =F48*G4 -> 334.54709 | H48: 8 | I48: =B48-C48 -> 148.68 | J48: =C48/B48 -> 0.77217881 | K48: =1-J48 -> 0.22782119 | N48: =B48-'10W30'!B48 -> 127.62709 | O48: =C48-'10W30'!C48 -> 102.62709
A50: Max Force 7 | B50: ='10W30'!B50+('10W30 Gallon'!G4-'10W30'!G4)*'10W30 Gallon'!F50+'10W30 Gallon'!M2 -> 527.30354 | C50: =E50+G50+H50 -> 397.95354 | E50: ='15W40'!E50 -> 222.68 | F50: ='15W40'!F50 -> 26 | G50: =F50*G4 -> 167.27354 | H50: 8 | I50: =B50-C50 -> 129.35 | J50: =C50/B50 -> 0.75469537 | K50: =1-J50 -> 0.24530463 | N50: =B50-'10W30'!B50 -> 66.313545 | O50: =C50-'10W30'!C50 -> 51.313545
A51: Max Force 7 With Fleetguard | B51: ='10W30'!B51+('10W30 Gallon'!G4-'10W30'!G4)*'10W30 Gallon'!F51+'10W30 Gallon'!M2 -> 448.30354 | C51: =E51+G51+H51 -> 320.44954 | E51: ='15W40'!E51 -> 145.176 | F51: ='15W40'!F51 -> 26 | G51: =F51*G4 -> 167.27354 | H51: 8 | I51: =B51-C51 -> 127.854 | J51: =C51/B51 -> 0.71480484 | K51: =1-J51 -> 0.28519516 | N51: =B51-'10W30'!B51 -> 66.313545 | O51: =C51-'10W30'!C51 -> 51.313545
A52: Max Force 13 | B52: ='10W30'!B52+('10W30 Gallon'!G4-'10W30'!G4)*'10W30 Gallon'!F52+'10W30 Gallon'!M2 -> 549.98672 | C52: =E52+G52+H52 -> 417.16672 | E52: ='15W40'!E52 -> 164.69 | F52: ='15W40'!F52 -> 38 | G52: =F52*G4 -> 244.47672 | H52: 8 | I52: =B52-C52 -> 132.82 | J52: =C52/B52 -> 0.75850326 | K52: =1-J52 -> 0.24149674 | N52: =B52-'10W30'!B52 -> 89.99672 | O52: =C52-'10W30'!C52 -> 74.99672
A53: Max Force 13 With Fleetguard | B53: ='10W30'!B53+('10W30 Gallon'!G4-'10W30'!G4)*'10W30 Gallon'!F53+'10W30 Gallon'!M2 -> 471.98672 | C53: =E53+G53+H53 -> 341.27992 | E53: ='15W40'!E53 -> 88.8032 | F53: ='15W40'!F53 -> 38 | G53: =F53*G4 -> 244.47672 | H53: 8 | I53: =B53-C53 -> 130.7068 | J53: =C53/B53 -> 0.72307102 | K53: =1-J53 -> 0.27692898 | N53: =B53-'10W30'!B53 -> 89.99672 | O53: =C53-'10W30'!C53 -> 74.99672
A55: Mercedes Benz 4000 | B55: ='10W30'!B55+('10W30 Gallon'!G4-'10W30'!G4)*'10W30 Gallon'!F55+'10W30 Gallon'!M3 -> 507.7491 | C55: =E55+G55+H55 -> 360.3891 | E55: ='15W40'!E55 -> 50.01 | F55: ='15W40'!F55 -> 47 | G55: =F55*G4 -> 302.3791 | H55: 8 | I55: =B55-C55 -> 147.36 | J55: =C55/B55 -> 0.70977792 | K55: =1-J55 -> 0.29022208 | N55: =B55-'10W30'!B55 -> 112.7591 | O55: =C55-'10W30'!C55 -> 92.759101
A56: Mercedes Benz 4000 With Fleeguard Filter | B56: ='10W30'!B56+('10W30 Gallon'!G4-'10W30'!G4)*'10W30 Gallon'!F56+'10W30 Gallon'!M3 -> 485.7491 | C56: =E56+G56+H56 -> 351.8207 | E56: ='15W40'!E56 -> 41.4416 | F56: ='15W40'!F56 -> 47 | G56: =F56*G4 -> 302.3791 | H56: 8 | I56: =B56-C56 -> 133.9284 | J56: =C56/B56 -> 0.72428482 | K56: =1-J56 -> 0.27571518 | N56: =B56-'10W30'!B56 -> 112.7591 | O56: =C56-'10W30'!C56 -> 92.759101
A57: Mercedes Benz 900 | B57: ='10W30'!B57+('10W30 Gallon'!G4-'10W30'!G4)*'10W30 Gallon'!F57+'10W30 Gallon'!M2 -> 371.30354 | C57: =E57+G57+H57 -> 222.82354 | E57: ='15W40'!E57 -> 47.55 | F57: ='15W40'!F57 -> 26 | G57: =F57*G4 -> 167.27354 | H57: 8 | I57: =B57-C57 -> 148.48 | J57: =C57/B57 -> 0.60011155 | K57: =1-J57 -> 0.39988845 | N57: =B57-'10W30'!B57 -> 66.313545 | O57: =C57-'10W30'!C57 -> 51.313545
A58: Mercedes Benz 900 With Fleetguard Filter | B58: ='10W30'!B58+('10W30 Gallon'!G4-'10W30'!G4)*'10W30 Gallon'!F58+'10W30 Gallon'!M2 -> 333.30354 | C58: =E58+G58+H58 -> 208.74954 | E58: ='15W40'!E58 -> 33.476 | F58: ='15W40'!F58 -> 26 | G58: =F58*G4 -> 167.27354 | H58: 8 | I58: =B58-C58 -> 124.554 | J58: =C58/B58 -> 0.6263046 | K58: =1-J58 -> 0.3736954 | N58: =B58-'10W30'!B58 -> 66.313545 | O58: =C58-'10W30'!C58 -> 51.313545
A59: Mercedes Benz Sprinter | B59: ='10W30'!B59+('10W30 Gallon'!G4-'10W30'!G4)*'10W30 Gallon'!F59+'10W30 Gallon'!M1 -> 302.35635 | C59: =E59+G59+H59 -> 162.40635 | E59: ='15W40'!E59 -> 0 | F59: ='15W40'!F59 -> 24 | G59: =F59*G4 -> 154.40635 | H59: 8 | I59: =B59-C59 -> 139.95 | J59: =C59/B59 -> 0.53713557 | K59: =1-J59 -> 0.46286443 | N59: =B59-'10W30'!B59 -> 57.366349 | O59: =C59-'10W30'!C59 -> 47.366349
A60: Mitsubishi | B60: ='10W30'!B60+('10W30 Gallon'!G4-'10W30'!G4)*'10W30 Gallon'!F60+'10W30 Gallon'!M1 -> 280.64677 | C60: =E60+G60+H60 -> 164.87677 | E60: ='15W40'!E60 -> 73.24 | F60: ='15W40'!F60 -> 13 | G60: =F60*G4 -> 83.636772 | H60: 8 | I60: =B60-C60 -> 115.77 | J60: =C60/B60 -> 0.58748858 | K60: =1-J60 -> 0.41251142 | N60: =B60-'10W30'!B60 -> 35.656772 | O60: =C60-'10W30'!C60 -> 25.656772
A63: Navistar | B63: ='10W30'!B63+('10W30 Gallon'!G4-'10W30'!G4)*'10W30 Gallon'!F63+'10W30 Gallon'!M2 -> 338.30354 | C63: =E63+G63+H63 -> 213.29994 | E63: ='15W40'!E63 -> 38.0264 | F63: ='15W40'!F63 -> 26 | G63: =F63*G4 -> 167.27354 | H63: 8 | I63: =B63-C63 -> 125.0036 | J63: =C63/B63 -> 0.6304987 | K63: =1-J63 -> 0.3695013 | N63: =B63-'10W30'!B63 -> 66.313545 | O63: =C63-'10W30'!C63 -> 51.313545
A65: Paccer | B65: ='10W30'!B65+('10W30 Gallon'!G4-'10W30'!G4)*'10W30 Gallon'!F65+'10W30 Gallon'!M3 -> 599.7755 | C65: =E65+G65+H65 -> 465.9955 | E65: ='15W40'!E65 -> 162.05 | F65: ='15W40'!F65 -> 46 | G65: =F65*G4 -> 295.9455 | H65: 8 | I65: =B65-C65 -> 133.78 | J65: =C65/B65 -> 0.77694988 | K65: =1-J65 -> 0.22305012 | N65: =B65-'10W30'!B65 -> 110.7855 | O65: =C65-'10W30'!C65 -> 90.785503
A66: Paccer With Fleetguard | B66: ='10W30'!B66+('10W30 Gallon'!G4-'10W30'!G4)*'10W30 Gallon'!F66+'10W30 Gallon'!M3 -> 520.7755 | C66: =E66+G66+H66 -> 383.7927 | E66: ='15W40'!E66 -> 79.8472 | F66: ='15W40'!F66 -> 46 | G66: =F66*G4 -> 295.9455 | H66: 8 | I66: =B66-C66 -> 136.9828 | J66: =C66/B66 -> 0.73696382 | K66: =1-J66 -> 0.26303618 | N66: =B66-'10W30'!B66 -> 110.7855 | O66: =C66-'10W30'!C66 -> 90.785503
A67: Paccer Small | B67: ='10W30'!B67+('10W30 Gallon'!G4-'10W30'!G4)*'10W30 Gallon'!F67+'10W30 Gallon'!M2 -> 317.35635 | C67: =E67+G67+H67 -> 189.09435 | E67: ='15W40'!E67 -> 26.688 | F67: ='15W40'!F67 -> 24 | G67: =F67*G4 -> 154.40635 | H67: 8 | I67: =B67-C67 -> 128.262 | J67: =C67/B67 -> 0.59584234 | K67: =1-J67 -> 0.40415766 | N67: =B67-'10W30'!B67 -> 62.366349 | O67: =C67-'10W30'!C67 -> 47.366349
A69: Volvo With Fleetguard | B69: ='10W30'!B69+('10W30 Gallon'!G4-'10W30'!G4)*'10W30 Gallon'!F69+'10W30 Gallon'!M2 -> 453.09233 | C69: =E69+G69+H69 -> 313.34713 | E69: ='15W40'!E69 -> 86.6048 | F69: ='15W40'!F69 -> 34 | G69: =F69*G4 -> 218.74233 | H69: 8 | I69: =B69-C69 -> 139.7452 | J69: =C69/B69 -> 0.69157456 | K69: =1-J69 -> 0.30842544 | N69: =B69-'10W30'!B69 -> 82.102328 | O69: =C69-'10W30'!C69 -> 67.102328
A70: Volvo With Fleetguard(D16 42L) | B70: ='10W30'!B70+('10W30 Gallon'!G4-'10W30'!G4)*'10W30 Gallon'!F70+'10W30 Gallon'!M3 -> 512.88111 | C70: =E70+G70+H70 -> 364.81591 | E70: ='15W40'!E70 -> 86.6048 | F70: ='15W40'!F70 -> 42 | G70: =F70*G4 -> 270.21111 | H70: 8 | I70: =B70-C70 -> 148.0652 | J70: =C70/B70 -> 0.71130697 | K70: =1-J70 -> 0.28869303 | N70: =B70-'10W30'!B70 -> 102.89111 | O70: =C70-'10W30'!C70 -> 82.891111
A71: Volvo With Fleetguard(D16 52L) | B71: ='10W30'!B71+('10W30 Gallon'!G4-'10W30'!G4)*'10W30 Gallon'!F71+'10W30 Gallon'!M4 -> 587.61709 | C71: =E71+G71+H71 -> 429.15189 | E71: ='15W40'!E71 -> 86.6048 | F71: ='15W40'!F71 -> 52 | G71: =F71*G4 -> 334.54709 | H71: 8 | I71: =B71-C71 -> 158.4652 | J71: =C71/B71 -> 0.73032575 | K71: =1-J71 -> 0.26967425 | N71: =B71-'10W30'!B71 -> 127.62709 | O71: =C71-'10W30'!C71 -> 102.62709
A72: Volvo With Volvo Filter | B72: ='10W30'!B72+('10W30 Gallon'!G4-'10W30'!G4)*'10W30 Gallon'!F72+'10W30 Gallon'!M2 -> 522.09233 | C72: =E72+G72+H72 -> 393.03233 | E72: ='15W40'!E72 -> 166.29 | F72: ='15W40'!F72 -> 34 | G72: =F72*G4 -> 218.74233 | H72: 8 | I72: =B72-C72 -> 129.06 | J72: =C72/B72 -> 0.75280234 | K72: =1-J72 -> 0.24719766 | N72: =B72-'10W30'!B72 -> 82.102328 | O72: =C72-'10W30'!C72 -> 67.102328
A73: Volvo With Volvo Filter (D16 42L) | B73: ='10W30'!B73+('10W30 Gallon'!G4-'10W30'!G4)*'10W30 Gallon'!F73+'10W30 Gallon'!M3 -> 582.88111 | C73: =E73+G73+H73 -> 444.50111 | E73: ='15W40'!E73 -> 166.29 | F73: ='15W40'!F73 -> 42 | G73: =F73*G4 -> 270.21111 | H73: 8 | I73: =B73-C73 -> 138.38 | J73: =C73/B73 -> 0.7625931 | K73: =1-J73 -> 0.2374069 | N73: =B73-'10W30'!B73 -> 102.89111 | O73: =C73-'10W30'!C73 -> 82.891111
A74: Volvo With Volvo Filter (D16 52L) | B74: ='10W30'!B74+('10W30 Gallon'!G4-'10W30'!G4)*'10W30 Gallon'!F74+'10W30 Gallon'!M4 -> 655.61709 | C74: =E74+G74+H74 -> 508.83709 | E74: ='15W40'!E74 -> 166.29 | F74: ='15W40'!F74 -> 52 | G74: =F74*G4 -> 334.54709 | H74: 8 | I74: =B74-C74 -> 146.78 | J74: =C74/B74 -> 0.77611932 | K74: =1-J74 -> 0.22388068 | N74: =B74-'10W30'!B74 -> 127.62709 | O74: =C74-'10W30'!C74 -> 102.62709

Sheet T5
A1: STANDARD JOB LIST | B1: T5 | G1: ='Oil Price'!C9 -> 3.89 | H1: 0.05 | L1: 8--20 | M1: 15
B2: selling | C2: cost | E2: Filtre | F2: Litre | G2: Oil | H2: Fuel | I2: Profit | J2: Cost | K2: Profit | L2: 21--38 | M2: 25
E3: Cost | G3: Cost | H3: Grease | L3: 39--46 | M3: 30
G4: =G1+H1 -> 3.94 | J4: 1 | L4: 47& UP | M4: 35
A6: C 7 / 10 / 3126 With Cat Filter | B6: ='15W40'!B6+'T5'!M2 -> 290.99 | C6: =E6+G6+H6 -> 159.79 | E6: ='15W40'!E6 -> 53.29 | F6: ='15W40'!F6 -> 25 | G6: =F6*G4 -> 98.5 | H6: 8 | I6: =B6-C6 -> 131.2 | J6: =C6/B6 -> 0.5491254 | K6: =1-J6 -> 0.4508746
A7: C 7 / 10 / 3126 With Fleetguard Filter | B7: ='15W40'!B7+'T5'!M2 -> 268.99 | C7: =E7+G7+H7 -> 128.2992 | E7: ='15W40'!E7 -> 21.7992 | F7: ='15W40'!F7 -> 25 | G7: =F7*G4 -> 98.5 | H7: 8 | I7: =B7-C7 -> 140.6908 | J7: =C7/B7 -> 0.47696643 | K7: =1-J7 -> 0.52303357
A9: C 12 / 3406 With Cat Filter | B9: ='15W40'!B9+'T5'!M2 -> 359.99 | C9: =E9+G9+H9 -> 228.3 | E9: ='15W40'!E9 -> 70.58 | F9: ='15W40'!F9 -> 38 | G9: =F9*G4 -> 149.72 | H9: 8 | I9: =B9-C9 -> 131.69 | J9: =C9/B9 -> 0.63418428 | K9: =1-J9 -> 0.36581572
A10: C 12 / 3406 With Fleetguard Filter | B10: ='15W40'!B10+'T5'!M2 -> 318.99 | C10: =E10+G10+H10 -> 188.7648 | E10: ='15W40'!E10 -> 31.0448 | F10: ='15W40'!F10 -> 38 | G10: =F10*G4 -> 149.72 | H10: 8 | I10: =B10-C10 -> 130.2252 | J10: =C10/B10 -> 0.59175774 | K10: =1-J10 -> 0.40824226
A12: C 13 / 15 With Cat Filter | B12: ='15W40'!B12+'T5'!M3 -> 384.99 | C12: =E12+G12+H12 -> 248 | E12: ='15W40'!E12 -> 70.58 | F12: ='15W40'!F12 -> 43 | G12: =F12*G4 -> 169.42 | H12: 8 | I12: =B12-C12 -> 136.99 | J12: =C12/B12 -> 0.64417258 | K12: =1-J12 -> 0.35582742
A13: C 13 / 15 With Fleetguard Filter | B13: ='15W40'!B13+'T5'!M3 -> 343.99 | C13: =E13+G13+H13 -> 208.4648 | E13: ='15W40'!E13 -> 31.0448 | F13: ='15W40'!F13 -> 43 | G13: =F13*G4 -> 169.42 | H13: 8 | I13: =B13-C13 -> 135.5252 | J13: =C13/B13 -> 0.60601994 | K13: =1-J13 -> 0.39398006
A15: Cummins N14 | B15: ='15W40'!B15+'T5'!M3 -> 331.99 | C15: =E15+G15+H15 -> 197.0312 | E15: ='15W40'!E15 -> 31.4312 | F15: ='15W40'!F15 -> 40 | G15: =F15*G4 -> 157.6 | H15: 8 | I15: =B15-C15 -> 134.9588 | J15: =C15/B15 -> 0.59348535 | K15: =1-J15 -> 0.40651465
A16: Cummins 5.9L/6.7L | B16: ='15W40'!B16+'T5'!M1 -> 185.99 | C16: =E16+G16+H16 -> 69.88 | E16: ='15W40'!E16 -> 6.72 | F16: ='15W40'!F16 -> 14 | G16: =F16*G4 -> 55.16 | H16: 8 | I16: =B16-C16 -> 116.11 | J16: =C16/B16 -> 0.37571912 | K16: =1-J16 -> 0.62428088
A17: Cummins ISC / ISL | B17: ='15W40'!B17+'T5'!M2 -> 282.99 | C17: =E17+G17+H17 -> 157.3104 | E17: ='15W40'!E17 -> 50.8104 | F17: ='15W40'!F17 -> 25 | G17: =F17*G4 -> 98.5 | H17: 8 | I17: =B17-C17 -> 125.6796 | J17: =C17/B17 -> 0.55588678 | K17: =1-J17 -> 0.44411322
A18: Cummins ISB | B18: ='15W40'!B18+'T5'!M2 -> 280.99 | C18: =E18+G18+H18 -> 133.188 | E18: ='15W40'!E18 -> 26.688 | F18: ='15W40'!F18 -> 25 | G18: =F18*G4 -> 98.5 | H18: 8 | I18: =B18-C18 -> 147.802 | J18: =C18/B18 -> 0.47399552 | K18: =1-J18 -> 0.52600448
A19: Cummins ISM | B19: ='15W40'!B19+'T5'!M2 -> 317.99 | C19: =E19+G19+H19 -> 189.6744 | E19: ='15W40'!E19 -> 39.8344 | F19: ='15W40'!F19 -> 36 | G19: =F19*G4 -> 141.84 | H19: 8 | I19: =B19-C19 -> 128.3156 | J19: =C19/B19 -> 0.59647913 | K19: =1-J19 -> 0.40352087
A20: Cummins ISX | B20: ='15W40'!B20+'T5'!M3 -> 408.99 | C20: =E20+G20+H20 -> 267.0096 | E20: ='15W40'!E20 -> 85.6496 | F20: ='15W40'!F20 -> 44 | G20: =F20*G4 -> 173.36 | H20: 8 | I20: =B20-C20 -> 141.9804 | J20: =C20/B20 -> 0.65285117 | K20: =1-J20 -> 0.34714883
A21: Cummins M11 | B21: ='15W40'!B21+'T5'!M2 -> 300.99 | C21: =E21+G21+H21 -> 173.3912 | E21: ='15W40'!E21 -> 31.4312 | F21: ='15W40'!F21 -> 34 | G21: =F21*G4 -> 133.96 | H21: 8 | I21: =B21-C21 -> 127.5988 | J21: =C21/B21 -> 0.57606964 | K21: =1-J21 -> 0.42393036
A23: Detroit With Detroit Filter | B23: ='15W40'!B23+'T5'!M2 -> 374.99 | C23: =E23+G23+H23 -> 235.34 | E23: ='15W40'!E23 -> 77.62 | F23: ='15W40'!F23 -> 38 | G23: =F23*G4 -> 149.72 | H23: 8 | I23: =B23-C23 -> 139.65 | J23: =C23/B23 -> 0.62759007 | K23: =1-J23 -> 0.37240993
A24: Detroit With Detroit Filter (DD8) | B24: ='15W40'!B24+'T5'!M2 -> 434.99 | C24: =E24+G24+H24 -> 302.93 | E24: ='15W40'!E24 -> 168.85 | F24: ='15W40'!F24 -> 32 | G24: =F24*G4 -> 126.08 | H24: 8 | I24: =B24-C24 -> 132.06 | J24: =C24/B24 -> 0.69640681 | K24: =1-J24 -> 0.30359319
A25: Detroit With Detroit Filter (DD13,DD15,DD16) | B25: ='15W40'!B25+'T5'!M3 -> 445.99 | C25: =E25+G25+H25 -> 311.27 | E25: ='15W40'!E25 -> 137.79 | F25: ='15W40'!F25 -> 42 | G25: =F25*G4 -> 165.48 | H25: 8 | I25: =B25-C25 -> 134.72 | J25: =C25/B25 -> 0.69793045 | K25: =1-J25 -> 0.30206955
A26: Detroit With Fleetguard Filter (DD13,DD15.DD16) | B26: ='15W40'!B26+'T5'!M3 -> 423.99 | C26: =E26+G26+H26 -> 287.5328 | E26: ='15W40'!E26 -> 114.0528 | F26: ='15W40'!F26 -> 42 | G26: =F26*G4 -> 165.48 | H26: 8 | I26: =B26-C26 -> 136.4572 | J26: =C26/B26 -> 0.67815939 | K26: =1-J26 -> 0.32184061
A27: Detroit With Fleetguard | B27: ='15W40'!B27+'T5'!M2 -> 327.99 | C27: =E27+G27+H27 -> 203.1112 | E27: ='15W40'!E27 -> 45.3912 | F27: ='15W40'!F27 -> 38 | G27: =F27*G4 -> 149.72 | H27: 8 | I27: =B27-C27 -> 124.8788 | J27: =C27/B27 -> 0.61926034 | K27: =1-J27 -> 0.38073966
A28: Duramax / Vortec 8100L | B28: ='15W40'!B28+'T5'!M1 -> 185.99 | C28: =E28+G28+H28 -> 73.2624 | E28: ='15W40'!E28 -> 10.1024 | F28: ='15W40'!F28 -> 14 | G28: =F28*G4 -> 55.16 | H28: 8 | I28: =B28-C28 -> 112.7276 | J28: =C28/B28 -> 0.39390505 | K28: =1-J28 -> 0.60609495
A30: F250 / F350 / F550 / F650 | B30: ='15W40'!B30+'T5'!M1 -> 185.99 | C30: =E30+G30+H30 -> 77.5768 | E30: ='15W40'!E30 -> 14.4168 | F30: ='15W40'!F30 -> 14 | G30: =F30*G4 -> 55.16 | H30: 8 | I30: =B30-C30 -> 108.4132 | J30: =C30/B30 -> 0.41710199 | K30: =1-J30 -> 0.58289801
A32: Hino | B32: ='15W40'!B32+'T5'!M1 -> 284.99 | C32: =E32+G32+H32 -> 159.16 | E32: ='15W40'!E32 -> 96 | F32: ='15W40'!F32 -> 14 | G32: =F32*G4 -> 55.16 | H32: 8 | I32: =B32-C32 -> 125.83 | J32: =C32/B32 -> 0.55847574 | K32: =1-J32 -> 0.44152426
A33: Hino With Fleetguard | B33: ='15W40'!B33+'T5'!M1 -> 214.99 | C33: =E33+G33+H33 -> 90.5816 | E33: ='15W40'!E33 -> 27.4216 | F33: ='15W40'!F33 -> 14 | G33: =F33*G4 -> 55.16 | H33: 8 | I33: =B33-C33 -> 124.4084 | J33: =C33/B33 -> 0.42132936 | K33: =1-J33 -> 0.57867064
A35: International | B35: ='15W40'!B35+'T5'!M2 -> 290.99 | C35: =E35+G35+H35 -> 164.0088 | E35: ='15W40'!E35 -> 53.5688 | F35: ='15W40'!F35 -> 26 | G35: =F35*G4 -> 102.44 | H35: 8 | I35: =B35-C35 -> 126.9812 | J35: =C35/B35 -> 0.56362349 | K35: =1-J35 -> 0.43637651
A36: International S13 | B36: ='15W40'!B36+'T5'!M3 -> 529.99 | C36: =E36+G36+H36 -> 368.04 | E36: ='15W40'!E36 -> 178.8 | F36: ='15W40'!F36 -> 46 | G36: =F36*G4 -> 181.24 | H36: 8 | I36: =B36-C36 -> 161.95 | J36: =C36/B36 -> 0.6944282 | K36: =1-J36 -> 0.3055718
A37: International Vista | B37: ='15W40'!B37+'T5'!M1 -> 264.99 | C37: =E37+G37+H37 -> 121.0328 | E37: ='15W40'!E37 -> 57.8728 | F37: ='15W40'!F37 -> 14 | G37: =F37*G4 -> 55.16 | H37: 8 | I37: =B37-C37 -> 143.9572 | J37: =C37/B37 -> 0.45674478 | K37: =1-J37 -> 0.54325522
A38: Isuzu With Fleetguard Filter | B38: ='15W40'!B38+'T5'!M1 -> 230.99 | C38: =E38+G38+H38 -> 107.3008 | E38: ='15W40'!E38 -> 44.1408 | F38: ='15W40'!F38 -> 14 | G38: =F38*G4 -> 55.16 | H38: 8 | I38: =B38-C38 -> 123.6892 | J38: =C38/B38 -> 0.46452574 | K38: =1-J38 -> 0.53547426
A39: Isuzu | B39: ='15W40'!B39+'T5'!M1 -> 290.99 | C39: =E39+G39+H39 -> 132.13 | E39: ='15W40'!E39 -> 68.97 | F39: ='15W40'!F39 -> 14 | G39: =F39*G4 -> 55.16 | H39: 8 | I39: =B39-C39 -> 158.86 | J39: =C39/B39 -> 0.45407059 | K39: =1-J39 -> 0.54592941
A41: MP 7 / MP8 With Fleetguard | B41: ='15W40'!B41+'T5'!M2 -> 388.99 | C41: =E41+G41+H41 -> 244.3248 | E41: ='15W40'!E41 -> 86.6048 | F41: ='15W40'!F41 -> 38 | G41: =F41*G4 -> 149.72 | H41: 8 | I41: =B41-C41 -> 144.6652 | J41: =C41/B41 -> 0.62810047 | K41: =1-J41 -> 0.37189953
A42: MP 7 / MP8 With Mack | B42: ='15W40'!B42+'T5'!M2 -> 459.99 | C42: =E42+G42+H42 -> 331.22 | E42: ='15W40'!E42 -> 173.5 | F42: ='15W40'!F42 -> 38 | G42: =F42*G4 -> 149.72 | H42: 8 | I42: =B42-C42 -> 128.77 | J42: =C42/B42 -> 0.72005913 | K42: =1-J42 -> 0.27994087
A43: MP 7/MP8/ MP10 With Fleetguard ( 52L) | B43: ='15W40'!B43+'T5'!M4 -> 471.99 | C43: =E43+G43+H43 -> 311.3048 | E43: ='15W40'!E43 -> 86.6048 | F43: ='15W40'!F43 -> 55 | G43: =F43*G4 -> 216.7 | H43: 8 | I43: =B43-C43 -> 160.6852 | J43: =C43/B43 -> 0.65955804 | K43: =1-J43 -> 0.34044196
A44: MP 7/MP8/ MP10 With Mack (52L) | B44: ='15W40'!B44+'T5'!M4 -> 544.99 | C44: =E44+G44+H44 -> 398.2 | E44: ='15W40'!E44 -> 173.5 | F44: ='15W40'!F44 -> 55 | G44: =F44*G4 -> 216.7 | H44: 8 | I44: =B44-C44 -> 146.79 | J44: =C44/B44 -> 0.73065561 | K44: =1-J44 -> 0.26934439
A45: Mack With Fleetguard Filter | B45: ='15W40'!B45+'T5'!M2 -> 342.99 | C45: =E45+G45+H45 -> 208.104 | E45: ='15W40'!E45 -> 50.384 | F45: ='15W40'!F45 -> 38 | G45: =F45*G4 -> 149.72 | H45: 8 | I45: =B45-C45 -> 134.886 | J45: =C45/B45 -> 0.60673489 | K45: =1-J45 -> 0.39326511
A46: Mack With Fleetguard Filter(52L) | B46: ='15W40'!B46+'T5'!M4 -> 412.99 | C46: =E46+G46+H46 -> 263.264 | E46: ='15W40'!E46 -> 50.384 | F46: ='15W40'!F46 -> 52 | G46: =F46*G4 -> 204.88 | H46: 8 | I46: =B46-C46 -> 149.726 | J46: =C46/B46 -> 0.63745853 | K46: =1-J46 -> 0.36254147
A47: Mack With Mack Filter | B47: ='15W40'!B47+'T5'!M2 -> 451.99 | C47: =E47+G47+H47 -> 319.11 | E47: ='15W40'!E47 -> 161.39 | F47: ='15W40'!F47 -> 38 | G47: =F47*G4 -> 149.72 | H47: 8 | I47: =B47-C47 -> 132.88 | J47: =C47/B47 -> 0.70601119 | K47: =1-J47 -> 0.29398881
A48: Mack With Mack Filter( 52L ) | B48: ='15W40'!B48+'T5'!M4 -> 524.99 | C48: =E48+G48+H48 -> 374.27 | E48: ='15W40'!E48 -> 161.39 | F48: ='15W40'!F48 -> 52 | G48: =F48*G4 -> 204.88 | H48: 8 | I48: =B48-C48 -> 150.72 | J48: =C48/B48 -> 0.71290882 | K48: =1-J48 -> 0.28709118
A50: Max Force 7 | B50: ='15W40'!B50+'T5'!M2 -> 460.99 | C50: =E50+G50+H50 -> 333.12 | E50: ='15W40'!E50 -> 222.68 | F50: ='15W40'!F50 -> 26 | G50: =F50*G4 -> 102.44 | H50: 8 | I50: =B50-C50 -> 127.87 | J50: =C50/B50 -> 0.72261871 | K50: =1-J50 -> 0.27738129
A51: Max Force 7 With Fleetguard | B51: ='15W40'!B51+'T5'!M2 -> 381.99 | C51: =E51+G51+H51 -> 255.616 | E51: ='15W40'!E51 -> 145.176 | F51: ='15W40'!F51 -> 26 | G51: =F51*G4 -> 102.44 | H51: 8 | I51: =B51-C51 -> 126.374 | J51: =C51/B51 -> 0.66916935 | K51: =1-J51 -> 0.33083065
A52: Max Force 13 | B52: ='15W40'!B52+'T5'!M2 -> 459.99 | C52: =E52+G52+H52 -> 322.41 | E52: ='15W40'!E52 -> 164.69 | F52: ='15W40'!F52 -> 38 | G52: =F52*G4 -> 149.72 | H52: 8 | I52: =B52-C52 -> 137.58 | J52: =C52/B52 -> 0.70090654 | K52: =1-J52 -> 0.29909346
A53: Max Force 13 With Fleetguard | B53: ='15W40'!B53+'T5'!M2 -> 381.99 | C53: =E53+G53+H53 -> 246.5232 | E53: ='15W40'!E53 -> 88.8032 | F53: ='15W40'!F53 -> 38 | G53: =F53*G4 -> 149.72 | H53: 8 | I53: =B53-C53 -> 135.4668 | J53: =C53/B53 -> 0.64536559 | K53: =1-J53 -> 0.35463441
A55: Mercedes Benz 4000 | B55: ='15W40'!B55+'T5'!M3 -> 394.99 | C55: =E55+G55+H55 -> 243.19 | E55: ='15W40'!E55 -> 50.01 | F55: ='15W40'!F55 -> 47 | G55: =F55*G4 -> 185.18 | H55: 8 | I55: =B55-C55 -> 151.8 | J55: =C55/B55 -> 0.61568647 | K55: =1-J55 -> 0.38431353
A56: Mercedes Benz 4000 With Fleeguard Filter | B56: ='15W40'!B56+'T5'!M3 -> 372.99 | C56: =E56+G56+H56 -> 234.6216 | E56: ='15W40'!E56 -> 41.4416 | F56: ='15W40'!F56 -> 47 | G56: =F56*G4 -> 185.18 | H56: 8 | I56: =B56-C56 -> 138.3684 | J56: =C56/B56 -> 0.6290292 | K56: =1-J56 -> 0.3709708
A57: Mercedes Benz 900 | B57: ='15W40'!B57+'T5'!M2 -> 304.99 | C57: =E57+G57+H57 -> 157.99 | E57: ='15W40'!E57 -> 47.55 | F57: ='15W40'!F57 -> 26 | G57: =F57*G4 -> 102.44 | H57: 8 | I57: =B57-C57 -> 147 | J57: =C57/B57 -> 0.51801698 | K57: =1-J57 -> 0.48198302
A58: Mercedes Benz 900 With Fleetguard Filter | B58: ='15W40'!B58+'T5'!M2 -> 266.99 | C58: =E58+G58+H58 -> 143.916 | E58: ='15W40'!E58 -> 33.476 | F58: ='15W40'!F58 -> 26 | G58: =F58*G4 -> 102.44 | H58: 8 | I58: =B58-C58 -> 123.074 | J58: =C58/B58 -> 0.53903142 | K58: =1-J58 -> 0.46096858
A59: Mercedes Benz Sprinter | B59: ='15W40'!B59+'T5'!M2 -> 244.99 | C59: =E59+G59+H59 -> 102.56 | E59: ='15W40'!E59 -> 0 | F59: ='15W40'!F59 -> 24 | G59: =F59*G4 -> 94.56 | H59: 8 | I59: =B59-C59 -> 142.43 | J59: =C59/B59 -> 0.41862933 | K59: =1-J59 -> 0.58137067
A60: Mitsubushi | B60: ='15W40'!B60+'T5'!M1 -> 244.99 | C60: =E60+G60+H60 -> 132.46 | E60: ='15W40'!E60 -> 73.24 | F60: ='15W40'!F60 -> 13 | G60: =F60*G4 -> 51.22 | H60: 8 | I60: =B60-C60 -> 112.53 | J60: =C60/B60 -> 0.54067513 | K60: =1-J60 -> 0.45932487
A63: Navistar | B63: ='15W40'!B63+'T5'!M2 -> 271.99 | C63: =E63+G63+H63 -> 148.4664 | E63: ='15W40'!E63 -> 38.0264 | F63: ='15W40'!F63 -> 26 | G63: =F63*G4 -> 102.44 | H63: 8 | I63: =B63-C63 -> 123.5236 | J63: =C63/B63 -> 0.54585242 | K63: =1-J63 -> 0.45414758
A65: Paccer | B65: ='15W40'!B65+'T5'!M3 -> 488.99 | C65: =E65+G65+H65 -> 351.29 | E65: ='15W40'!E65 -> 162.05 | F65: ='15W40'!F65 -> 46 | G65: =F65*G4 -> 181.24 | H65: 8 | I65: =B65-C65 -> 137.7 | J65: =C65/B65 -> 0.71839915 | K65: =1-J65 -> 0.28160085
A66: Paccer With Fleetguard | B66: ='15W40'!B66+'T5'!M3 -> 409.99 | C66: =E66+G66+H66 -> 269.0872 | E66: ='15W40'!E66 -> 79.8472 | F66: ='15W40'!F66 -> 46 | G66: =F66*G4 -> 181.24 | H66: 8 | I66: =B66-C66 -> 140.9028 | J66: =C66/B66 -> 0.65632625 | K66: =1-J66 -> 0.34367375
A67: Paccer Small | B67: ='15W40'!B67+'T5'!M2 -> 254.99 | C67: =E67+G67+H67 -> 129.248 | E67: ='15W40'!E67 -> 26.688 | F67: ='15W40'!F67 -> 24 | G67: =F67*G4 -> 94.56 | H67: 8 | I67: =B67-C67 -> 125.742 | J67: =C67/B67 -> 0.50687478 | K67: =1-J67 -> 0.49312522
A69: Volvo With Fleetguard | B69: ='15W40'!B69+'T5'!M2 -> 370.99 | C69: =E69+G69+H69 -> 228.5648 | E69: ='15W40'!E69 -> 86.6048 | F69: ='15W40'!F69 -> 34 | G69: =F69*G4 -> 133.96 | H69: 8 | I69: =B69-C69 -> 142.4252 | J69: =C69/B69 -> 0.61609423 | K69: =1-J69 -> 0.38390577
A70: Volvo With Fleetguard(D16 42L) | B70: ='15W40'!B70+'T5'!M3 -> 409.99 | C70: =E70+G70+H70 -> 260.0848 | E70: ='15W40'!E70 -> 86.6048 | F70: ='15W40'!F70 -> 42 | G70: =F70*G4 -> 165.48 | H70: 8 | I70: =B70-C70 -> 149.9052 | J70: =C70/B70 -> 0.63436864 | K70: =1-J70 -> 0.36563136
A71: Volvo With Fleetguard(D16 52L) | B71: ='15W40'!B71+'T5'!M4 -> 459.99 | C71: =E71+G71+H71 -> 299.4848 | E71: ='15W40'!E71 -> 86.6048 | F71: ='15W40'!F71 -> 52 | G71: =F71*G4 -> 204.88 | H71: 8 | I71: =B71-C71 -> 160.5052 | J71: =C71/B71 -> 0.65106807 | K71: =1-J71 -> 0.34893193
A72: Volvo With Volvo Filter | B72: ='15W40'!B72+'T5'!M2 -> 439.99 | C72: =E72+G72+H72 -> 308.25 | E72: ='15W40'!E72 -> 166.29 | F72: ='15W40'!F72 -> 34 | G72: =F72*G4 -> 133.96 | H72: 8 | I72: =B72-C72 -> 131.74 | J72: =C72/B72 -> 0.7005841 | K72: =1-J72 -> 0.2994159
A73: Volvo With Volvo Filter (D16 42L) | B73: ='15W40'!B73+'T5'!M3 -> 479.99 | C73: =E73+G73+H73 -> 339.77 | E73: ='15W40'!E73 -> 166.29 | F73: ='15W40'!F73 -> 42 | G73: =F73*G4 -> 165.48 | H73: 8 | I73: =B73-C73 -> 140.22 | J73: =C73/B73 -> 0.70786891 | K73: =1-J73 -> 0.29213109
A74: Volvo With Volvo Filter (D16 52L) | B74: ='15W40'!B74+'T5'!M4 -> 527.99 | C74: =E74+G74+H74 -> 379.17 | E74: ='15W40'!E74 -> 166.29 | F74: ='15W40'!F74 -> 52 | G74: =F74*G4 -> 204.88 | H74: 8 | I74: =B74-C74 -> 148.82 | J74: =C74/B74 -> 0.7181386 | K74: =1-J74 -> 0.2818614

Sheet T5 Gallon
A1: STANDARD JOB LIST | B1: T5 Gallon | G1: ='Oil Price'!F9 -> 6.5306667 | H1: 0.05 | L1: 8--20 | M1: 10
B2: selling | C2: cost | E2: Filtre | F2: Litre | G2: Oil | H2: Fuel | I2: Profit | J2: Cost | K2: Profit | L2: 21--38 | M2: 15
E3: Cost | G3: Cost | H3: Grease | L3: 39--46 | M3: 20 | N3: Price Diff | O3: Cost Diff
G4: =G1+H1 -> 6.5806667 | J4: 1 | L4: 47& UP | M4: 25
A6: C 7 / 10 / 3126 With Cat Filter | B6: ='T5'!B6+('T5 Gallon'!G4-'T5'!G4)*'T5 Gallon'!F6+'T5 Gallon'!M2 -> 372.00667 | C6: =E6+G6+H6 -> 225.80667 | E6: ='15W40'!E6 -> 53.29 | F6: ='15W40'!F6 -> 25 | G6: =F6*G4 -> 164.51667 | H6: 8 | I6: =B6-C6 -> 146.2 | J6: =C6/B6 -> 0.60699629 | K6: =1-J6 -> 0.39300371 | N6: =B6-'T5'!B6 -> 81.016667 | O6: =C6-'T5'!C6 -> 66.016667
A7: C 7 / 10 / 3126 With Fleetguard Filter | B7: ='T5'!B7+('T5 Gallon'!G4-'T5'!G4)*'T5 Gallon'!F7+'T5 Gallon'!M2 -> 350.00667 | C7: =E7+G7+H7 -> 194.31587 | E7: ='15W40'!E7 -> 21.7992 | F7: ='15W40'!F7 -> 25 | G7: =F7*G4 -> 164.51667 | H7: 8 | I7: =B7-C7 -> 155.6908 | J7: =C7/B7 -> 0.55517762 | K7: =1-J7 -> 0.44482238 | N7: =B7-'T5'!B7 -> 81.016667 | O7: =C7-'T5'!C7 -> 66.016667
A9: C 12 / 3406 With Cat Filter | B9: ='T5'!B9+('T5 Gallon'!G4-'T5'!G4)*'T5 Gallon'!F9+'T5 Gallon'!M2 -> 475.33533 | C9: =E9+G9+H9 -> 328.64533 | E9: ='15W40'!E9 -> 70.58 | F9: ='15W40'!F9 -> 38 | G9: =F9*G4 -> 250.06533 | H9: 8 | I9: =B9-C9 -> 146.69 | J9: =C9/B9 -> 0.69139681 | K9: =1-J9 -> 0.30860319 | N9: =B9-'T5'!B9 -> 115.34533 | O9: =C9-'T5'!C9 -> 100.34533
A10: C 12 / 3406 With Fleetguard Filter | B10: ='T5'!B10+('T5 Gallon'!G4-'T5'!G4)*'T5 Gallon'!F10+'T5 Gallon'!M2 -> 434.33533 | C10: =E10+G10+H10 -> 289.11013 | E10: ='15W40'!E10 -> 31.0448 | F10: ='15W40'!F10 -> 38 | G10: =F10*G4 -> 250.06533 | H10: 8 | I10: =B10-C10 -> 145.2252 | J10: =C10/B10 -> 0.66563807 | K10: =1-J10 -> 0.33436193 | N10: =B10-'T5'!B10 -> 115.34533 | O10: =C10-'T5'!C10 -> 100.34533
A12: C 13 / 15 With Cat Filter | B12: ='T5'!B12+('T5 Gallon'!G4-'T5'!G4)*'T5 Gallon'!F12+'T5 Gallon'!M3 -> 518.53867 | C12: =E12+G12+H12 -> 361.54867 | E12: ='15W40'!E12 -> 70.58 | F12: ='15W40'!F12 -> 43 | G12: =F12*G4 -> 282.96867 | H12: 8 | I12: =B12-C12 -> 156.99 | J12: =C12/B12 -> 0.69724534 | K12: =1-J12 -> 0.30275466 | N12: =B12-'T5'!B12 -> 133.54867 | O12: =C12-'T5'!C12 -> 113.54867
A13: C 13 / 15 With Fleetguard Filter | B13: ='T5'!B13+('T5 Gallon'!G4-'T5'!G4)*'T5 Gallon'!F13+'T5 Gallon'!M3 -> 477.53867 | C13: =E13+G13+H13 -> 322.01347 | E13: ='15W40'!E13 -> 31.0448 | F13: ='15W40'!F13 -> 43 | G13: =F13*G4 -> 282.96867 | H13: 8 | I13: =B13-C13 -> 155.5252 | J13: =C13/B13 -> 0.67431915 | K13: =1-J13 -> 0.32568085 | N13: =B13-'T5'!B13 -> 133.54867 | O13: =C13-'T5'!C13 -> 113.54867
A15: Cummins N14 | B15: ='T5'!B15+('T5 Gallon'!G4-'T5'!G4)*'T5 Gallon'!F15+'T5 Gallon'!M3 -> 457.61667 | C15: =E15+G15+H15 -> 302.65787 | E15: ='15W40'!E15 -> 31.4312 | F15: ='15W40'!F15 -> 40 | G15: =F15*G4 -> 263.22667 | H15: 8 | I15: =B15-C15 -> 154.9588 | J15: =C15/B15 -> 0.66137859 | K15: =1-J15 -> 0.33862141 | N15: =B15-'T5'!B15 -> 125.62667 | O15: =C15-'T5'!C15 -> 105.62667
A16: Cummins 5.9L/6.7L | B16: ='T5'!B16+('T5 Gallon'!G4-'T5'!G4)*'T5 Gallon'!F16+'T5 Gallon'!M1 -> 232.95933 | C16: =E16+G16+H16 -> 106.84933 | E16: ='15W40'!E16 -> 6.72 | F16: ='15W40'!F16 -> 14 | G16: =F16*G4 -> 92.129333 | H16: 8 | I16: =B16-C16 -> 126.11 | J16: =C16/B16 -> 0.45866088 | K16: =1-J16 -> 0.54133912 | N16: =B16-'T5'!B16 -> 46.969333 | O16: =C16-'T5'!C16 -> 36.969333
A17: Cummins ISC / ISL | B17: ='T5'!B17+('T5 Gallon'!G4-'T5'!G4)*'T5 Gallon'!F17+'T5 Gallon'!M2 -> 364.00667 | C17: =E17+G17+H17 -> 223.32707 | E17: ='15W40'!E17 -> 50.8104 | F17: ='15W40'!F17 -> 25 | G17: =F17*G4 -> 164.51667 | H17: 8 | I17: =B17-C17 -> 140.6796 | J17: =C17/B17 -> 0.61352466 | K17: =1-J17 -> 0.38647534 | N17: =B17-'T5'!B17 -> 81.016667 | O17: =C17-'T5'!C17 -> 66.016667
A18: Cummins ISB | B18: ='T5'!B18+('T5 Gallon'!G4-'T5'!G4)*'T5 Gallon'!F18+'T5 Gallon'!M2 -> 362.00667 | C18: =E18+G18+H18 -> 199.20467 | E18: ='15W40'!E18 -> 26.688 | F18: ='15W40'!F18 -> 25 | G18: =F18*G4 -> 164.51667 | H18: 8 | I18: =B18-C18 -> 162.802 | J18: =C18/B18 -> 0.550279 | K18: =1-J18 -> 0.449721 | N18: =B18-'T5'!B18 -> 81.016667 | O18: =C18-'T5'!C18 -> 66.016667
A19: Cummins ISM | B19: ='T5'!B19+('T5 Gallon'!G4-'T5'!G4)*'T5 Gallon'!F19+'T5 Gallon'!M2 -> 428.054 | C19: =E19+G19+H19 -> 284.7384 | E19: ='15W40'!E19 -> 39.8344 | F19: ='15W40'!F19 -> 36 | G19: =F19*G4 -> 236.904 | H19: 8 | I19: =B19-C19 -> 143.3156 | J19: =C19/B19 -> 0.66519271 | K19: =1-J19 -> 0.33480729 | N19: =B19-'T5'!B19 -> 110.064 | O19: =C19-'T5'!C19 -> 95.064
A20: Cummins ISX | B20: ='T5'!B20+('T5 Gallon'!G4-'T5'!G4)*'T5 Gallon'!F20+'T5 Gallon'!M3 -> 545.17933 | C20: =E20+G20+H20 -> 383.19893 | E20: ='15W40'!E20 -> 85.6496 | F20: ='15W40'!F20 -> 44 | G20: =F20*G4 -> 289.54933 | H20: 8 | I20: =B20-C20 -> 161.9804 | J20: =C20/B20 -> 0.70288602 | K20: =1-J20 -> 0.29711398 | N20: =B20-'T5'!B20 -> 136.18933 | O20: =C20-'T5'!C20 -> 116.18933
A21: Cummins M11 | B21: ='T5'!B21+('T5 Gallon'!G4-'T5'!G4)*'T5 Gallon'!F21+'T5 Gallon'!M2 -> 405.77267 | C21: =E21+G21+H21 -> 263.17387 | E21: ='15W40'!E21 -> 31.4312 | F21: ='15W40'!F21 -> 34 | G21: =F21*G4 -> 223.74267 | H21: 8 | I21: =B21-C21 -> 142.5988 | J21: =C21/B21 -> 0.64857465 | K21: =1-J21 -> 0.35142535 | N21: =B21-'T5'!B21 -> 104.78267 | O21: =C21-'T5'!C21 -> 89.782667
A23: Detroit With Detroit Filter | B23: ='T5'!B23+('T5 Gallon'!G4-'T5'!G4)*'T5 Gallon'!F23+'T5 Gallon'!M2 -> 490.33533 | C23: =E23+G23+H23 -> 335.68533 | E23: ='15W40'!E23 -> 77.62 | F23: ='15W40'!F23 -> 38 | G23: =F23*G4 -> 250.06533 | H23: 8 | I23: =B23-C23 -> 154.65 | J23: =C23/B23 -> 0.6846036 | K23: =1-J23 -> 0.3153964 | N23: =B23-'T5'!B23 -> 115.34533 | O23: =C23-'T5'!C23 -> 100.34533
A24: Detroit With Detroit Filter (DD8) | B24: ='T5'!B24+('T5 Gallon'!G4-'T5'!G4)*'T5 Gallon'!F24+'T5 Gallon'!M2 -> 534.49133 | C24: =E24+G24+H24 -> 387.43133 | E24: ='15W40'!E24 -> 168.85 | F24: ='15W40'!F24 -> 32 | G24: =F24*G4 -> 210.58133 | H24: 8 | I24: =B24-C24 -> 147.06 | J24: =C24/B24 -> 0.7248599 | K24: =1-J24 -> 0.2751401 | N24: =B24-'T5'!B24 -> 99.501333 | O24: =C24-'T5'!C24 -> 84.501333
A25: Detroit With Detroit Filter (DD13,DD15,DD16) | B25: ='T5'!B25+('T5 Gallon'!G4-'T5'!G4)*'T5 Gallon'!F25+'T5 Gallon'!M3 -> 576.898 | C25: =E25+G25+H25 -> 422.178 | E25: ='15W40'!E25 -> 137.79 | F25: ='15W40'!F25 -> 42 | G25: =F25*G4 -> 276.388 | H25: 8 | I25: =B25-C25 -> 154.72 | J25: =C25/B25 -> 0.73180701 | K25: =1-J25 -> 0.26819299 | N25: =B25-'T5'!B25 -> 130.908 | O25: =C25-'T5'!C25 -> 110.908
A26: Detroit With Fleetguard Filter (DD13,DD15.DD16) | B26: ='T5'!B26+('T5 Gallon'!G4-'T5'!G4)*'T5 Gallon'!F26+'T5 Gallon'!M3 -> 554.898 | C26: =E26+G26+H26 -> 398.4408 | E26: ='15W40'!E26 -> 114.0528 | F26: ='15W40'!F26 -> 42 | G26: =F26*G4 -> 276.388 | H26: 8 | I26: =B26-C26 -> 156.4572 | J26: =C26/B26 -> 0.71804332 | K26: =1-J26 -> 0.28195668 | N26: =B26-'T5'!B26 -> 130.908 | O26: =C26-'T5'!C26 -> 110.908
A27: Detroit With Fleetguard | B27: ='T5'!B27+('T5 Gallon'!G4-'T5'!G4)*'T5 Gallon'!F27+'T5 Gallon'!M2 -> 443.33533 | C27: =E27+G27+H27 -> 303.45653 | E27: ='15W40'!E27 -> 45.3912 | F27: ='15W40'!F27 -> 38 | G27: =F27*G4 -> 250.06533 | H27: 8 | I27: =B27-C27 -> 139.8788 | J27: =C27/B27 -> 0.68448533 | K27: =1-J27 -> 0.31551467 | N27: =B27-'T5'!B27 -> 115.34533 | O27: =C27-'T5'!C27 -> 100.34533
A28: Duramax / Vortec 8100L | B28: ='T5'!B28+('T5 Gallon'!G4-'T5'!G4)*'T5 Gallon'!F28+'T5 Gallon'!M1 -> 232.95933 | C28: =E28+G28+H28 -> 110.23173 | E28: ='15W40'!E28 -> 10.1024 | F28: ='15W40'!F28 -> 14 | G28: =F28*G4 -> 92.129333 | H28: 8 | I28: =B28-C28 -> 122.7276 | J28: =C28/B28 -> 0.47318015 | K28: =1-J28 -> 0.52681985 | N28: =B28-'T5'!B28 -> 46.969333 | O28: =C28-'T5'!C28 -> 36.969333
A30: F250 / F350 / F550 / F650 | B30: ='T5'!B30+('T5 Gallon'!G4-'T5'!G4)*'T5 Gallon'!F30+'T5 Gallon'!M1 -> 232.95933 | C30: =E30+G30+H30 -> 114.54613 | E30: ='15W40'!E30 -> 14.4168 | F30: ='15W40'!F30 -> 14 | G30: =F30*G4 -> 92.129333 | H30: 8 | I30: =B30-C30 -> 118.4132 | J30: =C30/B30 -> 0.49170013 | K30: =1-J30 -> 0.50829987 | N30: =B30-'T5'!B30 -> 46.969333 | O30: =C30-'T5'!C30 -> 36.969333
A32: Hino | B32: ='T5'!B32+('T5 Gallon'!G4-'T5'!G4)*'T5 Gallon'!F32+'T5 Gallon'!M1 -> 331.95933 | C32: =E32+G32+H32 -> 196.12933 | E32: ='15W40'!E32 -> 96 | F32: ='15W40'!F32 -> 14 | G32: =F32*G4 -> 92.129333 | H32: 8 | I32: =B32-C32 -> 135.83 | J32: =C32/B32 -> 0.59082337 | K32: =1-J32 -> 0.40917663 | N32: =B32-'T5'!B32 -> 46.969333 | O32: =C32-'T5'!C32 -> 36.969333
A33: Hino With Fleetguard | B33: ='T5'!B33+('T5 Gallon'!G4-'T5'!G4)*'T5 Gallon'!F33+'T5 Gallon'!M1 -> 261.95933 | C33: =E33+G33+H33 -> 127.55093 | E33: ='15W40'!E33 -> 27.4216 | F33: ='15W40'!F33 -> 14 | G33: =F33*G4 -> 92.129333 | H33: 8 | I33: =B33-C33 -> 134.4084 | J33: =C33/B33 -> 0.4869112 | K33: =1-J33 -> 0.5130888 | N33: =B33-'T5'!B33 -> 46.969333 | O33: =C33-'T5'!C33 -> 36.969333
A35: International | B35: ='T5'!B35+('T5 Gallon'!G4-'T5'!G4)*'T5 Gallon'!F35+'T5 Gallon'!M2 -> 374.64733 | C35: =E35+G35+H35 -> 232.66613 | E35: ='15W40'!E35 -> 53.5688 | F35: ='15W40'!F35 -> 26 | G35: =F35*G4 -> 171.09733 | H35: 8 | I35: =B35-C35 -> 141.9812 | J35: =C35/B35 -> 0.62102706 | K35: =1-J35 -> 0.37897294 | N35: =B35-'T5'!B35 -> 83.657333 | O35: =C35-'T5'!C35 -> 68.657333
A36: International S13 | B36: ='T5'!B36+('T5 Gallon'!G4-'T5'!G4)*'T5 Gallon'!F36+'T5 Gallon'!M3 -> 671.46067 | C36: =E36+G36+H36 -> 489.51067 | E36: ='15W40'!E36 -> 178.8 | F36: ='15W40'!F36 -> 46 | G36: =F36*G4 -> 302.71067 | H36: 8 | I36: =B36-C36 -> 181.95 | J36: =C36/B36 -> 0.72902359 | K36: =1-J36 -> 0.27097641 | O36: =C36-'T5'!C36 -> 121.47067
A37: International Vista | B37: ='T5'!B37+('T5 Gallon'!G4-'T5'!G4)*'T5 Gallon'!F37+'T5 Gallon'!M1 -> 311.95933 | C37: =E37+G37+H37 -> 158.00213 | E37: ='15W40'!E37 -> 57.8728 | F37: ='15W40'!F37 -> 14 | G37: =F37*G4 -> 92.129333 | H37: 8 | I37: =B37-C37 -> 153.9572 | J37: =C37/B37 -> 0.50648311 | K37: =1-J37 -> 0.49351689
A38: Isuzu With Fleetguard Filter | B38: ='T5'!B38+('T5 Gallon'!G4-'T5'!G4)*'T5 Gallon'!F38+'T5 Gallon'!M1 -> 277.95933 | C38: =E38+G38+H38 -> 144.27013 | E38: ='15W40'!E38 -> 44.1408 | F38: ='15W40'!F38 -> 14 | G38: =F38*G4 -> 92.129333 | H38: 8 | I38: =B38-C38 -> 133.6892 | J38: =C38/B38 -> 0.51903324 | K38: =1-J38 -> 0.48096676 | N38: =B38-'T5'!B38 -> 46.969333 | O38: =C38-'T5'!C38 -> 36.969333
A39: Isuzu | B39: ='T5'!B39+('T5 Gallon'!G4-'T5'!G4)*'T5 Gallon'!F39+'T5 Gallon'!M1 -> 337.95933 | C39: =E39+G39+H39 -> 169.09933 | E39: ='15W40'!E39 -> 68.97 | F39: ='15W40'!F39 -> 14 | G39: =F39*G4 -> 92.129333 | H39: 8 | I39: =B39-C39 -> 168.86 | J39: =C39/B39 -> 0.50035409 | K39: =1-J39 -> 0.49964591 | O39: =C39-'T5'!C39 -> 36.969333
A41: MP 7 / MP8 With Fleetguard | B41: ='T5'!B41+('T5 Gallon'!G4-'T5'!G4)*'T5 Gallon'!F41+'T5 Gallon'!M2 -> 504.33533 | C41: =E41+G41+H41 -> 344.67013 | E41: ='15W40'!E41 -> 86.6048 | F41: ='15W40'!F41 -> 38 | G41: =F41*G4 -> 250.06533 | H41: 8 | I41: =B41-C41 -> 159.6652 | J41: =C41/B41 -> 0.68341461 | K41: =1-J41 -> 0.31658539 | N41: =B41-'T5'!B41 -> 115.34533 | O41: =C41-'T5'!C41 -> 100.34533
A42: MP 7 / MP8 With Mack | B42: ='T5'!B42+('T5 Gallon'!G4-'T5'!G4)*'T5 Gallon'!F42+'T5 Gallon'!M2 -> 575.33533 | C42: =E42+G42+H42 -> 431.56533 | E42: ='15W40'!E42 -> 173.5 | F42: ='15W40'!F42 -> 38 | G42: =F42*G4 -> 250.06533 | H42: 8 | I42: =B42-C42 -> 143.77 | J42: =C42/B42 -> 0.75011095 | K42: =1-J42 -> 0.24988905 | N42: =B42-'T5'!B42 -> 115.34533 | O42: =C42-'T5'!C42 -> 100.34533
A43: MP 7/MP8/ MP10 With Fleetguard ( 52L) | B43: ='T5'!B43+('T5 Gallon'!G4-'T5'!G4)*'T5 Gallon'!F43+'T5 Gallon'!M3 -> 637.22667 | C43: =E43+G43+H43 -> 456.54147 | E43: ='15W40'!E43 -> 86.6048 | F43: ='15W40'!F43 -> 55 | G43: =F43*G4 -> 361.93667 | H43: 8 | I43: =B43-C43 -> 180.6852 | J43: =C43/B43 -> 0.71645066 | K43: =1-J43 -> 0.28354934 | O43: =C43-'T5'!C43 -> 145.23667
A44: MP 7/MP8/ MP10 With Mack (52L) | B44: ='T5'!B44+('T5 Gallon'!G4-'T5'!G4)*'T5 Gallon'!F44+'T5 Gallon'!M3 -> 710.22667 | C44: =E44+G44+H44 -> 543.43667 | E44: ='15W40'!E44 -> 173.5 | F44: ='15W40'!F44 -> 55 | G44: =F44*G4 -> 361.93667 | H44: 8 | I44: =B44-C44 -> 166.79 | J44: =C44/B44 -> 0.76515948 | K44: =1-J44 -> 0.23484052 | O44: =C44-'T5'!C44 -> 145.23667
A45: Mack With Fleetguard Filter | B45: ='T5'!B45+('T5 Gallon'!G4-'T5'!G4)*'T5 Gallon'!F45+'T5 Gallon'!M2 -> 458.33533 | C45: =E45+G45+H45 -> 308.44933 | E45: ='15W40'!E45 -> 50.384 | F45: ='15W40'!F45 -> 38 | G45: =F45*G4 -> 250.06533 | H45: 8 | I45: =B45-C45 -> 149.886 | J45: =C45/B45 -> 0.67297743 | K45: =1-J45 -> 0.32702257 | N45: =B45-'T5'!B45 -> 115.34533 | O45: =C45-'T5'!C45 -> 100.34533
A46: Mack With Fleetguard Filter(52L) | B46: ='T5'!B46+('T5 Gallon'!G4-'T5'!G4)*'T5 Gallon'!F46+'T5 Gallon'!M4 -> 575.30467 | C46: =E46+G46+H46 -> 400.57867 | E46: ='15W40'!E46 -> 50.384 | F46: ='15W40'!F46 -> 52 | G46: =F46*G4 -> 342.19467 | H46: 8 | I46: =B46-C46 -> 174.726 | J46: =C46/B46 -> 0.69628962 | K46: =1-J46 -> 0.30371038 | N46: =B46-'T5'!B46 -> 162.31467 | O46: =C46-'T5'!C46 -> 137.31467
A47: Mack With Mack Filter | B47: ='T5'!B47+('T5 Gallon'!G4-'T5'!G4)*'T5 Gallon'!F47+'T5 Gallon'!M2 -> 567.33533 | C47: =E47+G47+H47 -> 419.45533 | E47: ='15W40'!E47 -> 161.39 | F47: ='15W40'!F47 -> 38 | G47: =F47*G4 -> 250.06533 | H47: 8 | I47: =B47-C47 -> 147.88 | J47: =C47/B47 -> 0.73934287 | K47: =1-J47 -> 0.26065713 | N47: =B47-'T5'!B47 -> 115.34533 | O47: =C47-'T5'!C47 -> 100.34533
A48: Mack With Mack Filter( 52L ) | B48: ='T5'!B48+('T5 Gallon'!G4-'T5'!G4)*'T5 Gallon'!F48+'T5 Gallon'!M4 -> 687.30467 | C48: =E48+G48+H48 -> 511.58467 | E48: ='15W40'!E48 -> 161.39 | F48: ='15W40'!F48 -> 52 | G48: =F48*G4 -> 342.19467 | H48: 8 | I48: =B48-C48 -> 175.72 | J48: =C48/B48 -> 0.74433463 | K48: =1-J48 -> 0.25566537 | N48: =B48-'T5'!B48 -> 162.31467 | O48: =C48-'T5'!C48 -> 137.31467
A50: Max Force 7 | B50: ='T5'!B50+('T5 Gallon'!G4-'T5'!G4)*'T5 Gallon'!F50+'T5 Gallon'!M2 -> 544.64733 | C50: =E50+G50+H50 -> 401.77733 | E50: ='15W40'!E50 -> 222.68 | F50: ='15W40'!F50 -> 26 | G50: =F50*G4 -> 171.09733 | H50: 8 | I50: =B50-C50 -> 142.87 | J50: =C50/B50 -> 0.73768347 | K50: =1-J50 -> 0.26231653 | N50: =B50-'T5'!B50 -> 83.657333 | O50: =C50-'T5'!C50 -> 68.657333
A51: Max Force 7 With Fleetguard | B51: ='T5'!B51+('T5 Gallon'!G4-'T5'!G4)*'T5 Gallon'!F51+'T5 Gallon'!M2 -> 465.64733 | C51: =E51+G51+H51 -> 324.27333 | E51: ='15W40'!E51 -> 145.176 | F51: ='15W40'!F51 -> 26 | G51: =F51*G4 -> 171.09733 | H51: 8 | I51: =B51-C51 -> 141.374 | J51: =C51/B51 -> 0.69639255 | K51: =1-J51 -> 0.30360745 | N51: =B51-'T5'!B51 -> 83.657333 | O51: =C51-'T5'!C51 -> 68.657333
A52: Max Force 13 | B52: ='T5'!B52+('T5 Gallon'!G4-'T5'!G4)*'T5 Gallon'!F52+'T5 Gallon'!M2 -> 575.33533 | C52: =E52+G52+H52 -> 422.75533 | E52: ='15W40'!E52 -> 164.69 | F52: ='15W40'!F52 -> 38 | G52: =F52*G4 -> 250.06533 | H52: 8 | I52: =B52-C52 -> 152.58 | J52: =C52/B52 -> 0.73479814 | K52: =1-J52 -> 0.26520186 | N52: =B52-'T5'!B52 -> 115.34533 | O52: =C52-'T5'!C52 -> 100.34533
A53: Max Force 13 With Fleetguard | B53: ='T5'!B53+('T5 Gallon'!G4-'T5'!G4)*'T5 Gallon'!F53+'T5 Gallon'!M2 -> 497.33533 | C53: =E53+G53+H53 -> 346.86853 | E53: ='15W40'!E53 -> 88.8032 | F53: ='15W40'!F53 -> 38 | G53: =F53*G4 -> 250.06533 | H53: 8 | I53: =B53-C53 -> 150.4668 | J53: =C53/B53 -> 0.69745403 | K53: =1-J53 -> 0.30254597 | N53: =B53-'T5'!B53 -> 115.34533 | O53: =C53-'T5'!C53 -> 100.34533
A55: Mercedes Benz 4000 | B55: ='T5'!B55+('T5 Gallon'!G4-'T5'!G4)*'T5 Gallon'!F55+'T5 Gallon'!M3 -> 539.10133 | C55: =E55+G55+H55 -> 367.30133 | E55: ='15W40'!E55 -> 50.01 | F55: ='15W40'!F55 -> 47 | G55: =F55*G4 -> 309.29133 | H55: 8 | I55: =B55-C55 -> 171.8 | J55: =C55/B55 -> 0.68132151 | K55: =1-J55 -> 0.31867849 | N55: =B55-'T5'!B55 -> 144.11133 | O55: =C55-'T5'!C55 -> 124.11133
A56: Mercedes Benz 4000 With Fleeguard Filter | B56: ='T5'!B56+('T5 Gallon'!G4-'T5'!G4)*'T5 Gallon'!F56+'T5 Gallon'!M3 -> 517.10133 | C56: =E56+G56+H56 -> 358.73293 | E56: ='15W40'!E56 -> 41.4416 | F56: ='15W40'!F56 -> 47 | G56: =F56*G4 -> 309.29133 | H56: 8 | I56: =B56-C56 -> 158.3684 | J56: =C56/B56 -> 0.69373817 | K56: =1-J56 -> 0.30626183 | N56: =B56-'T5'!B56 -> 144.11133 | O56: =C56-'T5'!C56 -> 124.11133
A57: Mercedes Benz 900 | B57: ='T5'!B57+('T5 Gallon'!G4-'T5'!G4)*'T5 Gallon'!F57+'T5 Gallon'!M2 -> 388.64733 | C57: =E57+G57+H57 -> 226.64733 | E57: ='15W40'!E57 -> 47.55 | F57: ='15W40'!F57 -> 26 | G57: =F57*G4 -> 171.09733 | H57: 8 | I57: =B57-C57 -> 162 | J57: =C57/B57 -> 0.58316966 | K57: =1-J57 -> 0.41683034 | N57: =B57-'T5'!B57 -> 83.657333 | O57: =C57-'T5'!C57 -> 68.657333
A58: Mercedes Benz 900 With Fleetguard Filter | B58: ='T5'!B58+('T5 Gallon'!G4-'T5'!G4)*'T5 Gallon'!F58+'T5 Gallon'!M2 -> 350.64733 | C58: =E58+G58+H58 -> 212.57333 | E58: ='15W40'!E58 -> 33.476 | F58: ='15W40'!F58 -> 26 | G58: =F58*G4 -> 171.09733 | H58: 8 | I58: =B58-C58 -> 138.074 | J58: =C58/B58 -> 0.60623114 | K58: =1-J58 -> 0.39376886 | N58: =B58-'T5'!B58 -> 83.657333 | O58: =C58-'T5'!C58 -> 68.657333
A59: Mercedes Benz Sprinter | B59: ='T5'!B59+('T5 Gallon'!G4-'T5'!G4)*'T5 Gallon'!F59+'T5 Gallon'!M1 -> 318.366 | C59: =E59+G59+H59 -> 165.936 | E59: ='15W40'!E59 -> 0 | F59: ='15W40'!F59 -> 24 | G59: =F59*G4 -> 157.936 | H59: 8 | I59: =B59-C59 -> 152.43 | J59: =C59/B59 -> 0.52121144 | K59: =1-J59 -> 0.47878856 | N59: =B59-'T5'!B59 -> 73.376 | O59: =C59-'T5'!C59 -> 63.376
A60: Mitsubushi | B60: ='T5'!B60+('T5 Gallon'!G4-'T5'!G4)*'T5 Gallon'!F60+'T5 Gallon'!M1 -> 289.31867 | C60: =E60+G60+H60 -> 166.78867 | E60: ='15W40'!E60 -> 73.24 | F60: ='15W40'!F60 -> 13 | G60: =F60*G4 -> 85.548667 | H60: 8 | I60: =B60-C60 -> 122.53 | J60: =C60/B60 -> 0.57648775 | K60: =1-J60 -> 0.42351225 | N60: =B60-'T5'!B60 -> 44.328667 | O60: =C60-'T5'!C60 -> 34.328667
A63: Navistar | B63: ='T5'!B63+('T5 Gallon'!G4-'T5'!G4)*'T5 Gallon'!F63+'T5 Gallon'!M2 -> 355.64733 | C63: =E63+G63+H63 -> 217.12373 | E63: ='15W40'!E63 -> 38.0264 | F63: ='15W40'!F63 -> 26 | G63: =F63*G4 -> 171.09733 | H63: 8 | I63: =B63-C63 -> 138.5236 | J63: =C63/B63 -> 0.61050291 | K63: =1-J63 -> 0.38949709 | N63: =B63-'T5'!B63 -> 83.657333 | O63: =C63-'T5'!C63 -> 68.657333
A65: Paccer | B65: ='T5'!B65+('T5 Gallon'!G4-'T5'!G4)*'T5 Gallon'!F65+'T5 Gallon'!M3 -> 630.46067 | C65: =E65+G65+H65 -> 472.76067 | E65: ='15W40'!E65 -> 162.05 | F65: ='15W40'!F65 -> 46 | G65: =F65*G4 -> 302.71067 | H65: 8 | I65: =B65-C65 -> 157.7 | J65: =C65/B65 -> 0.74986544 | K65: =1-J65 -> 0.25013456 | N65: =B65-'T5'!B65 -> 141.47067 | O65: =C65-'T5'!C65 -> 121.47067
A66: Paccer With Fleetguard | B66: ='T5'!B66+('T5 Gallon'!G4-'T5'!G4)*'T5 Gallon'!F66+'T5 Gallon'!M3 -> 551.46067 | C66: =E66+G66+H66 -> 390.55787 | E66: ='15W40'!E66 -> 79.8472 | F66: ='15W40'!F66 -> 46 | G66: =F66*G4 -> 302.71067 | H66: 8 | I66: =B66-C66 -> 160.9028 | J66: =C66/B66 -> 0.70822434 | K66: =1-J66 -> 0.29177566 | N66: =B66-'T5'!B66 -> 141.47067 | O66: =C66-'T5'!C66 -> 121.47067
A67: Paccer Small | B67: ='T5'!B67+('T5 Gallon'!G4-'T5'!G4)*'T5 Gallon'!F67+'T5 Gallon'!M2 -> 333.366 | C67: =E67+G67+H67 -> 192.624 | E67: ='15W40'!E67 -> 26.688 | F67: ='15W40'!F67 -> 24 | G67: =F67*G4 -> 157.936 | H67: 8 | I67: =B67-C67 -> 140.742 | J67: =C67/B67 -> 0.57781537 | K67: =1-J67 -> 0.42218463 | N67: =B67-'T5'!B67 -> 78.376 | O67: =C67-'T5'!C67 -> 63.376
A69: Volvo With Fleetguard | B69: ='T5'!B69+('T5 Gallon'!G4-'T5'!G4)*'T5 Gallon'!F69+'T5 Gallon'!M2 -> 475.77267 | C69: =E69+G69+H69 -> 318.34747 | E69: ='15W40'!E69 -> 86.6048 | F69: ='15W40'!F69 -> 34 | G69: =F69*G4 -> 223.74267 | H69: 8 | I69: =B69-C69 -> 157.4252 | J69: =C69/B69 -> 0.66911676 | K69: =1-J69 -> 0.33088324 | N69: =B69-'T5'!B69 -> 104.78267 | O69: =C69-'T5'!C69 -> 89.782667
A70: Volvo With Fleetguard(D16 42L) | B70: ='T5'!B70+('T5 Gallon'!G4-'T5'!G4)*'T5 Gallon'!F70+'T5 Gallon'!M3 -> 540.898 | C70: =E70+G70+H70 -> 370.9928 | E70: ='15W40'!E70 -> 86.6048 | F70: ='15W40'!F70 -> 42 | G70: =F70*G4 -> 276.388 | H70: 8 | I70: =B70-C70 -> 169.9052 | J70: =C70/B70 -> 0.68588311 | K70: =1-J70 -> 0.31411689 | N70: =B70-'T5'!B70 -> 130.908 | O70: =C70-'T5'!C70 -> 110.908
A71: Volvo With Fleetguard(D16 52L) | B71: ='T5'!B71+('T5 Gallon'!G4-'T5'!G4)*'T5 Gallon'!F71+'T5 Gallon'!M4 -> 622.30467 | C71: =E71+G71+H71 -> 436.79947 | E71: ='15W40'!E71 -> 86.6048 | F71: ='15W40'!F71 -> 52 | G71: =F71*G4 -> 342.19467 | H71: 8 | I71: =B71-C71 -> 185.5052 | J71: =C71/B71 -> 0.70190614 | K71: =1-J71 -> 0.29809386 | N71: =B71-'T5'!B71 -> 162.31467 | O71: =C71-'T5'!C71 -> 137.31467
A72: Volvo With Volvo Filter | B72: ='T5'!B72+('T5 Gallon'!G4-'T5'!G4)*'T5 Gallon'!F72+'T5 Gallon'!M2 -> 544.77267 | C72: =E72+G72+H72 -> 398.03267 | E72: ='15W40'!E72 -> 166.29 | F72: ='15W40'!F72 -> 34 | G72: =F72*G4 -> 223.74267 | H72: 8 | I72: =B72-C72 -> 146.74 | J72: =C72/B72 -> 0.73063994 | K72: =1-J72 -> 0.26936006 | N72: =B72-'T5'!B72 -> 104.78267 | O72: =C72-'T5'!C72 -> 89.782667
A73: Volvo With Volvo Filter (D16 42L) | B73: ='T5'!B73+('T5 Gallon'!G4-'T5'!G4)*'T5 Gallon'!F73+'T5 Gallon'!M3 -> 610.898 | C73: =E73+G73+H73 -> 450.678 | E73: ='15W40'!E73 -> 166.29 | F73: ='15W40'!F73 -> 42 | G73: =F73*G4 -> 276.388 | H73: 8 | I73: =B73-C73 -> 160.22 | J73: =C73/B73 -> 0.73773036 | K73: =1-J73 -> 0.26226964 | N73: =B73-'T5'!B73 -> 130.908 | O73: =C73-'T5'!C73 -> 110.908
A74: Volvo With Volvo Filter (D16 52L) | B74: ='T5'!B74+('T5 Gallon'!G4-'T5'!G4)*'T5 Gallon'!F74+'T5 Gallon'!M4 -> 690.30467 | C74: =E74+G74+H74 -> 516.48467 | E74: ='15W40'!E74 -> 166.29 | F74: ='15W40'!F74 -> 52 | G74: =F74*G4 -> 342.19467 | H74: 8 | I74: =B74-C74 -> 173.82 | J74: =C74/B74 -> 0.74819814 | K74: =1-J74 -> 0.25180186 | N74: =B74-'T5'!B74 -> 162.31467 | O74: =C74-'T5'!C74 -> 137.31467

Sheet Petro 10W30
A1: STANDARD JOB LIST | B1: Petro | C1: 10W30 | D1: SYN | G1: 3.5 | H1: 0.05 | L1: 8--20 | M1: 15
B2: selling | C2: cost | E2: Filtre | F2: Litre | G2: Oil | H2: Fuel | I2: Profit | J2: Cost | K2: Profit | L2: 21--38 | M2: 25
E3: Cost | G3: Cost | H3: Grease | L3: 39--46 | M3: 30
G4: =G1+H1 -> 3.55 | J4: 1 | L4: 47& UP | M4: 35
A6: C 7 / 10 / 3126 With Cat Filter | B6: ='15W40'!B6+'Petro 10W30'!M2 -> 290.99 | C6: =E6+G6+H6 -> 150.04 | E6: ='15W40'!E6 -> 53.29 | F6: ='15W40'!F6 -> 25 | G6: =F6*G4 -> 88.75 | H6: 8 | I6: =B6-C6 -> 140.95 | J6: =C6/B6 -> 0.51561909 | K6: =1-J6 -> 0.48438091
A7: C 7 / 10 / 3126 With Fleetguard Filter | B7: ='15W40'!B7+'Petro 10W30'!M2 -> 268.99 | C7: =E7+G7+H7 -> 118.5492 | E7: ='15W40'!E7 -> 21.7992 | F7: ='15W40'!F7 -> 25 | G7: =F7*G4 -> 88.75 | H7: 8 | I7: =B7-C7 -> 150.4408 | J7: =C7/B7 -> 0.44071973 | K7: =1-J7 -> 0.55928027
A9: C 12 / 3406 With Cat Filter | B9: ='15W40'!B9+'Petro 10W30'!M2 -> 359.99 | C9: =E9+G9+H9 -> 213.48 | E9: ='15W40'!E9 -> 70.58 | F9: ='15W40'!F9 -> 38 | G9: =F9*G4 -> 134.9 | H9: 8 | I9: =B9-C9 -> 146.51 | J9: =C9/B9 -> 0.59301647 | K9: =1-J9 -> 0.40698353
A10: C 12 / 3406 With Fleetguard Filter | B10: ='15W40'!B10+'Petro 10W30'!M2 -> 318.99 | C10: =E10+G10+H10 -> 173.9448 | E10: ='15W40'!E10 -> 31.0448 | F10: ='15W40'!F10 -> 38 | G10: =F10*G4 -> 134.9 | H10: 8 | I10: =B10-C10 -> 145.0452 | J10: =C10/B10 -> 0.5452986 | K10: =1-J10 -> 0.4547014
A12: C 13 / 15 With Cat Filter | B12: ='15W40'!B12+'Petro 10W30'!M3 -> 384.99 | C12: =E12+G12+H12 -> 231.23 | E12: ='15W40'!E12 -> 70.58 | F12: ='15W40'!F12 -> 43 | G12: =F12*G4 -> 152.65 | H12: 8 | I12: =B12-C12 -> 153.76 | J12: =C12/B12 -> 0.600613 | K12: =1-J12 -> 0.399387
A13: C 13 / 15 With Fleetguard Filter | B13: ='15W40'!B13+'Petro 10W30'!M3 -> 343.99 | C13: =E13+G13+H13 -> 191.6948 | E13: ='15W40'!E13 -> 31.0448 | F13: ='15W40'!F13 -> 43 | G13: =F13*G4 -> 152.65 | H13: 8 | I13: =B13-C13 -> 152.2952 | J13: =C13/B13 -> 0.55726853 | K13: =1-J13 -> 0.44273147
A15: Cummins N14 | B15: ='15W40'!B15+'Petro 10W30'!M3 -> 331.99 | C15: =E15+G15+H15 -> 181.4312 | E15: ='15W40'!E15 -> 31.4312 | F15: ='15W40'!F15 -> 40 | G15: =F15*G4 -> 142 | H15: 8 | I15: =B15-C15 -> 150.5588 | J15: =C15/B15 -> 0.54649598 | K15: =1-J15 -> 0.45350402
A16: Cummins 5.9L/6.7L | B16: ='15W40'!B16+'Petro 10W30'!M1 -> 185.99 | C16: =E16+G16+H16 -> 64.42 | E16: ='15W40'!E16 -> 6.72 | F16: ='15W40'!F16 -> 14 | G16: =F16*G4 -> 49.7 | H16: 8 | I16: =B16-C16 -> 121.57 | J16: =C16/B16 -> 0.34636271 | K16: =1-J16 -> 0.65363729
A17: Cummins ISC / ISL | B17: ='15W40'!B17+'Petro 10W30'!M2 -> 282.99 | C17: =E17+G17+H17 -> 147.5604 | E17: ='15W40'!E17 -> 50.8104 | F17: ='15W40'!F17 -> 25 | G17: =F17*G4 -> 88.75 | H17: 8 | I17: =B17-C17 -> 135.4296 | J17: =C17/B17 -> 0.52143327 | K17: =1-J17 -> 0.47856673
A18: Cummins ISB | B18: ='15W40'!B18+'Petro 10W30'!M2 -> 280.99 | C18: =E18+G18+H18 -> 123.438 | E18: ='15W40'!E18 -> 26.688 | F18: ='15W40'!F18 -> 25 | G18: =F18*G4 -> 88.75 | H18: 8 | I18: =B18-C18 -> 157.552 | J18: =C18/B18 -> 0.43929677 | K18: =1-J18 -> 0.56070323
A19: Cummins ISM | B19: ='15W40'!B19+'Petro 10W30'!M2 -> 317.99 | C19: =E19+G19+H19 -> 175.6344 | E19: ='15W40'!E19 -> 39.8344 | F19: ='15W40'!F19 -> 36 | G19: =F19*G4 -> 127.8 | H19: 8 | I19: =B19-C19 -> 142.3556 | J19: =C19/B19 -> 0.5523268 | K19: =1-J19 -> 0.4476732
A20: Cummins ISX | B20: ='15W40'!B20+'Petro 10W30'!M3 -> 408.99 | C20: =E20+G20+H20 -> 249.8496 | E20: ='15W40'!E20 -> 85.6496 | F20: ='15W40'!F20 -> 44 | G20: =F20*G4 -> 156.2 | H20: 8 | I20: =B20-C20 -> 159.1404 | J20: =C20/B20 -> 0.61089415 | K20: =1-J20 -> 0.38910585
A21: Cummins M11 | B21: ='15W40'!B21+'Petro 10W30'!M2 -> 300.99 | C21: =E21+G21+H21 -> 160.1312 | E21: ='15W40'!E21 -> 31.4312 | F21: ='15W40'!F21 -> 34 | G21: =F21*G4 -> 120.7 | H21: 8 | I21: =B21-C21 -> 140.8588 | J21: =C21/B21 -> 0.53201502 | K21: =1-J21 -> 0.46798498
A23: Detroit With Detroit Filter | B23: ='15W40'!B23+'Petro 10W30'!M2 -> 374.99 | C23: =E23+G23+H23 -> 220.52 | E23: ='15W40'!E23 -> 77.62 | F23: ='15W40'!F23 -> 38 | G23: =F23*G4 -> 134.9 | H23: 8 | I23: =B23-C23 -> 154.47 | J23: =C23/B23 -> 0.58806902 | K23: =1-J23 -> 0.41193098
A24: Detroit With Detroit Filter (DD8) | B24: ='15W40'!B24+'Petro 10W30'!M2 -> 434.99 | C24: =E24+G24+H24 -> 290.45 | E24: ='15W40'!E24 -> 168.85 | F24: ='15W40'!F24 -> 32 | G24: =F24*G4 -> 113.6 | H24: 8 | I24: =B24-C24 -> 144.54 | J24: =C24/B24 -> 0.6677165 | K24: =1-J24 -> 0.3322835
A25: Detroit With Detroit Filter (DD13,DD15,DD16) | B25: ='15W40'!B25+'Petro 10W30'!M3 -> 445.99 | C25: =E25+G25+H25 -> 294.89 | E25: ='15W40'!E25 -> 137.79 | F25: ='15W40'!F25 -> 42 | G25: =F25*G4 -> 149.1 | H25: 8 | I25: =B25-C25 -> 151.1 | J25: =C25/B25 -> 0.66120317 | K25: =1-J25 -> 0.33879683
A26: Detroit With Fleetguard Filter (DD13,DD15.DD16) | B26: ='15W40'!B26+'Petro 10W30'!M3 -> 423.99 | C26: =E26+G26+H26 -> 271.1528 | E26: ='15W40'!E26 -> 114.0528 | F26: ='15W40'!F26 -> 42 | G26: =F26*G4 -> 149.1 | H26: 8 | I26: =B26-C26 -> 152.8372 | J26: =C26/B26 -> 0.6395264 | K26: =1-J26 -> 0.3604736
A27: Detroit With Fleetguard | B27: ='15W40'!B27+'Petro 10W30'!M2 -> 327.99 | C27: =E27+G27+H27 -> 188.2912 | E27: ='15W40'!E27 -> 45.3912 | F27: ='15W40'!F27 -> 38 | G27: =F27*G4 -> 134.9 | H27: 8 | I27: =B27-C27 -> 139.6988 | J27: =C27/B27 -> 0.57407604 | K27: =1-J27 -> 0.42592396
A28: Duramax / Vortec 8100L | B28: ='15W40'!B28+'Petro 10W30'!M1 -> 185.99 | C28: =E28+G28+H28 -> 67.8024 | E28: ='15W40'!E28 -> 10.1024 | F28: ='15W40'!F28 -> 14 | G28: =F28*G4 -> 49.7 | H28: 8 | I28: =B28-C28 -> 118.1876 | J28: =C28/B28 -> 0.36454863 | K28: =1-J28 -> 0.63545137
A30: F250 / F350 / F550 / F650 | B30: ='15W40'!B30+'Petro 10W30'!M1 -> 185.99 | C30: =E30+G30+H30 -> 72.1168 | E30: ='15W40'!E30 -> 14.4168 | F30: ='15W40'!F30 -> 14 | G30: =F30*G4 -> 49.7 | H30: 8 | I30: =B30-C30 -> 113.8732 | J30: =C30/B30 -> 0.38774558 | K30: =1-J30 -> 0.61225442
A32: Hino | B32: ='15W40'!B32+'Petro 10W30'!M1 -> 284.99 | C32: =E32+G32+H32 -> 153.7 | E32: ='15W40'!E32 -> 96 | F32: ='15W40'!F32 -> 14 | G32: =F32*G4 -> 49.7 | H32: 8 | I32: =B32-C32 -> 131.29 | J32: =C32/B32 -> 0.53931717 | K32: =1-J32 -> 0.46068283
A33: Hino With Fleetguard | B33: ='15W40'!B33+'Petro 10W30'!M1 -> 214.99 | C33: =E33+G33+H33 -> 85.1216 | E33: ='15W40'!E33 -> 27.4216 | F33: ='15W40'!F33 -> 14 | G33: =F33*G4 -> 49.7 | H33: 8 | I33: =B33-C33 -> 129.8684 | J33: =C33/B33 -> 0.39593283 | K33: =1-J33 -> 0.60406717
A35: International | B35: ='15W40'!B35+'Petro 10W30'!M2 -> 290.99 | C35: =E35+G35+H35 -> 153.8688 | E35: ='15W40'!E35 -> 53.5688 | F35: ='15W40'!F35 -> 26 | G35: =F35*G4 -> 92.3 | H35: 8 | I35: =B35-C35 -> 137.1212 | J35: =C35/B35 -> 0.52877693 | K35: =1-J35 -> 0.47122307
A36: International S13 | B36: ='15W40'!B36+'Petro 10W30'!M3 -> 529.99 | C36: =E36+G36+H36 -> 350.1 | E36: ='15W40'!E36 -> 178.8 | F36: ='15W40'!F36 -> 46 | G36: =F36*G4 -> 163.3 | H36: 8 | I36: =B36-C36 -> 179.89 | J36: =C36/B36 -> 0.6605785 | K36: =1-J36 -> 0.3394215
A37: International Vista | B37: ='15W40'!B37+'Petro 10W30'!M1 -> 264.99 | C37: =E37+G37+H37 -> 115.5728 | E37: ='15W40'!E37 -> 57.8728 | F37: ='15W40'!F37 -> 14 | G37: =F37*G4 -> 49.7 | H37: 8 | I37: =B37-C37 -> 149.4172 | J37: =C37/B37 -> 0.43614023 | K37: =1-J37 -> 0.56385977
A38: Isuzu With Fleetguard Filter | B38: ='15W40'!B38+'Petro 10W30'!M1 -> 230.99 | C38: =E38+G38+H38 -> 101.8408 | E38: ='15W40'!E38 -> 44.1408 | F38: ='15W40'!F38 -> 14 | G38: =F38*G4 -> 49.7 | H38: 8 | I38: =B38-C38 -> 129.1492 | J38: =C38/B38 -> 0.44088835 | K38: =1-J38 -> 0.55911165
A39: Isuzu | B39: ='15W40'!B39+'Petro 10W30'!M1 -> 290.99 | C39: =E39+G39+H39 -> 126.67 | E39: ='15W40'!E39 -> 68.97 | F39: ='15W40'!F39 -> 14 | G39: =F39*G4 -> 49.7 | H39: 8 | I39: =B39-C39 -> 164.32 | J39: =C39/B39 -> 0.43530706 | K39: =1-J39 -> 0.56469294
A41: MP 7 / MP8 With Fleetguard | B41: ='15W40'!B41+'Petro 10W30'!M2 -> 388.99 | C41: =E41+G41+H41 -> 229.5048 | E41: ='15W40'!E41 -> 86.6048 | F41: ='15W40'!F41 -> 38 | G41: =F41*G4 -> 134.9 | H41: 8 | I41: =B41-C41 -> 159.4852 | J41: =C41/B41 -> 0.5900018 | K41: =1-J41 -> 0.4099982
A42: MP 7 / MP8 With Mack | B42: ='15W40'!B42+'Petro 10W30'!M2 -> 459.99 | C42: =E42+G42+H42 -> 316.4 | E42: ='15W40'!E42 -> 173.5 | F42: ='15W40'!F42 -> 38 | G42: =F42*G4 -> 134.9 | H42: 8 | I42: =B42-C42 -> 143.59 | J42: =C42/B42 -> 0.68784104 | K42: =1-J42 -> 0.31215896
A43: MP 7/MP8/ MP10 With Fleetguard ( 52L) | B43: ='15W40'!B43+'Petro 10W30'!M4 -> 471.99 | C43: =E43+G43+H43 -> 289.8548 | E43: ='15W40'!E43 -> 86.6048 | F43: ='15W40'!F43 -> 55 | G43: =F43*G4 -> 195.25 | H43: 8 | I43: =B43-C43 -> 182.1352 | J43: =C43/B43 -> 0.61411216 | K43: =1-J43 -> 0.38588784
A44: MP 7/MP8/ MP10 With Mack (52L) | B44: ='15W40'!B44+'Petro 10W30'!M4 -> 544.99 | C44: =E44+G44+H44 -> 376.75 | E44: ='15W40'!E44 -> 173.5 | F44: ='15W40'!F44 -> 55 | G44: =F44*G4 -> 195.25 | H44: 8 | I44: =B44-C44 -> 168.24 | J44: =C44/B44 -> 0.69129709 | K44: =1-J44 -> 0.30870291
A45: Mack With Fleetguard Filter | B45: ='15W40'!B45+'Petro 10W30'!M2 -> 342.99 | C45: =E45+G45+H45 -> 193.284 | E45: ='15W40'!E45 -> 50.384 | F45: ='15W40'!F45 -> 38 | G45: =F45*G4 -> 134.9 | H45: 8 | I45: =B45-C45 -> 149.706 | J45: =C45/B45 -> 0.56352663 | K45: =1-J45 -> 0.43647337
A46: Mack With Fleetguard Filter(52L) | B46: ='15W40'!B46+'Petro 10W30'!M4 -> 412.99 | C46: =E46+G46+H46 -> 242.984 | E46: ='15W40'!E46 -> 50.384 | F46: ='15W40'!F46 -> 52 | G46: =F46*G4 -> 184.6 | H46: 8 | I46: =B46-C46 -> 170.006 | J46: =C46/B46 -> 0.58835323 | K46: =1-J46 -> 0.41164677
A47: Mack With Mack Filter | B47: ='15W40'!B47+'Petro 10W30'!M2 -> 451.99 | C47: =E47+G47+H47 -> 304.29 | E47: ='15W40'!E47 -> 161.39 | F47: ='15W40'!F47 -> 38 | G47: =F47*G4 -> 134.9 | H47: 8 | I47: =B47-C47 -> 147.7 | J47: =C47/B47 -> 0.67322286 | K47: =1-J47 -> 0.32677714
A48: Mack With Mack Filter( 52L ) | B48: ='15W40'!B48+'Petro 10W30'!M4 -> 524.99 | C48: =E48+G48+H48 -> 353.99 | E48: ='15W40'!E48 -> 161.39 | F48: ='15W40'!F48 -> 52 | G48: =F48*G4 -> 184.6 | H48: 8 | I48: =B48-C48 -> 171 | J48: =C48/B48 -> 0.67427951 | K48: =1-J48 -> 0.32572049
A50: Max Force 7 | B50: ='15W40'!B50+'Petro 10W30'!M2 -> 460.99 | C50: =E50+G50+H50 -> 322.98 | E50: ='15W40'!E50 -> 222.68 | F50: ='15W40'!F50 -> 26 | G50: =F50*G4 -> 92.3 | H50: 8 | I50: =B50-C50 -> 138.01 | J50: =C50/B50 -> 0.70062257 | K50: =1-J50 -> 0.29937743
A51: Max Force 7 With Fleetguard | B51: ='15W40'!B51+'Petro 10W30'!M2 -> 381.99 | C51: =E51+G51+H51 -> 245.476 | E51: ='15W40'!E51 -> 145.176 | F51: ='15W40'!F51 -> 26 | G51: =F51*G4 -> 92.3 | H51: 8 | I51: =B51-C51 -> 136.514 | J51: =C51/B51 -> 0.64262415 | K51: =1-J51 -> 0.35737585
A52: Max Force 13 | B52: ='15W40'!B52+'Petro 10W30'!M2 -> 459.99 | C52: =E52+G52+H52 -> 307.59 | E52: ='15W40'!E52 -> 164.69 | F52: ='15W40'!F52 -> 38 | G52: =F52*G4 -> 134.9 | H52: 8 | I52: =B52-C52 -> 152.4 | J52: =C52/B52 -> 0.66868845 | K52: =1-J52 -> 0.33131155
A53: Max Force 13 With Fleetguard | B53: ='15W40'!B53+'Petro 10W30'!M2 -> 381.99 | C53: =E53+G53+H53 -> 231.7032 | E53: ='15W40'!E53 -> 88.8032 | F53: ='15W40'!F53 -> 38 | G53: =F53*G4 -> 134.9 | H53: 8 | I53: =B53-C53 -> 150.2868 | J53: =C53/B53 -> 0.60656876 | K53: =1-J53 -> 0.39343124
A55: Mercedes Benz 4000 | B55: ='15W40'!B55+'Petro 10W30'!M3 -> 394.99 | C55: =E55+G55+H55 -> 224.86 | E55: ='15W40'!E55 -> 50.01 | F55: ='15W40'!F55 -> 47 | G55: =F55*G4 -> 166.85 | H55: 8 | I55: =B55-C55 -> 170.13 | J55: =C55/B55 -> 0.56928023 | K55: =1-J55 -> 0.43071977
A56: Mercedes Benz 4000 With Fleeguard Filter | B56: ='15W40'!B56+'Petro 10W30'!M3 -> 372.99 | C56: =E56+G56+H56 -> 216.2916 | E56: ='15W40'!E56 -> 41.4416 | F56: ='15W40'!F56 -> 47 | G56: =F56*G4 -> 166.85 | H56: 8 | I56: =B56-C56 -> 156.6984 | J56: =C56/B56 -> 0.57988579 | K56: =1-J56 -> 0.42011421
A57: Mercedes Benz 900 | B57: ='15W40'!B57+'Petro 10W30'!M2 -> 304.99 | C57: =E57+G57+H57 -> 147.85 | E57: ='15W40'!E57 -> 47.55 | F57: ='15W40'!F57 -> 26 | G57: =F57*G4 -> 92.3 | H57: 8 | I57: =B57-C57 -> 157.14 | J57: =C57/B57 -> 0.48476999 | K57: =1-J57 -> 0.51523001
A58: Mercedes Benz 900 With Fleetguard Filter | B58: ='15W40'!B58+'Petro 10W30'!M2 -> 266.99 | C58: =E58+G58+H58 -> 133.776 | E58: ='15W40'!E58 -> 33.476 | F58: ='15W40'!F58 -> 26 | G58: =F58*G4 -> 92.3 | H58: 8 | I58: =B58-C58 -> 133.214 | J58: =C58/B58 -> 0.50105247 | K58: =1-J58 -> 0.49894753
A59: Mercedes Benz Sprinter | B59: ='15W40'!B59+'Petro 10W30'!M2 -> 244.99 | C59: =E59+G59+H59 -> 93.2 | E59: ='15W40'!E59 -> 0 | F59: ='15W40'!F59 -> 24 | G59: =F59*G4 -> 85.2 | H59: 8 | I59: =B59-C59 -> 151.79 | J59: =C59/B59 -> 0.38042369 | K59: =1-J59 -> 0.61957631
A60: Mitsubushi | B60: ='15W40'!B60+'Petro 10W30'!M1 -> 244.99 | C60: =E60+G60+H60 -> 127.39 | E60: ='15W40'!E60 -> 73.24 | F60: ='15W40'!F60 -> 13 | G60: =F60*G4 -> 46.15 | H60: 8 | I60: =B60-C60 -> 117.6 | J60: =C60/B60 -> 0.51998041 | K60: =1-J60 -> 0.48001959
A63: Navistar | B63: ='15W40'!B63+'Petro 10W30'!M2 -> 271.99 | C63: =E63+G63+H63 -> 138.3264 | E63: ='15W40'!E63 -> 38.0264 | F63: ='15W40'!F63 -> 26 | G63: =F63*G4 -> 92.3 | H63: 8 | I63: =B63-C63 -> 133.6636 | J63: =C63/B63 -> 0.50857164 | K63: =1-J63 -> 0.49142836
A65: Paccer | B65: ='15W40'!B65+'Petro 10W30'!M3 -> 488.99 | C65: =E65+G65+H65 -> 333.35 | E65: ='15W40'!E65 -> 162.05 | F65: ='15W40'!F65 -> 46 | G65: =F65*G4 -> 163.3 | H65: 8 | I65: =B65-C65 -> 155.64 | J65: =C65/B65 -> 0.68171128 | K65: =1-J65 -> 0.31828872
A66: Paccer With Fleetguard | B66: ='15W40'!B66+'Petro 10W30'!M3 -> 409.99 | C66: =E66+G66+H66 -> 251.1472 | E66: ='15W40'!E66 -> 79.8472 | F66: ='15W40'!F66 -> 46 | G66: =F66*G4 -> 163.3 | H66: 8 | I66: =B66-C66 -> 158.8428 | J66: =C66/B66 -> 0.61256909 | K66: =1-J66 -> 0.38743091
A67: Paccer Small | B67: ='15W40'!B67+'Petro 10W30'!M2 -> 254.99 | C67: =E67+G67+H67 -> 119.888 | E67: ='15W40'!E67 -> 26.688 | F67: ='15W40'!F67 -> 24 | G67: =F67*G4 -> 85.2 | H67: 8 | I67: =B67-C67 -> 135.102 | J67: =C67/B67 -> 0.47016746 | K67: =1-J67 -> 0.52983254
A69: Volvo With Fleetguard | B69: ='15W40'!B69+'Petro 10W30'!M2 -> 370.99 | C69: =E69+G69+H69 -> 215.3048 | E69: ='15W40'!E69 -> 86.6048 | F69: ='15W40'!F69 -> 34 | G69: =F69*G4 -> 120.7 | H69: 8 | I69: =B69-C69 -> 155.6852 | J69: =C69/B69 -> 0.58035203 | K69: =1-J69 -> 0.41964797
A70: Volvo With Fleetguard(D16 42L) | B70: ='15W40'!B70+'Petro 10W30'!M3 -> 409.99 | C70: =E70+G70+H70 -> 243.7048 | E70: ='15W40'!E70 -> 86.6048 | F70: ='15W40'!F70 -> 42 | G70: =F70*G4 -> 149.1 | H70: 8 | I70: =B70-C70 -> 166.2852 | J70: =C70/B70 -> 0.59441645 | K70: =1-J70 -> 0.40558355
A71: Volvo With Fleetguard(D16 52L) | B71: ='15W40'!B71+'Petro 10W30'!M4 -> 459.99 | C71: =E71+G71+H71 -> 279.2048 | E71: ='15W40'!E71 -> 86.6048 | F71: ='15W40'!F71 -> 52 | G71: =F71*G4 -> 184.6 | H71: 8 | I71: =B71-C71 -> 180.7852 | J71: =C71/B71 -> 0.60698015 | K71: =1-J71 -> 0.39301985
A72: Volvo With Volvo Filter | B72: ='15W40'!B72+'Petro 10W30'!M2 -> 439.99 | C72: =E72+G72+H72 -> 294.99 | E72: ='15W40'!E72 -> 166.29 | F72: ='15W40'!F72 -> 34 | G72: =F72*G4 -> 120.7 | H72: 8 | I72: =B72-C72 -> 145 | J72: =C72/B72 -> 0.67044706 | K72: =1-J72 -> 0.32955294
A73: Volvo With Volvo Filter (D16 42L) | B73: ='15W40'!B73+'Petro 10W30'!M3 -> 479.99 | C73: =E73+G73+H73 -> 323.39 | E73: ='15W40'!E73 -> 166.29 | F73: ='15W40'!F73 -> 42 | G73: =F73*G4 -> 149.1 | H73: 8 | I73: =B73-C73 -> 156.6 | J73: =C73/B73 -> 0.6737432 | K73: =1-J73 -> 0.3262568
A74: Volvo With Volvo Filter (D16 52L) | B74: ='15W40'!B74+'Petro 10W30'!M4 -> 527.99 | C74: =E74+G74+H74 -> 358.89 | E74: ='15W40'!E74 -> 166.29 | F74: ='15W40'!F74 -> 52 | G74: =F74*G4 -> 184.6 | H74: 8 | I74: =B74-C74 -> 169.1 | J74: =C74/B74 -> 0.67972878 | K74: =1-J74 -> 0.32027122

Sheet Petro 10W30Gallon
A1: STANDARD JOB LIST | B1: Petro | C1: 10W30 Gallon | G1: 4.05 | H1: 0.05 | L1: 8--20 | M1: 10
B2: selling | C2: cost | E2: Filtre | F2: Litre | G2: Oil | H2: Fuel | I2: Profit | J2: Cost | K2: Profit | L2: 21--38 | M2: 15
E3: Cost | G3: Cost | H3: Grease | L3: 39--46 | M3: 20 | N3: Price Diff | O3: Cost Diff
G4: =G1+H1 -> 4.1 | J4: 1 | L4: 47& UP | M4: 25
A6: C 7 / 10 / 3126 With Cat Filter | B6: ='Petro 10W30'!B6+('Petro 10W30Gallon'!G4-'Petro 10W30'!G4)*'Petro 10W30Gallon'!F6+'Petro 10W30Gallon'!M2 -> 319.74 | C6: =E6+G6+H6 -> 163.79 | E6: ='15W40'!E6 -> 53.29 | F6: ='15W40'!F6 -> 25 | G6: =F6*G4 -> 102.5 | H6: 8 | I6: =B6-C6 -> 155.95 | J6: =C6/B6 -> 0.51225996 | K6: =1-J6 -> 0.48774004 | N6: =B6-'T5'!B6 -> 28.75 | O6: =C6-'T5'!C6 -> 4
A7: C 7 / 10 / 3126 With Fleetguard Filter | B7: ='Petro 10W30'!B7+('Petro 10W30Gallon'!G4-'Petro 10W30'!G4)*'Petro 10W30Gallon'!F7+'Petro 10W30Gallon'!M2 -> 297.74 | C7: =E7+G7+H7 -> 132.2992 | E7: ='15W40'!E7 -> 21.7992 | F7: ='15W40'!F7 -> 25 | G7: =F7*G4 -> 102.5 | H7: 8 | I7: =B7-C7 -> 165.4408 | J7: =C7/B7 -> 0.44434473 | K7: =1-J7 -> 0.55565527 | N7: =B7-'T5'!B7 -> 28.75 | O7: =C7-'T5'!C7 -> 4
A9: C 12 / 3406 With Cat Filter | B9: ='Petro 10W30'!B9+('Petro 10W30Gallon'!G4-'Petro 10W30'!G4)*'Petro 10W30Gallon'!F9+'Petro 10W30Gallon'!M2 -> 395.89 | C9: =E9+G9+H9 -> 234.38 | E9: ='15W40'!E9 -> 70.58 | F9: ='15W40'!F9 -> 38 | G9: =F9*G4 -> 155.8 | H9: 8 | I9: =B9-C9 -> 161.51 | J9: =C9/B9 -> 0.59203314 | K9: =1-J9 -> 0.40796686 | N9: =B9-'T5'!B9 -> 35.9 | O9: =C9-'T5'!C9 -> 6.08
A10: C 12 / 3406 With Fleetguard Filter | B10: ='Petro 10W30'!B10+('Petro 10W30Gallon'!G4-'Petro 10W30'!G4)*'Petro 10W30Gallon'!F10+'Petro 10W30Gallon'!M2 -> 354.89 | C10: =E10+G10+H10 -> 194.8448 | E10: ='15W40'!E10 -> 31.0448 | F10: ='15W40'!F10 -> 38 | G10: =F10*G4 -> 155.8 | H10: 8 | I10: =B10-C10 -> 160.0452 | J10: =C10/B10 -> 0.54902871 | K10: =1-J10 -> 0.45097129 | N10: =B10-'T5'!B10 -> 35.9 | O10: =C10-'T5'!C10 -> 6.08
A12: C 13 / 15 With Cat Filter | B12: ='Petro 10W30'!B12+('Petro 10W30Gallon'!G4-'Petro 10W30'!G4)*'Petro 10W30Gallon'!F12+'Petro 10W30Gallon'!M3 -> 428.64 | C12: =E12+G12+H12 -> 254.88 | E12: ='15W40'!E12 -> 70.58 | F12: ='15W40'!F12 -> 43 | G12: =F12*G4 -> 176.3 | H12: 8 | I12: =B12-C12 -> 173.76 | J12: =C12/B12 -> 0.59462486 | K12: =1-J12 -> 0.40537514 | N12: =B12-'T5'!B12 -> 43.65 | O12: =C12-'T5'!C12 -> 6.88
A13: C 13 / 15 With Fleetguard Filter | B13: ='Petro 10W30'!B13+('Petro 10W30Gallon'!G4-'Petro 10W30'!G4)*'Petro 10W30Gallon'!F13+'Petro 10W30Gallon'!M3 -> 387.64 | C13: =E13+G13+H13 -> 215.3448 | E13: ='15W40'!E13 -> 31.0448 | F13: ='15W40'!F13 -> 43 | G13: =F13*G4 -> 176.3 | H13: 8 | I13: =B13-C13 -> 172.2952 | J13: =C13/B13 -> 0.55552781 | K13: =1-J13 -> 0.44447219 | N13: =B13-'T5'!B13 -> 43.65 | O13: =C13-'T5'!C13 -> 6.88
A15: Cummins N14 | B15: ='Petro 10W30'!B15+('Petro 10W30Gallon'!G4-'Petro 10W30'!G4)*'Petro 10W30Gallon'!F15+'Petro 10W30Gallon'!M3 -> 373.99 | C15: =E15+G15+H15 -> 203.4312 | E15: ='15W40'!E15 -> 31.4312 | F15: ='15W40'!F15 -> 40 | G15: =F15*G4 -> 164 | H15: 8 | I15: =B15-C15 -> 170.5588 | J15: =C15/B15 -> 0.54394823 | K15: =1-J15 -> 0.45605177 | N15: =B15-'T5'!B15 -> 42 | O15: =C15-'T5'!C15 -> 6.4
A16: Cummins 5.9L/6.7L | B16: ='Petro 10W30'!B16+('Petro 10W30Gallon'!G4-'Petro 10W30'!G4)*'Petro 10W30Gallon'!F16+'Petro 10W30Gallon'!M1 -> 203.69 | C16: =E16+G16+H16 -> 72.12 | E16: ='15W40'!E16 -> 6.72 | F16: ='15W40'!F16 -> 14 | G16: =F16*G4 -> 57.4 | H16: 8 | I16: =B16-C16 -> 131.57 | J16: =C16/B16 -> 0.35406746 | K16: =1-J16 -> 0.64593254 | N16: =B16-'T5'!B16 -> 17.7 | O16: =C16-'T5'!C16 -> 2.24
A17: Cummins ISC / ISL | B17: ='Petro 10W30'!B17+('Petro 10W30Gallon'!G4-'Petro 10W30'!G4)*'Petro 10W30Gallon'!F17+'Petro 10W30Gallon'!M2 -> 311.74 | C17: =E17+G17+H17 -> 161.3104 | E17: ='15W40'!E17 -> 50.8104 | F17: ='15W40'!F17 -> 25 | G17: =F17*G4 -> 102.5 | H17: 8 | I17: =B17-C17 -> 150.4296 | J17: =C17/B17 -> 0.51745172 | K17: =1-J17 -> 0.48254828 | N17: =B17-'T5'!B17 -> 28.75 | O17: =C17-'T5'!C17 -> 4
A18: Cummins ISB | B18: ='Petro 10W30'!B18+('Petro 10W30Gallon'!G4-'Petro 10W30'!G4)*'Petro 10W30Gallon'!F18+'Petro 10W30Gallon'!M2 -> 309.74 | C18: =E18+G18+H18 -> 137.188 | E18: ='15W40'!E18 -> 26.688 | F18: ='15W40'!F18 -> 25 | G18: =F18*G4 -> 102.5 | H18: 8 | I18: =B18-C18 -> 172.552 | J18: =C18/B18 -> 0.44291341 | K18: =1-J18 -> 0.55708659 | N18: =B18-'T5'!B18 -> 28.75 | O18: =C18-'T5'!C18 -> 4
A19: Cummins ISM | B19: ='Petro 10W30'!B19+('Petro 10W30Gallon'!G4-'Petro 10W30'!G4)*'Petro 10W30Gallon'!F19+'Petro 10W30Gallon'!M2 -> 352.79 | C19: =E19+G19+H19 -> 195.4344 | E19: ='15W40'!E19 -> 39.8344 | F19: ='15W40'!F19 -> 36 | G19: =F19*G4 -> 147.6 | H19: 8 | I19: =B19-C19 -> 157.3556 | J19: =C19/B19 -> 0.55396808 | K19: =1-J19 -> 0.44603192 | N19: =B19-'T5'!B19 -> 34.8 | O19: =C19-'T5'!C19 -> 5.76
A20: Cummins ISX | B20: ='Petro 10W30'!B20+('Petro 10W30Gallon'!G4-'Petro 10W30'!G4)*'Petro 10W30Gallon'!F20+'Petro 10W30Gallon'!M3 -> 453.19 | C20: =E20+G20+H20 -> 274.0496 | E20: ='15W40'!E20 -> 85.6496 | F20: ='15W40'!F20 -> 44 | G20: =F20*G4 -> 180.4 | H20: 8 | I20: =B20-C20 -> 179.1404 | J20: =C20/B20 -> 0.60471237 | K20: =1-J20 -> 0.39528763 | N20: =B20-'T5'!B20 -> 44.2 | O20: =C20-'T5'!C20 -> 7.04
A21: Cummins M11 | B21: ='Petro 10W30'!B21+('Petro 10W30Gallon'!G4-'Petro 10W30'!G4)*'Petro 10W30Gallon'!F21+'Petro 10W30Gallon'!M2 -> 334.69 | C21: =E21+G21+H21 -> 178.8312 | E21: ='15W40'!E21 -> 31.4312 | F21: ='15W40'!F21 -> 34 | G21: =F21*G4 -> 139.4 | H21: 8 | I21: =B21-C21 -> 155.8588 | J21: =C21/B21 -> 0.53431892 | K21: =1-J21 -> 0.46568108 | N21: =B21-'T5'!B21 -> 33.7 | O21: =C21-'T5'!C21 -> 5.44
A23: Detroit With Detroit Filter | B23: ='Petro 10W30'!B23+('Petro 10W30Gallon'!G4-'Petro 10W30'!G4)*'Petro 10W30Gallon'!F23+'Petro 10W30Gallon'!M2 -> 410.89 | C23: =E23+G23+H23 -> 241.42 | E23: ='15W40'!E23 -> 77.62 | F23: ='15W40'!F23 -> 38 | G23: =F23*G4 -> 155.8 | H23: 8 | I23: =B23-C23 -> 169.47 | J23: =C23/B23 -> 0.58755385 | K23: =1-J23 -> 0.41244615 | N23: =B23-'T5'!B23 -> 35.9 | O23: =C23-'T5'!C23 -> 6.08
A24: Detroit With Detroit Filter (DD8) | B24: ='Petro 10W30'!B24+('Petro 10W30Gallon'!G4-'Petro 10W30'!G4)*'Petro 10W30Gallon'!F24+'Petro 10W30Gallon'!M2 -> 467.59 | C24: =E24+G24+H24 -> 308.05 | E24: ='15W40'!E24 -> 168.85 | F24: ='15W40'!F24 -> 32 | G24: =F24*G4 -> 131.2 | H24: 8 | I24: =B24-C24 -> 159.54 | J24: =C24/B24 -> 0.65880365 | K24: =1-J24 -> 0.34119635 | N24: =B24-'T5'!B24 -> 32.6 | O24: =C24-'T5'!C24 -> 5.12
A25: Detroit With Detroit Filter (DD13,DD15,DD16) | B25: ='Petro 10W30'!B25+('Petro 10W30Gallon'!G4-'Petro 10W30'!G4)*'Petro 10W30Gallon'!F25+'Petro 10W30Gallon'!M3 -> 489.09 | C25: =E25+G25+H25 -> 317.99 | E25: ='15W40'!E25 -> 137.79 | F25: ='15W40'!F25 -> 42 | G25: =F25*G4 -> 172.2 | H25: 8 | I25: =B25-C25 -> 171.1 | J25: =C25/B25 -> 0.65016664 | K25: =1-J25 -> 0.34983336 | N25: =B25-'T5'!B25 -> 43.1 | O25: =C25-'T5'!C25 -> 6.72
A26: Detroit With Fleetguard Filter (DD13,DD15.DD16) | B26: ='Petro 10W30'!B26+('Petro 10W30Gallon'!G4-'Petro 10W30'!G4)*'Petro 10W30Gallon'!F26+'Petro 10W30Gallon'!M3 -> 467.09 | C26: =E26+G26+H26 -> 294.2528 | E26: ='15W40'!E26 -> 114.0528 | F26: ='15W40'!F26 -> 42 | G26: =F26*G4 -> 172.2 | H26: 8 | I26: =B26-C26 -> 172.8372 | J26: =C26/B26 -> 0.62997024 | K26: =1-J26 -> 0.37002976 | N26: =B26-'T5'!B26 -> 43.1 | O26: =C26-'T5'!C26 -> 6.72
A27: Detroit With Fleetguard | B27: ='Petro 10W30'!B27+('Petro 10W30Gallon'!G4-'Petro 10W30'!G4)*'Petro 10W30Gallon'!F27+'Petro 10W30Gallon'!M2 -> 363.89 | C27: =E27+G27+H27 -> 209.1912 | E27: ='15W40'!E27 -> 45.3912 | F27: ='15W40'!F27 -> 38 | G27: =F27*G4 -> 155.8 | H27: 8 | I27: =B27-C27 -> 154.6988 | J27: =C27/B27 -> 0.57487482 | K27: =1-J27 -> 0.42512518 | N27: =B27-'T5'!B27 -> 35.9 | O27: =C27-'T5'!C27 -> 6.08
A28: Duramax / Vortec 8100L | B28: ='Petro 10W30'!B28+('Petro 10W30Gallon'!G4-'Petro 10W30'!G4)*'Petro 10W30Gallon'!F28+'Petro 10W30Gallon'!M1 -> 203.69 | C28: =E28+G28+H28 -> 75.5024 | E28: ='15W40'!E28 -> 10.1024 | F28: ='15W40'!F28 -> 14 | G28: =F28*G4 -> 57.4 | H28: 8 | I28: =B28-C28 -> 128.1876 | J28: =C28/B28 -> 0.37067308 | K28: =1-J28 -> 0.62932692 | N28: =B28-'T5'!B28 -> 17.7 | O28: =C28-'T5'!C28 -> 2.24
A30: F250 / F350 / F550 / F650 | B30: ='Petro 10W30'!B30+('Petro 10W30Gallon'!G4-'Petro 10W30'!G4)*'Petro 10W30Gallon'!F30+'Petro 10W30Gallon'!M1 -> 203.69 | C30: =E30+G30+H30 -> 79.8168 | E30: ='15W40'!E30 -> 14.4168 | F30: ='15W40'!F30 -> 14 | G30: =F30*G4 -> 57.4 | H30: 8 | I30: =B30-C30 -> 123.8732 | J30: =C30/B30 -> 0.39185429 | K30: =1-J30 -> 0.60814571 | N30: =B30-'T5'!B30 -> 17.7 | O30: =C30-'T5'!C30 -> 2.24
A32: Hino | B32: ='Petro 10W30'!B32+('Petro 10W30Gallon'!G4-'Petro 10W30'!G4)*'Petro 10W30Gallon'!F32+'Petro 10W30Gallon'!M1 -> 302.69 | C32: =E32+G32+H32 -> 161.4 | E32: ='15W40'!E32 -> 96 | F32: ='15W40'!F32 -> 14 | G32: =F32*G4 -> 57.4 | H32: 8 | I32: =B32-C32 -> 141.29 | J32: =C32/B32 -> 0.5332188 | K32: =1-J32 -> 0.4667812 | N32: =B32-'T5'!B32 -> 17.7 | O32: =C32-'T5'!C32 -> 2.24
A33: Hino With Fleetguard | B33: ='Petro 10W30'!B33+('Petro 10W30Gallon'!G4-'Petro 10W30'!G4)*'Petro 10W30Gallon'!F33+'Petro 10W30Gallon'!M1 -> 232.69 | C33: =E33+G33+H33 -> 92.8216 | E33: ='15W40'!E33 -> 27.4216 | F33: ='15W40'!F33 -> 14 | G33: =F33*G4 -> 57.4 | H33: 8 | I33: =B33-C33 -> 139.8684 | J33: =C33/B33 -> 0.3989067 | K33: =1-J33 -> 0.6010933 | N33: =B33-'T5'!B33 -> 17.7 | O33: =C33-'T5'!C33 -> 2.24
A35: International | B35: ='Petro 10W30'!B35+('Petro 10W30Gallon'!G4-'Petro 10W30'!G4)*'Petro 10W30Gallon'!F35+'Petro 10W30Gallon'!M2 -> 320.29 | C35: =E35+G35+H35 -> 168.1688 | E35: ='15W40'!E35 -> 53.5688 | F35: ='15W40'!F35 -> 26 | G35: =F35*G4 -> 106.6 | H35: 8 | I35: =B35-C35 -> 152.1212 | J35: =C35/B35 -> 0.52505167 | K35: =1-J35 -> 0.47494833 | N35: =B35-'T5'!B35 -> 29.3 | O35: =C35-'T5'!C35 -> 4.16
A36: International S13 | B36: ='Petro 10W30'!B36+('Petro 10W30Gallon'!G4-'Petro 10W30'!G4)*'Petro 10W30Gallon'!F36+'Petro 10W30Gallon'!M3 -> 575.29 | C36: =E36+G36+H36 -> 375.4 | E36: ='15W40'!E36 -> 178.8 | F36: ='15W40'!F36 -> 46 | G36: =F36*G4 -> 188.6 | H36: 8 | I36: =B36-C36 -> 199.89 | J36: =C36/B36 -> 0.65254046 | K36: =1-J36 -> 0.34745954 | O36: =C36-'T5'!C36 -> 7.36
A37: International Vista | B37: ='Petro 10W30'!B37+('Petro 10W30Gallon'!G4-'Petro 10W30'!G4)*'Petro 10W30Gallon'!F37+'Petro 10W30Gallon'!M1 -> 282.69 | C37: =E37+G37+H37 -> 123.2728 | E37: ='15W40'!E37 -> 57.8728 | F37: ='15W40'!F37 -> 14 | G37: =F37*G4 -> 57.4 | H37: 8 | I37: =B37-C37 -> 159.4172 | J37: =C37/B37 -> 0.43607061 | K37: =1-J37 -> 0.56392939
A38: Isuzu With Fleetguard Filter | B38: ='Petro 10W30'!B38+('Petro 10W30Gallon'!G4-'Petro 10W30'!G4)*'Petro 10W30Gallon'!F38+'Petro 10W30Gallon'!M1 -> 248.69 | C38: =E38+G38+H38 -> 109.5408 | E38: ='15W40'!E38 -> 44.1408 | F38: ='15W40'!F38 -> 14 | G38: =F38*G4 -> 57.4 | H38: 8 | I38: =B38-C38 -> 139.1492 | J38: =C38/B38 -> 0.44047127 | K38: =1-J38 -> 0.55952873 | N38: =B38-'T5'!B38 -> 17.7 | O38: =C38-'T5'!C38 -> 2.24
A39: Isuzu | B39: ='Petro 10W30'!B39+('Petro 10W30Gallon'!G4-'Petro 10W30'!G4)*'Petro 10W30Gallon'!F39+'Petro 10W30Gallon'!M1 -> 308.69 | C39: =E39+G39+H39 -> 134.37 | E39: ='15W40'!E39 -> 68.97 | F39: ='15W40'!F39 -> 14 | G39: =F39*G4 -> 57.4 | H39: 8 | I39: =B39-C39 -> 174.32 | J39: =C39/B39 -> 0.43529107 | K39: =1-J39 -> 0.56470893 | O39: =C39-'T5'!C39 -> 2.24
A41: MP 7 / MP8 With Fleetguard | B41: ='Petro 10W30'!B41+('Petro 10W30Gallon'!G4-'Petro 10W30'!G4)*'Petro 10W30Gallon'!F41+'Petro 10W30Gallon'!M2 -> 424.89 | C41: =E41+G41+H41 -> 250.4048 | E41: ='15W40'!E41 -> 86.6048 | F41: ='15W40'!F41 -> 38 | G41: =F41*G4 -> 155.8 | H41: 8 | I41: =B41-C41 -> 174.4852 | J41: =C41/B41 -> 0.5893403 | K41: =1-J41 -> 0.4106597 | N41: =B41-'T5'!B41 -> 35.9 | O41: =C41-'T5'!C41 -> 6.08
A42: MP 7 / MP8 With Mack | B42: ='Petro 10W30'!B42+('Petro 10W30Gallon'!G4-'Petro 10W30'!G4)*'Petro 10W30Gallon'!F42+'Petro 10W30Gallon'!M2 -> 495.89 | C42: =E42+G42+H42 -> 337.3 | E42: ='15W40'!E42 -> 173.5 | F42: ='15W40'!F42 -> 38 | G42: =F42*G4 -> 155.8 | H42: 8 | I42: =B42-C42 -> 158.59 | J42: =C42/B42 -> 0.68019117 | K42: =1-J42 -> 0.31980883 | N42: =B42-'T5'!B42 -> 35.9 | O42: =C42-'T5'!C42 -> 6.08
A43: MP 7/MP8/ MP10 With Fleetguard ( 52L) | B43: ='Petro 10W30'!B43+('Petro 10W30Gallon'!G4-'Petro 10W30'!G4)*'Petro 10W30Gallon'!F43+'Petro 10W30Gallon'!M4 -> 527.24 | C43: =E43+G43+H43 -> 320.1048 | E43: ='15W40'!E43 -> 86.6048 | F43: ='15W40'!F43 -> 55 | G43: =F43*G4 -> 225.5 | H43: 8 | I43: =B43-C43 -> 207.1352 | J43: =C43/B43 -> 0.60713299 | K43: =1-J43 -> 0.39286701 | O43: =C43-'T5'!C43 -> 8.8
